{"TrainCount": 1, "MeanTrainLoss": 4.103001294981146, "MeanValidationLoss": 5.492300238530591, "FinalMeanRMSE": -1}
{"TrainCount": 1, "MeanTrainLoss": 11.992622303291105, "MeanValidationLoss": 10.543398299307194, "FinalMeanRMSE": -1}
{"TrainCount": 1, "MeanTrainLoss": 12.784453625970043, "MeanValidationLoss": 14.823362890279517, "FinalMeanRMSE": -1}
{"TrainCount": 1, "MeanTrainLoss": 18.17492158647994, "MeanValidationLoss": 31.12148015004284, "FinalMeanRMSE": -1}
{"TrainCount": 1, "MeanTrainLoss": 21.77025442839788, "MeanValidationLoss": 20.668486397221404, "FinalMeanRMSE": -1}
{"TrainCount": 1, "MeanTrainLoss": 20.318525830764727, "MeanValidationLoss": 0.05671209096908569, "FinalMeanRMSE": -1}
{"TrainCount": 1, "MeanTrainLoss": 1.7438445024087394, "MeanValidationLoss": 2.9042298816285044, "FinalMeanRMSE": -1}
{"TrainCount": 1, "MeanTrainLoss": 2.2753616230028895, "MeanValidationLoss": 4.521889884516878, "FinalMeanRMSE": -1}
{"TrainCount": 1, "MeanTrainLoss": 4.152713510352121, "MeanValidationLoss": 4.04974616698499, "FinalMeanRMSE": -1}
{"TrainCount": 1, "MeanTrainLoss": 2.796873557735497, "MeanValidationLoss": 1.128628134727478, "FinalMeanRMSE": -1}
{"TrainCount": 1, "MeanTrainLoss": 1.3040855307954018, "MeanValidationLoss": 0.30230165989893787, "FinalMeanRMSE": -1}
{"TrainCount": 1, "MeanTrainLoss": 0.20207630013915853, "MeanValidationLoss": 0.19199679679465745, "FinalMeanRMSE": -1}
{"TrainCount": 1, "MeanTrainLoss": 0.47167899630998783, "MeanValidationLoss": 0.25908272333864896, "FinalMeanRMSE": -1}
{"TrainCount": 1, "MeanTrainLoss": 0.23694386938368212, "MeanValidationLoss": 0.1969129558441774, "FinalMeanRMSE": -1}
{"TrainCount": 1, "MeanTrainLoss": 0.8213300766519538, "MeanValidationLoss": 0.49335047883807487, "FinalMeanRMSE": 0.49335045188445525}
{"TrainCount": 2, "MeanTrainLoss": 0.28357545777434917, "MeanValidationLoss": 0.14553942816594512, "FinalMeanRMSE": -1}
{"TrainCount": 2, "MeanTrainLoss": 0.09079541870731737, "MeanValidationLoss": 0.17658350090983285, "FinalMeanRMSE": -1}
{"TrainCount": 2, "MeanTrainLoss": 0.07850996093023521, "MeanValidationLoss": 0.1384790339031998, "FinalMeanRMSE": -1}
{"TrainCount": 2, "MeanTrainLoss": 0.09005550570008712, "MeanValidationLoss": 0.07593585946121995, "FinalMeanRMSE": -1}
{"TrainCount": 2, "MeanTrainLoss": 0.0398802866652115, "MeanValidationLoss": 0.12044754687162729, "FinalMeanRMSE": -1}
{"TrainCount": 2, "MeanTrainLoss": 0.050183329446852665, "MeanValidationLoss": 0.2217364104426637, "FinalMeanRMSE": -1}
{"TrainCount": 2, "MeanTrainLoss": 0.07435334811304666, "MeanValidationLoss": 0.10853745590667335, "FinalMeanRMSE": -1}
{"TrainCount": 2, "MeanTrainLoss": 0.09788937362399114, "MeanValidationLoss": 0.08948361980063575, "FinalMeanRMSE": -1}
{"TrainCount": 2, "MeanTrainLoss": 0.04214035757549543, "MeanValidationLoss": 0.17236408794551794, "FinalMeanRMSE": -1}
{"TrainCount": 2, "MeanTrainLoss": 0.05385169033292899, "MeanValidationLoss": 0.09877279999829848, "FinalMeanRMSE": -1}
{"TrainCount": 2, "MeanTrainLoss": 0.059837496585897515, "MeanValidationLoss": 0.06261260050740354, "FinalMeanRMSE": -1}
{"TrainCount": 2, "MeanTrainLoss": 0.037001629120672626, "MeanValidationLoss": 0.06965847191761951, "FinalMeanRMSE": -1}
{"TrainCount": 2, "MeanTrainLoss": 0.03834665778066972, "MeanValidationLoss": 0.11269936292451255, "FinalMeanRMSE": -1}
{"TrainCount": 2, "MeanTrainLoss": 0.0405777244598773, "MeanValidationLoss": 0.1691871559133335, "FinalMeanRMSE": -1}
{"TrainCount": 2, "MeanTrainLoss": 0.07697767580435173, "MeanValidationLoss": 0.07367359659429913, "FinalMeanRMSE": 0.07367359713686523}
{"TrainCount": 3, "MeanTrainLoss": 0.06481488044909407, "MeanValidationLoss": 0.11264582133266778, "FinalMeanRMSE": -1}
{"TrainCount": 3, "MeanTrainLoss": 0.0858461669506093, "MeanValidationLoss": 0.09426852480500145, "FinalMeanRMSE": -1}
{"TrainCount": 3, "MeanTrainLoss": 0.04577769217106093, "MeanValidationLoss": 0.05804897712922729, "FinalMeanRMSE": -1}
{"TrainCount": 3, "MeanTrainLoss": 0.05001810252402736, "MeanValidationLoss": 0.09668783800659982, "FinalMeanRMSE": -1}
{"TrainCount": 3, "MeanTrainLoss": 0.06176098187215033, "MeanValidationLoss": 0.05501886213247755, "FinalMeanRMSE": -1}
{"TrainCount": 3, "MeanTrainLoss": 0.05286438981549139, "MeanValidationLoss": 0.05243764059469763, "FinalMeanRMSE": -1}
{"TrainCount": 3, "MeanTrainLoss": 0.04124389386084755, "MeanValidationLoss": 0.05577127538225819, "FinalMeanRMSE": -1}
{"TrainCount": 3, "MeanTrainLoss": 0.04530064847353285, "MeanValidationLoss": 0.08168918731729541, "FinalMeanRMSE": -1}
{"TrainCount": 3, "MeanTrainLoss": 0.053148280664355355, "MeanValidationLoss": 0.05564663371285506, "FinalMeanRMSE": -1}
{"TrainCount": 3, "MeanTrainLoss": 0.04876640303043929, "MeanValidationLoss": 0.05121498897803568, "FinalMeanRMSE": -1}
{"TrainCount": 3, "MeanTrainLoss": 0.03894255724859185, "MeanValidationLoss": 0.0523697253547411, "FinalMeanRMSE": -1}
{"TrainCount": 3, "MeanTrainLoss": 0.041779680012733536, "MeanValidationLoss": 0.06953929424022151, "FinalMeanRMSE": -1}
{"TrainCount": 3, "MeanTrainLoss": 0.04621314044745095, "MeanValidationLoss": 0.06053742482862641, "FinalMeanRMSE": -1}
{"TrainCount": 3, "MeanTrainLoss": 0.04771669462850663, "MeanValidationLoss": 0.0502438613798766, "FinalMeanRMSE": -1}
{"TrainCount": 3, "MeanTrainLoss": 0.03825084989544301, "MeanValidationLoss": 0.05043994074901648, "FinalMeanRMSE": 0.05043994085114835}
{"TrainCount": 4, "MeanTrainLoss": 0.05725295054912567, "MeanValidationLoss": 0.05188110903386147, "FinalMeanRMSE": -1}
{"TrainCount": 4, "MeanTrainLoss": 0.053872079312801364, "MeanValidationLoss": 0.0539189170925848, "FinalMeanRMSE": -1}
{"TrainCount": 4, "MeanTrainLoss": 0.04672260528802872, "MeanValidationLoss": 0.05300860443422871, "FinalMeanRMSE": -1}
{"TrainCount": 4, "MeanTrainLoss": 0.04706926393508911, "MeanValidationLoss": 0.057471219810747334, "FinalMeanRMSE": -1}
{"TrainCount": 4, "MeanTrainLoss": 0.05065117311477661, "MeanValidationLoss": 0.05200887038823097, "FinalMeanRMSE": -1}
{"TrainCount": 4, "MeanTrainLoss": 0.049189754605293276, "MeanValidationLoss": 0.05277406808830077, "FinalMeanRMSE": -1}
{"TrainCount": 4, "MeanTrainLoss": 0.044959394812583924, "MeanValidationLoss": 0.0521976538002491, "FinalMeanRMSE": -1}
{"TrainCount": 4, "MeanTrainLoss": 0.045449337661266326, "MeanValidationLoss": 0.05323456191728192, "FinalMeanRMSE": -1}
{"TrainCount": 4, "MeanTrainLoss": 0.04709932947158813, "MeanValidationLoss": 0.05207501087457903, "FinalMeanRMSE": -1}
{"TrainCount": 4, "MeanTrainLoss": 0.04614870464801788, "MeanValidationLoss": 0.05239479195687079, "FinalMeanRMSE": -1}
{"TrainCount": 4, "MeanTrainLoss": 0.044374731838703156, "MeanValidationLoss": 0.05217730338054319, "FinalMeanRMSE": -1}
{"TrainCount": 4, "MeanTrainLoss": 0.04451709771156311, "MeanValidationLoss": 0.05234723357904342, "FinalMeanRMSE": -1}
{"TrainCount": 4, "MeanTrainLoss": 0.04512990587949753, "MeanValidationLoss": 0.052262813573883425, "FinalMeanRMSE": -1}
{"TrainCount": 4, "MeanTrainLoss": 0.04452144569158554, "MeanValidationLoss": 0.05243887511953231, "FinalMeanRMSE": -1}
{"TrainCount": 4, "MeanTrainLoss": 0.04367456287145614, "MeanValidationLoss": 0.052308121155346596, "FinalMeanRMSE": 0.052308119915554445}
{"TrainCount": 5, "MeanTrainLoss": 0.045483244197994634, "MeanValidationLoss": 0.058509179516069924, "FinalMeanRMSE": -1}
{"TrainCount": 5, "MeanTrainLoss": 0.04741804380823114, "MeanValidationLoss": 0.0661647139089321, "FinalMeanRMSE": -1}
{"TrainCount": 5, "MeanTrainLoss": 0.04869386616199376, "MeanValidationLoss": 0.052261731976559804, "FinalMeanRMSE": -1}
{"TrainCount": 5, "MeanTrainLoss": 0.04507619535179334, "MeanValidationLoss": 0.054332048034490044, "FinalMeanRMSE": -1}
{"TrainCount": 5, "MeanTrainLoss": 0.045129628127069665, "MeanValidationLoss": 0.06182663543010825, "FinalMeanRMSE": -1}
{"TrainCount": 5, "MeanTrainLoss": 0.046548726658026375, "MeanValidationLoss": 0.05854996549549388, "FinalMeanRMSE": -1}
{"TrainCount": 5, "MeanTrainLoss": 0.045714325967003734, "MeanValidationLoss": 0.05511213533246695, "FinalMeanRMSE": -1}
{"TrainCount": 5, "MeanTrainLoss": 0.04450487622946112, "MeanValidationLoss": 0.05783765817255671, "FinalMeanRMSE": -1}
{"TrainCount": 5, "MeanTrainLoss": 0.0449443210186905, "MeanValidationLoss": 0.058382699627484845, "FinalMeanRMSE": -1}
{"TrainCount": 5, "MeanTrainLoss": 0.044913564883241885, "MeanValidationLoss": 0.05599638291481716, "FinalMeanRMSE": -1}
{"TrainCount": 5, "MeanTrainLoss": 0.04412916653704599, "MeanValidationLoss": 0.05662942772258574, "FinalMeanRMSE": -1}
{"TrainCount": 5, "MeanTrainLoss": 0.04407826593246318, "MeanValidationLoss": 0.057627705050938165, "FinalMeanRMSE": -1}
{"TrainCount": 5, "MeanTrainLoss": 0.04415518979176019, "MeanValidationLoss": 0.05673918439381158, "FinalMeanRMSE": -1}
{"TrainCount": 5, "MeanTrainLoss": 0.04379321373929747, "MeanValidationLoss": 0.05662367048103418, "FinalMeanRMSE": -1}
{"TrainCount": 5, "MeanTrainLoss": 0.04361282928640394, "MeanValidationLoss": 0.05722089588586519, "FinalMeanRMSE": 0.057220895592203086}
{"TrainCount": 6, "MeanTrainLoss": 0.04600419087073267, "MeanValidationLoss": 0.057391590931836295, "FinalMeanRMSE": -1}
{"TrainCount": 6, "MeanTrainLoss": 0.05111089266387157, "MeanValidationLoss": 0.05655286198153215, "FinalMeanRMSE": -1}
{"TrainCount": 6, "MeanTrainLoss": 0.04207974485031429, "MeanValidationLoss": 0.058271054835880506, "FinalMeanRMSE": -1}
{"TrainCount": 6, "MeanTrainLoss": 0.04866130462757412, "MeanValidationLoss": 0.05357440604883082, "FinalMeanRMSE": -1}
{"TrainCount": 6, "MeanTrainLoss": 0.04265915576566072, "MeanValidationLoss": 0.05468417791759267, "FinalMeanRMSE": -1}
{"TrainCount": 6, "MeanTrainLoss": 0.045771085849573234, "MeanValidationLoss": 0.05352672014166327, "FinalMeanRMSE": -1}
{"TrainCount": 6, "MeanTrainLoss": 0.044001944676395746, "MeanValidationLoss": 0.05346749810611501, "FinalMeanRMSE": -1}
{"TrainCount": 6, "MeanTrainLoss": 0.04372171188621242, "MeanValidationLoss": 0.054106087149942625, "FinalMeanRMSE": -1}
{"TrainCount": 6, "MeanTrainLoss": 0.04436573602082089, "MeanValidationLoss": 0.05333770680076936, "FinalMeanRMSE": -1}
{"TrainCount": 6, "MeanTrainLoss": 0.04288839561084942, "MeanValidationLoss": 0.054061640136163026, "FinalMeanRMSE": -1}
{"TrainCount": 6, "MeanTrainLoss": 0.043869638192370344, "MeanValidationLoss": 0.05341944843530655, "FinalMeanRMSE": -1}
{"TrainCount": 6, "MeanTrainLoss": 0.04272660542912849, "MeanValidationLoss": 0.053797658094588446, "FinalMeanRMSE": -1}
{"TrainCount": 6, "MeanTrainLoss": 0.04318269708583734, "MeanValidationLoss": 0.05355646077762632, "FinalMeanRMSE": -1}
{"TrainCount": 6, "MeanTrainLoss": 0.042633091618853466, "MeanValidationLoss": 0.053642423713908476, "FinalMeanRMSE": -1}
{"TrainCount": 6, "MeanTrainLoss": 0.042596939903508595, "MeanValidationLoss": 0.053689030053861, "FinalMeanRMSE": 0.053689031203769444}
{"TrainCount": 7, "MeanTrainLoss": 0.04093252393862475, "MeanValidationLoss": 0.07515980443962804, "FinalMeanRMSE": -1}
{"TrainCount": 7, "MeanTrainLoss": 0.051650170891181284, "MeanValidationLoss": 0.049928460973542886, "FinalMeanRMSE": -1}
{"TrainCount": 7, "MeanTrainLoss": 0.03838838023336037, "MeanValidationLoss": 0.05587916941075892, "FinalMeanRMSE": -1}
{"TrainCount": 7, "MeanTrainLoss": 0.04432299291310103, "MeanValidationLoss": 0.04762239946977242, "FinalMeanRMSE": -1}
{"TrainCount": 7, "MeanTrainLoss": 0.03973616435475971, "MeanValidationLoss": 0.04945314699015417, "FinalMeanRMSE": -1}
{"TrainCount": 7, "MeanTrainLoss": 0.04027971664200659, "MeanValidationLoss": 0.04958366144161958, "FinalMeanRMSE": -1}
{"TrainCount": 7, "MeanTrainLoss": 0.04101006200132163, "MeanValidationLoss": 0.04813081132886293, "FinalMeanRMSE": -1}
{"TrainCount": 7, "MeanTrainLoss": 0.038858922868967055, "MeanValidationLoss": 0.050454021646426275, "FinalMeanRMSE": -1}
{"TrainCount": 7, "MeanTrainLoss": 0.04037540837474491, "MeanValidationLoss": 0.048350021920420906, "FinalMeanRMSE": -1}
{"TrainCount": 7, "MeanTrainLoss": 0.03879700995657755, "MeanValidationLoss": 0.049592628658234654, "FinalMeanRMSE": -1}
{"TrainCount": 7, "MeanTrainLoss": 0.0391648212917473, "MeanValidationLoss": 0.04916023498179613, "FinalMeanRMSE": -1}
{"TrainCount": 7, "MeanTrainLoss": 0.038908990181010704, "MeanValidationLoss": 0.04905768968425431, "FinalMeanRMSE": -1}
{"TrainCount": 7, "MeanTrainLoss": 0.03841326756969742, "MeanValidationLoss": 0.04966295290399681, "FinalMeanRMSE": -1}
{"TrainCount": 7, "MeanTrainLoss": 0.038632505905369055, "MeanValidationLoss": 0.04916392670540543, "FinalMeanRMSE": -1}
{"TrainCount": 7, "MeanTrainLoss": 0.03810602252898009, "MeanValidationLoss": 0.049672330084901586, "FinalMeanRMSE": 0.04967232981450536}
{"TrainCount": 8, "MeanTrainLoss": 0.05224619313977123, "MeanValidationLoss": 0.05739209624497514, "FinalMeanRMSE": -1}
{"TrainCount": 8, "MeanTrainLoss": 0.046409771430726145, "MeanValidationLoss": 0.04835762024710053, "FinalMeanRMSE": -1}
{"TrainCount": 8, "MeanTrainLoss": 0.04427704224789065, "MeanValidationLoss": 0.04817582980582589, "FinalMeanRMSE": -1}
{"TrainCount": 8, "MeanTrainLoss": 0.04487536501845503, "MeanValidationLoss": 0.04824067436550793, "FinalMeanRMSE": -1}
{"TrainCount": 8, "MeanTrainLoss": 0.044355688141841515, "MeanValidationLoss": 0.048261019548303204, "FinalMeanRMSE": -1}
{"TrainCount": 8, "MeanTrainLoss": 0.043925267613791175, "MeanValidationLoss": 0.04792926401684159, "FinalMeanRMSE": -1}
{"TrainCount": 8, "MeanTrainLoss": 0.043902518945971344, "MeanValidationLoss": 0.04788155657680411, "FinalMeanRMSE": -1}
{"TrainCount": 8, "MeanTrainLoss": 0.04399849415994158, "MeanValidationLoss": 0.047901879996061325, "FinalMeanRMSE": -1}
{"TrainCount": 8, "MeanTrainLoss": 0.04388571262749192, "MeanValidationLoss": 0.047947492156373825, "FinalMeanRMSE": -1}
{"TrainCount": 8, "MeanTrainLoss": 0.04369903570101931, "MeanValidationLoss": 0.04789427765890172, "FinalMeanRMSE": -1}
{"TrainCount": 8, "MeanTrainLoss": 0.04358627116368487, "MeanValidationLoss": 0.047834975742980054, "FinalMeanRMSE": -1}
{"TrainCount": 8, "MeanTrainLoss": 0.04353981757280873, "MeanValidationLoss": 0.04781537267722582, "FinalMeanRMSE": -1}
{"TrainCount": 8, "MeanTrainLoss": 0.043490647490507635, "MeanValidationLoss": 0.04782262326855408, "FinalMeanRMSE": -1}
{"TrainCount": 8, "MeanTrainLoss": 0.04340194272839166, "MeanValidationLoss": 0.047812141772163544, "FinalMeanRMSE": -1}
{"TrainCount": 8, "MeanTrainLoss": 0.04330632967107436, "MeanValidationLoss": 0.047774007445887515, "FinalMeanRMSE": 0.04777400865917438}
{"TrainCount": 9, "MeanTrainLoss": 0.04660053206285496, "MeanValidationLoss": 0.06316828959627657, "FinalMeanRMSE": -1}
{"TrainCount": 9, "MeanTrainLoss": 0.048195959432464845, "MeanValidationLoss": 0.06242262204455224, "FinalMeanRMSE": -1}
{"TrainCount": 9, "MeanTrainLoss": 0.04673546282620564, "MeanValidationLoss": 0.06287223870391088, "FinalMeanRMSE": -1}
{"TrainCount": 9, "MeanTrainLoss": 0.046973544502818015, "MeanValidationLoss": 0.06243269473610335, "FinalMeanRMSE": -1}
{"TrainCount": 9, "MeanTrainLoss": 0.047168200629988846, "MeanValidationLoss": 0.06248590752285048, "FinalMeanRMSE": -1}
{"TrainCount": 9, "MeanTrainLoss": 0.04652594967056342, "MeanValidationLoss": 0.06264737534601957, "FinalMeanRMSE": -1}
{"TrainCount": 9, "MeanTrainLoss": 0.047038493748551735, "MeanValidationLoss": 0.06246737094707047, "FinalMeanRMSE": -1}
{"TrainCount": 9, "MeanTrainLoss": 0.046552242198728847, "MeanValidationLoss": 0.06267557850736656, "FinalMeanRMSE": -1}
{"TrainCount": 9, "MeanTrainLoss": 0.04669676403188234, "MeanValidationLoss": 0.06258132123690567, "FinalMeanRMSE": -1}
{"TrainCount": 9, "MeanTrainLoss": 0.04660230511692053, "MeanValidationLoss": 0.06268890453687567, "FinalMeanRMSE": -1}
{"TrainCount": 9, "MeanTrainLoss": 0.04645123463461584, "MeanValidationLoss": 0.06274497509002686, "FinalMeanRMSE": -1}
{"TrainCount": 9, "MeanTrainLoss": 0.046532900282833876, "MeanValidationLoss": 0.06275948472567741, "FinalMeanRMSE": -1}
{"TrainCount": 9, "MeanTrainLoss": 0.04635595231389096, "MeanValidationLoss": 0.06285842128147352, "FinalMeanRMSE": -1}
{"TrainCount": 9, "MeanTrainLoss": 0.046380905713732594, "MeanValidationLoss": 0.06286992596474704, "FinalMeanRMSE": -1}
{"TrainCount": 9, "MeanTrainLoss": 0.04629497723485139, "MeanValidationLoss": 0.06294193997091016, "FinalMeanRMSE": 0.06294193923922234}
{"TrainCount": 10, "MeanTrainLoss": 0.04869961480331746, "MeanValidationLoss": 0.055607187120538006, "FinalMeanRMSE": -1}
{"TrainCount": 10, "MeanTrainLoss": 0.04332079417232809, "MeanValidationLoss": 0.04662194455924787, "FinalMeanRMSE": -1}
{"TrainCount": 10, "MeanTrainLoss": 0.04487943000730574, "MeanValidationLoss": 0.050745602795167974, "FinalMeanRMSE": -1}
{"TrainCount": 10, "MeanTrainLoss": 0.04355196434735322, "MeanValidationLoss": 0.04796276280754491, "FinalMeanRMSE": -1}
{"TrainCount": 10, "MeanTrainLoss": 0.0440784261618513, "MeanValidationLoss": 0.049750418059135736, "FinalMeanRMSE": -1}
{"TrainCount": 10, "MeanTrainLoss": 0.04348163584810001, "MeanValidationLoss": 0.04887531913424793, "FinalMeanRMSE": -1}
{"TrainCount": 10, "MeanTrainLoss": 0.04362929841558554, "MeanValidationLoss": 0.04968250170350075, "FinalMeanRMSE": -1}
{"TrainCount": 10, "MeanTrainLoss": 0.04333073607139742, "MeanValidationLoss": 0.04924681704295309, "FinalMeanRMSE": -1}
{"TrainCount": 10, "MeanTrainLoss": 0.043316741763768575, "MeanValidationLoss": 0.04951245587711271, "FinalMeanRMSE": -1}
{"TrainCount": 10, "MeanTrainLoss": 0.04312071888531713, "MeanValidationLoss": 0.04941960855534202, "FinalMeanRMSE": -1}
{"TrainCount": 10, "MeanTrainLoss": 0.04302814063785845, "MeanValidationLoss": 0.049534853645845464, "FinalMeanRMSE": -1}
{"TrainCount": 10, "MeanTrainLoss": 0.04288710094797188, "MeanValidationLoss": 0.04953932997427488, "FinalMeanRMSE": -1}
{"TrainCount": 10, "MeanTrainLoss": 0.04277961643998418, "MeanValidationLoss": 0.04960079569565622, "FinalMeanRMSE": -1}
{"TrainCount": 10, "MeanTrainLoss": 0.04266057495365748, "MeanValidationLoss": 0.04962762209929918, "FinalMeanRMSE": -1}
{"TrainCount": 10, "MeanTrainLoss": 0.0425594192814871, "MeanValidationLoss": 0.049684463951148485, "FinalMeanRMSE": 0.0496844648682318}
{"TrainCount": 11, "MeanTrainLoss": 0.04808584538994321, "MeanValidationLoss": 0.05966860684714499, "FinalMeanRMSE": -1}
{"TrainCount": 11, "MeanTrainLoss": 0.046579484371053186, "MeanValidationLoss": 0.05272749697516678, "FinalMeanRMSE": -1}
{"TrainCount": 11, "MeanTrainLoss": 0.044798520909752816, "MeanValidationLoss": 0.053741923491856095, "FinalMeanRMSE": -1}
{"TrainCount": 11, "MeanTrainLoss": 0.044680202462870605, "MeanValidationLoss": 0.053649521960764175, "FinalMeanRMSE": -1}
{"TrainCount": 11, "MeanTrainLoss": 0.04439968506621707, "MeanValidationLoss": 0.05300739352965051, "FinalMeanRMSE": -1}
{"TrainCount": 11, "MeanTrainLoss": 0.04401932367283827, "MeanValidationLoss": 0.053918706122667165, "FinalMeanRMSE": -1}
{"TrainCount": 11, "MeanTrainLoss": 0.04401314429416778, "MeanValidationLoss": 0.05341995898990115, "FinalMeanRMSE": -1}
{"TrainCount": 11, "MeanTrainLoss": 0.04382035857552936, "MeanValidationLoss": 0.053588870889062334, "FinalMeanRMSE": -1}
{"TrainCount": 11, "MeanTrainLoss": 0.04377884123545543, "MeanValidationLoss": 0.05374360241138252, "FinalMeanRMSE": -1}
{"TrainCount": 11, "MeanTrainLoss": 0.0437322007907424, "MeanValidationLoss": 0.053598642123827506, "FinalMeanRMSE": -1}
{"TrainCount": 11, "MeanTrainLoss": 0.04366963090980129, "MeanValidationLoss": 0.05369403941711043, "FinalMeanRMSE": -1}
{"TrainCount": 11, "MeanTrainLoss": 0.043644705680525225, "MeanValidationLoss": 0.05364307139519673, "FinalMeanRMSE": -1}
{"TrainCount": 11, "MeanTrainLoss": 0.04359796235136166, "MeanValidationLoss": 0.05360946184985197, "FinalMeanRMSE": -1}
{"TrainCount": 11, "MeanTrainLoss": 0.04356284411090195, "MeanValidationLoss": 0.05362622862219051, "FinalMeanRMSE": -1}
{"TrainCount": 11, "MeanTrainLoss": 0.043531725835648315, "MeanValidationLoss": 0.05357734345279302, "FinalMeanRMSE": 0.05357734212723743}
{"TrainCount": 12, "MeanTrainLoss": 0.04607664010463617, "MeanValidationLoss": 0.05292987250364744, "FinalMeanRMSE": -1}
{"TrainCount": 12, "MeanTrainLoss": 0.04195954507360092, "MeanValidationLoss": 0.060366193453470864, "FinalMeanRMSE": -1}
{"TrainCount": 12, "MeanTrainLoss": 0.04240748114310778, "MeanValidationLoss": 0.05436784286911671, "FinalMeanRMSE": -1}
{"TrainCount": 12, "MeanTrainLoss": 0.04154111273013628, "MeanValidationLoss": 0.05687666970949907, "FinalMeanRMSE": -1}
{"TrainCount": 12, "MeanTrainLoss": 0.041771699889348105, "MeanValidationLoss": 0.05508309554977295, "FinalMeanRMSE": -1}
{"TrainCount": 12, "MeanTrainLoss": 0.04149720454827333, "MeanValidationLoss": 0.055967229776657544, "FinalMeanRMSE": -1}
{"TrainCount": 12, "MeanTrainLoss": 0.04156780290680054, "MeanValidationLoss": 0.05534472660376476, "FinalMeanRMSE": -1}
{"TrainCount": 12, "MeanTrainLoss": 0.04144520627764555, "MeanValidationLoss": 0.055686343365754835, "FinalMeanRMSE": -1}
{"TrainCount": 12, "MeanTrainLoss": 0.041450757724352374, "MeanValidationLoss": 0.055454212646835886, "FinalMeanRMSE": -1}
{"TrainCount": 12, "MeanTrainLoss": 0.04138327495027811, "MeanValidationLoss": 0.055565693200780794, "FinalMeanRMSE": -1}
{"TrainCount": 12, "MeanTrainLoss": 0.04136377085859959, "MeanValidationLoss": 0.05546456861954469, "FinalMeanRMSE": -1}
{"TrainCount": 12, "MeanTrainLoss": 0.0413165009365632, "MeanValidationLoss": 0.055500042744171925, "FinalMeanRMSE": -1}
{"TrainCount": 12, "MeanTrainLoss": 0.04128774685355333, "MeanValidationLoss": 0.05547026067208021, "FinalMeanRMSE": -1}
{"TrainCount": 12, "MeanTrainLoss": 0.04125004252180075, "MeanValidationLoss": 0.0555051211745311, "FinalMeanRMSE": -1}
{"TrainCount": 12, "MeanTrainLoss": 0.04122518299099726, "MeanValidationLoss": 0.05544095161633614, "FinalMeanRMSE": 0.055440951016752914}
{"TrainCount": 13, "MeanTrainLoss": 0.05438582617225069, "MeanValidationLoss": 0.07772823691186381, "FinalMeanRMSE": -1}
{"TrainCount": 13, "MeanTrainLoss": 0.05428500462210539, "MeanValidationLoss": 0.0684711300745243, "FinalMeanRMSE": -1}
{"TrainCount": 13, "MeanTrainLoss": 0.053398071003682684, "MeanValidationLoss": 0.07302675959540576, "FinalMeanRMSE": -1}
{"TrainCount": 13, "MeanTrainLoss": 0.05357565116701704, "MeanValidationLoss": 0.06987573279113304, "FinalMeanRMSE": -1}
{"TrainCount": 13, "MeanTrainLoss": 0.05328914726322347, "MeanValidationLoss": 0.07149943720234171, "FinalMeanRMSE": -1}
{"TrainCount": 13, "MeanTrainLoss": 0.05335851257497614, "MeanValidationLoss": 0.07025580598813731, "FinalMeanRMSE": -1}
{"TrainCount": 13, "MeanTrainLoss": 0.053239569903323146, "MeanValidationLoss": 0.07082613357683508, "FinalMeanRMSE": -1}
{"TrainCount": 13, "MeanTrainLoss": 0.05325251641598615, "MeanValidationLoss": 0.07033272887148508, "FinalMeanRMSE": -1}
{"TrainCount": 13, "MeanTrainLoss": 0.053188740304022125, "MeanValidationLoss": 0.0704807195721603, "FinalMeanRMSE": -1}
{"TrainCount": 13, "MeanTrainLoss": 0.053174312909444174, "MeanValidationLoss": 0.07025028329070021, "FinalMeanRMSE": -1}
{"TrainCount": 13, "MeanTrainLoss": 0.05313688724329977, "MeanValidationLoss": 0.07025971663434331, "FinalMeanRMSE": -1}
{"TrainCount": 13, "MeanTrainLoss": 0.05311543049685883, "MeanValidationLoss": 0.07013981477016719, "FinalMeanRMSE": -1}
{"TrainCount": 13, "MeanTrainLoss": 0.053086189564430356, "MeanValidationLoss": 0.0701053781980058, "FinalMeanRMSE": -1}
{"TrainCount": 13, "MeanTrainLoss": 0.05306429795243523, "MeanValidationLoss": 0.0700444166162392, "FinalMeanRMSE": -1}
{"TrainCount": 13, "MeanTrainLoss": 0.05303930037400939, "MeanValidationLoss": 0.0700003437516166, "FinalMeanRMSE": 0.070000345399409}
{"TrainCount": 14, "MeanTrainLoss": 0.05156549052422091, "MeanValidationLoss": 0.05795674175024033, "FinalMeanRMSE": -1}
{"TrainCount": 14, "MeanTrainLoss": 0.05117261423642591, "MeanValidationLoss": 0.057079470902681353, "FinalMeanRMSE": -1}
{"TrainCount": 14, "MeanTrainLoss": 0.051139170431202245, "MeanValidationLoss": 0.05739831030368805, "FinalMeanRMSE": -1}
{"TrainCount": 14, "MeanTrainLoss": 0.051122799423170384, "MeanValidationLoss": 0.057275474071502686, "FinalMeanRMSE": -1}
{"TrainCount": 14, "MeanTrainLoss": 0.051009858941069304, "MeanValidationLoss": 0.057310673594474795, "FinalMeanRMSE": -1}
{"TrainCount": 14, "MeanTrainLoss": 0.05102328497985875, "MeanValidationLoss": 0.057345765829086306, "FinalMeanRMSE": -1}
{"TrainCount": 14, "MeanTrainLoss": 0.050915637603087455, "MeanValidationLoss": 0.05735190957784653, "FinalMeanRMSE": -1}
{"TrainCount": 14, "MeanTrainLoss": 0.050920614961141385, "MeanValidationLoss": 0.05742395892739296, "FinalMeanRMSE": -1}
{"TrainCount": 14, "MeanTrainLoss": 0.050837297894939876, "MeanValidationLoss": 0.057443706691265105, "FinalMeanRMSE": -1}
{"TrainCount": 14, "MeanTrainLoss": 0.05081994715869797, "MeanValidationLoss": 0.05752304717898369, "FinalMeanRMSE": -1}
{"TrainCount": 14, "MeanTrainLoss": 0.05075827069719386, "MeanValidationLoss": 0.057564905285835265, "FinalMeanRMSE": -1}
{"TrainCount": 14, "MeanTrainLoss": 0.05073380396232842, "MeanValidationLoss": 0.05763208866119385, "FinalMeanRMSE": -1}
{"TrainCount": 14, "MeanTrainLoss": 0.05068267419101288, "MeanValidationLoss": 0.057681252062320706, "FinalMeanRMSE": -1}
{"TrainCount": 14, "MeanTrainLoss": 0.05066083348500803, "MeanValidationLoss": 0.05773847624659538, "FinalMeanRMSE": -1}
{"TrainCount": 14, "MeanTrainLoss": 0.0506269069191832, "MeanValidationLoss": 0.057783625274896624, "FinalMeanRMSE": 0.05778362413002221}
{"TrainCount": 15, "MeanTrainLoss": 0.047674970678895354, "MeanValidationLoss": 0.07353980487043207, "FinalMeanRMSE": -1}
{"TrainCount": 15, "MeanTrainLoss": 0.04954819215169872, "MeanValidationLoss": 0.06006550820669817, "FinalMeanRMSE": -1}
{"TrainCount": 15, "MeanTrainLoss": 0.04718037730599024, "MeanValidationLoss": 0.06648091840924639, "FinalMeanRMSE": -1}
{"TrainCount": 15, "MeanTrainLoss": 0.04817596055477499, "MeanValidationLoss": 0.06202925396236506, "FinalMeanRMSE": -1}
{"TrainCount": 15, "MeanTrainLoss": 0.047321607773921574, "MeanValidationLoss": 0.06460544047030535, "FinalMeanRMSE": -1}
{"TrainCount": 15, "MeanTrainLoss": 0.04774503486163645, "MeanValidationLoss": 0.06291868647818002, "FinalMeanRMSE": -1}
{"TrainCount": 15, "MeanTrainLoss": 0.04739637762667185, "MeanValidationLoss": 0.06401658645181944, "FinalMeanRMSE": -1}
{"TrainCount": 15, "MeanTrainLoss": 0.047556451510593116, "MeanValidationLoss": 0.06336794633305434, "FinalMeanRMSE": -1}
{"TrainCount": 15, "MeanTrainLoss": 0.04740108253366976, "MeanValidationLoss": 0.06385501000014218, "FinalMeanRMSE": -1}
{"TrainCount": 15, "MeanTrainLoss": 0.047446456165557885, "MeanValidationLoss": 0.06366366886279799, "FinalMeanRMSE": -1}
{"TrainCount": 15, "MeanTrainLoss": 0.047370434749916375, "MeanValidationLoss": 0.06388611822868838, "FinalMeanRMSE": -1}
{"TrainCount": 15, "MeanTrainLoss": 0.04736835433237524, "MeanValidationLoss": 0.06386376544833183, "FinalMeanRMSE": -1}
{"TrainCount": 15, "MeanTrainLoss": 0.04732256728303002, "MeanValidationLoss": 0.0639913694876613, "FinalMeanRMSE": -1}
{"TrainCount": 15, "MeanTrainLoss": 0.047303340296788385, "MeanValidationLoss": 0.06402671158483082, "FinalMeanRMSE": -1}
{"TrainCount": 15, "MeanTrainLoss": 0.04726967525230833, "MeanValidationLoss": 0.06412083179210172, "FinalMeanRMSE": 0.06412083082747358}
{"TrainCount": 16, "MeanTrainLoss": 0.08599292501146458, "MeanValidationLoss": 0.06661656930859834, "FinalMeanRMSE": -1}
{"TrainCount": 16, "MeanTrainLoss": 0.060331402847754116, "MeanValidationLoss": 0.05880111386211006, "FinalMeanRMSE": -1}
{"TrainCount": 16, "MeanTrainLoss": 0.05559160615622268, "MeanValidationLoss": 0.07362255247229813, "FinalMeanRMSE": -1}
{"TrainCount": 16, "MeanTrainLoss": 0.05541885638501302, "MeanValidationLoss": 0.06131911753145464, "FinalMeanRMSE": -1}
{"TrainCount": 16, "MeanTrainLoss": 0.05488497721150928, "MeanValidationLoss": 0.06748387551197976, "FinalMeanRMSE": -1}
{"TrainCount": 16, "MeanTrainLoss": 0.054546006986535285, "MeanValidationLoss": 0.06266425038042243, "FinalMeanRMSE": -1}
{"TrainCount": 16, "MeanTrainLoss": 0.05438222257072955, "MeanValidationLoss": 0.06518731750883562, "FinalMeanRMSE": -1}
{"TrainCount": 16, "MeanTrainLoss": 0.054135904638865674, "MeanValidationLoss": 0.06305311709368155, "FinalMeanRMSE": -1}
{"TrainCount": 16, "MeanTrainLoss": 0.05403130965745959, "MeanValidationLoss": 0.06407435005245034, "FinalMeanRMSE": -1}
{"TrainCount": 16, "MeanTrainLoss": 0.053858824353380304, "MeanValidationLoss": 0.06305316456256468, "FinalMeanRMSE": -1}
{"TrainCount": 16, "MeanTrainLoss": 0.05376812546807327, "MeanValidationLoss": 0.06347158386663425, "FinalMeanRMSE": -1}
{"TrainCount": 16, "MeanTrainLoss": 0.05363444945794909, "MeanValidationLoss": 0.06293670924528977, "FinalMeanRMSE": -1}
{"TrainCount": 16, "MeanTrainLoss": 0.05354626974609285, "MeanValidationLoss": 0.0631141571319652, "FinalMeanRMSE": -1}
{"TrainCount": 16, "MeanTrainLoss": 0.053435974085094005, "MeanValidationLoss": 0.06280191724443597, "FinalMeanRMSE": -1}
{"TrainCount": 16, "MeanTrainLoss": 0.053352931223878075, "MeanValidationLoss": 0.06286824572305738, "FinalMeanRMSE": 0.0628682441846187}
{"TrainCount": 17, "MeanTrainLoss": 0.04851670102639632, "MeanValidationLoss": 0.051834495442851285, "FinalMeanRMSE": -1}
{"TrainCount": 17, "MeanTrainLoss": 0.048529763993891806, "MeanValidationLoss": 0.05218406494070844, "FinalMeanRMSE": -1}
{"TrainCount": 17, "MeanTrainLoss": 0.04831899673198209, "MeanValidationLoss": 0.051966177981074266, "FinalMeanRMSE": -1}
{"TrainCount": 17, "MeanTrainLoss": 0.04811125099658966, "MeanValidationLoss": 0.051771267158229176, "FinalMeanRMSE": -1}
{"TrainCount": 17, "MeanTrainLoss": 0.04814449833198027, "MeanValidationLoss": 0.05176115326765107, "FinalMeanRMSE": -1}
{"TrainCount": 17, "MeanTrainLoss": 0.04797131931691459, "MeanValidationLoss": 0.05154357016433218, "FinalMeanRMSE": -1}
{"TrainCount": 17, "MeanTrainLoss": 0.04798832427371632, "MeanValidationLoss": 0.051537115603284805, "FinalMeanRMSE": -1}
{"TrainCount": 17, "MeanTrainLoss": 0.047873900175997706, "MeanValidationLoss": 0.051382357209194, "FinalMeanRMSE": -1}
{"TrainCount": 17, "MeanTrainLoss": 0.04785933995788748, "MeanValidationLoss": 0.051359460620981894, "FinalMeanRMSE": -1}
{"TrainCount": 17, "MeanTrainLoss": 0.04778073152357882, "MeanValidationLoss": 0.05126454790190953, "FinalMeanRMSE": -1}
{"TrainCount": 17, "MeanTrainLoss": 0.04774525411652796, "MeanValidationLoss": 0.051221965562279634, "FinalMeanRMSE": -1}
{"TrainCount": 17, "MeanTrainLoss": 0.04769034173452493, "MeanValidationLoss": 0.05117708226529563, "FinalMeanRMSE": -1}
{"TrainCount": 17, "MeanTrainLoss": 0.047644830404809026, "MeanValidationLoss": 0.05114008265383479, "FinalMeanRMSE": -1}
{"TrainCount": 17, "MeanTrainLoss": 0.047599708582415724, "MeanValidationLoss": 0.05110466552943718, "FinalMeanRMSE": -1}
{"TrainCount": 17, "MeanTrainLoss": 0.04755767446124193, "MeanValidationLoss": 0.051085103939219216, "FinalMeanRMSE": 0.0510851033155683}
{"TrainCount": 18, "MeanTrainLoss": 0.05571063911139334, "MeanValidationLoss": 0.05221012501102505, "FinalMeanRMSE": -1}
{"TrainCount": 18, "MeanTrainLoss": 0.05477485751645828, "MeanValidationLoss": 0.049158723336277584, "FinalMeanRMSE": -1}
{"TrainCount": 18, "MeanTrainLoss": 0.051677362105714754, "MeanValidationLoss": 0.048715474995586906, "FinalMeanRMSE": -1}
{"TrainCount": 18, "MeanTrainLoss": 0.05093725495119319, "MeanValidationLoss": 0.04863417571918531, "FinalMeanRMSE": -1}
{"TrainCount": 18, "MeanTrainLoss": 0.05099878743651595, "MeanValidationLoss": 0.04875790562593576, "FinalMeanRMSE": -1}
{"TrainCount": 18, "MeanTrainLoss": 0.05072027092599472, "MeanValidationLoss": 0.048621548463900884, "FinalMeanRMSE": -1}
{"TrainCount": 18, "MeanTrainLoss": 0.05080840014676463, "MeanValidationLoss": 0.04870287326577289, "FinalMeanRMSE": -1}
{"TrainCount": 18, "MeanTrainLoss": 0.050663578827018635, "MeanValidationLoss": 0.048620842442368015, "FinalMeanRMSE": -1}
{"TrainCount": 18, "MeanTrainLoss": 0.05069221875175225, "MeanValidationLoss": 0.04865917552149657, "FinalMeanRMSE": -1}
{"TrainCount": 18, "MeanTrainLoss": 0.05060664692868263, "MeanValidationLoss": 0.048613325596758815, "FinalMeanRMSE": -1}
{"TrainCount": 18, "MeanTrainLoss": 0.05060841008434678, "MeanValidationLoss": 0.048630751804871995, "FinalMeanRMSE": -1}
{"TrainCount": 18, "MeanTrainLoss": 0.050549356292217476, "MeanValidationLoss": 0.04860533037307588, "FinalMeanRMSE": -1}
{"TrainCount": 18, "MeanTrainLoss": 0.05053196399389525, "MeanValidationLoss": 0.048609320209784944, "FinalMeanRMSE": -1}
{"TrainCount": 18, "MeanTrainLoss": 0.05048976294730146, "MeanValidationLoss": 0.04859584213488481, "FinalMeanRMSE": -1}
{"TrainCount": 18, "MeanTrainLoss": 0.05046348707150223, "MeanValidationLoss": 0.048593691578417114, "FinalMeanRMSE": 0.048593692415811775}
{"TrainCount": 19, "MeanTrainLoss": 0.05459710469324432, "MeanValidationLoss": 0.04721734708476209, "FinalMeanRMSE": -1}
{"TrainCount": 19, "MeanTrainLoss": 0.05309970770588892, "MeanValidationLoss": 0.04648955706128792, "FinalMeanRMSE": -1}
{"TrainCount": 19, "MeanTrainLoss": 0.05390430201670367, "MeanValidationLoss": 0.046582673481124603, "FinalMeanRMSE": -1}
{"TrainCount": 19, "MeanTrainLoss": 0.05343292965860424, "MeanValidationLoss": 0.046526704825639364, "FinalMeanRMSE": -1}
{"TrainCount": 19, "MeanTrainLoss": 0.05334168186266265, "MeanValidationLoss": 0.046484571351797996, "FinalMeanRMSE": -1}
{"TrainCount": 19, "MeanTrainLoss": 0.0534089133143425, "MeanValidationLoss": 0.04650637141601768, "FinalMeanRMSE": -1}
{"TrainCount": 19, "MeanTrainLoss": 0.05324734667104161, "MeanValidationLoss": 0.04648410475361133, "FinalMeanRMSE": -1}
{"TrainCount": 19, "MeanTrainLoss": 0.053247355727735396, "MeanValidationLoss": 0.04648192806872065, "FinalMeanRMSE": -1}
{"TrainCount": 19, "MeanTrainLoss": 0.05320582819912962, "MeanValidationLoss": 0.04648182416212059, "FinalMeanRMSE": -1}
{"TrainCount": 19, "MeanTrainLoss": 0.053144304606015096, "MeanValidationLoss": 0.046476188486631584, "FinalMeanRMSE": -1}
{"TrainCount": 19, "MeanTrainLoss": 0.05312213069664504, "MeanValidationLoss": 0.0464756159992989, "FinalMeanRMSE": -1}
{"TrainCount": 19, "MeanTrainLoss": 0.05307527756441139, "MeanValidationLoss": 0.04647352585490949, "FinalMeanRMSE": -1}
{"TrainCount": 19, "MeanTrainLoss": 0.053035989537567434, "MeanValidationLoss": 0.04647164818590987, "FinalMeanRMSE": -1}
{"TrainCount": 19, "MeanTrainLoss": 0.05300077510451128, "MeanValidationLoss": 0.046471631194849664, "FinalMeanRMSE": -1}
{"TrainCount": 19, "MeanTrainLoss": 0.05295839477441982, "MeanValidationLoss": 0.0464705170918546, "FinalMeanRMSE": 0.04647051688744329}
{"TrainCount": 20, "MeanTrainLoss": 0.0494611750931795, "MeanValidationLoss": 0.05013935259002411, "FinalMeanRMSE": -1}
{"TrainCount": 20, "MeanTrainLoss": 0.04932622668599245, "MeanValidationLoss": 0.05172238146473548, "FinalMeanRMSE": -1}
{"TrainCount": 20, "MeanTrainLoss": 0.04861673090735002, "MeanValidationLoss": 0.050769943253187365, "FinalMeanRMSE": -1}
{"TrainCount": 20, "MeanTrainLoss": 0.048633906374976416, "MeanValidationLoss": 0.050914401846553034, "FinalMeanRMSE": -1}
{"TrainCount": 20, "MeanTrainLoss": 0.04840284406370379, "MeanValidationLoss": 0.05105397332749681, "FinalMeanRMSE": -1}
{"TrainCount": 20, "MeanTrainLoss": 0.0483775905852717, "MeanValidationLoss": 0.050867547130513335, "FinalMeanRMSE": -1}
{"TrainCount": 20, "MeanTrainLoss": 0.04829674913799905, "MeanValidationLoss": 0.051024407968148146, "FinalMeanRMSE": -1}
{"TrainCount": 20, "MeanTrainLoss": 0.048243557683488716, "MeanValidationLoss": 0.050905842624024714, "FinalMeanRMSE": -1}
{"TrainCount": 20, "MeanTrainLoss": 0.048198257680141514, "MeanValidationLoss": 0.05097697701996672, "FinalMeanRMSE": -1}
{"TrainCount": 20, "MeanTrainLoss": 0.048146505117616846, "MeanValidationLoss": 0.05092932435566794, "FinalMeanRMSE": -1}
{"TrainCount": 20, "MeanTrainLoss": 0.04810869309254915, "MeanValidationLoss": 0.05095204979761275, "FinalMeanRMSE": -1}
{"TrainCount": 20, "MeanTrainLoss": 0.04806723829598259, "MeanValidationLoss": 0.05093875384616281, "FinalMeanRMSE": -1}
{"TrainCount": 20, "MeanTrainLoss": 0.04803445468613563, "MeanValidationLoss": 0.05093980854945982, "FinalMeanRMSE": -1}
{"TrainCount": 20, "MeanTrainLoss": 0.048001328235428076, "MeanValidationLoss": 0.050941533146950296, "FinalMeanRMSE": -1}
{"TrainCount": 20, "MeanTrainLoss": 0.04797088719002335, "MeanValidationLoss": 0.050936065391152203, "FinalMeanRMSE": 0.05093606553831888}
{"TrainCount": 21, "MeanTrainLoss": 0.053594941625354525, "MeanValidationLoss": 0.06952757176739224, "FinalMeanRMSE": -1}
{"TrainCount": 21, "MeanTrainLoss": 0.053027418382619665, "MeanValidationLoss": 0.06840057437412837, "FinalMeanRMSE": -1}
{"TrainCount": 21, "MeanTrainLoss": 0.05139755048742447, "MeanValidationLoss": 0.06795123935892032, "FinalMeanRMSE": -1}
{"TrainCount": 21, "MeanTrainLoss": 0.05130149553394387, "MeanValidationLoss": 0.06807787262300062, "FinalMeanRMSE": -1}
{"TrainCount": 21, "MeanTrainLoss": 0.05103494000427444, "MeanValidationLoss": 0.06803772757215613, "FinalMeanRMSE": -1}
{"TrainCount": 21, "MeanTrainLoss": 0.05105742058571432, "MeanValidationLoss": 0.06811054576100153, "FinalMeanRMSE": -1}
{"TrainCount": 21, "MeanTrainLoss": 0.05096446682501024, "MeanValidationLoss": 0.0681205778189841, "FinalMeanRMSE": -1}
{"TrainCount": 21, "MeanTrainLoss": 0.050970196439346874, "MeanValidationLoss": 0.06816842918388942, "FinalMeanRMSE": -1}
{"TrainCount": 21, "MeanTrainLoss": 0.05092387288013978, "MeanValidationLoss": 0.0681965583218978, "FinalMeanRMSE": -1}
{"TrainCount": 21, "MeanTrainLoss": 0.05091294216634778, "MeanValidationLoss": 0.06823440901273807, "FinalMeanRMSE": -1}
{"TrainCount": 21, "MeanTrainLoss": 0.05088152008478218, "MeanValidationLoss": 0.06826127452786858, "FinalMeanRMSE": -1}
{"TrainCount": 21, "MeanTrainLoss": 0.05086425810168563, "MeanValidationLoss": 0.06829207571300529, "FinalMeanRMSE": -1}
{"TrainCount": 21, "MeanTrainLoss": 0.050839589559569964, "MeanValidationLoss": 0.0683184967062177, "FinalMeanRMSE": -1}
{"TrainCount": 21, "MeanTrainLoss": 0.05082021042639658, "MeanValidationLoss": 0.0683427134738166, "FinalMeanRMSE": -1}
{"TrainCount": 21, "MeanTrainLoss": 0.050798899280353374, "MeanValidationLoss": 0.06836361299164197, "FinalMeanRMSE": 0.06836361387573732}
{"TrainCount": 22, "MeanTrainLoss": 0.060892966890019065, "MeanValidationLoss": 0.046947106032407725, "FinalMeanRMSE": -1}
{"TrainCount": 22, "MeanTrainLoss": 0.05861154349866448, "MeanValidationLoss": 0.04676963402145713, "FinalMeanRMSE": -1}
{"TrainCount": 22, "MeanTrainLoss": 0.05850203968488525, "MeanValidationLoss": 0.04672739936931599, "FinalMeanRMSE": -1}
{"TrainCount": 22, "MeanTrainLoss": 0.05790907640314616, "MeanValidationLoss": 0.04677110072776411, "FinalMeanRMSE": -1}
{"TrainCount": 22, "MeanTrainLoss": 0.057856134909159876, "MeanValidationLoss": 0.046612467782120026, "FinalMeanRMSE": -1}
{"TrainCount": 22, "MeanTrainLoss": 0.05782131841529671, "MeanValidationLoss": 0.04664549271206884, "FinalMeanRMSE": -1}
{"TrainCount": 22, "MeanTrainLoss": 0.057631029180951955, "MeanValidationLoss": 0.04668758068917066, "FinalMeanRMSE": -1}
{"TrainCount": 22, "MeanTrainLoss": 0.057602607053930874, "MeanValidationLoss": 0.04665392271336719, "FinalMeanRMSE": -1}
{"TrainCount": 22, "MeanTrainLoss": 0.05751844871150047, "MeanValidationLoss": 0.0466668438497027, "FinalMeanRMSE": -1}
{"TrainCount": 22, "MeanTrainLoss": 0.0574499540989711, "MeanValidationLoss": 0.04666119105232185, "FinalMeanRMSE": -1}
{"TrainCount": 22, "MeanTrainLoss": 0.05739980288033699, "MeanValidationLoss": 0.046655626251147345, "FinalMeanRMSE": -1}
{"TrainCount": 22, "MeanTrainLoss": 0.057334882709909565, "MeanValidationLoss": 0.04665780119245222, "FinalMeanRMSE": -1}
{"TrainCount": 22, "MeanTrainLoss": 0.0572861496102619, "MeanValidationLoss": 0.04664951110997143, "FinalMeanRMSE": -1}
{"TrainCount": 22, "MeanTrainLoss": 0.057232190050398694, "MeanValidationLoss": 0.046647989824855116, "FinalMeanRMSE": -1}
{"TrainCount": 22, "MeanTrainLoss": 0.05718226213864049, "MeanValidationLoss": 0.0466436027554718, "FinalMeanRMSE": 0.04664360094868337}
{"TrainCount": 23, "MeanTrainLoss": 0.055394285831015584, "MeanValidationLoss": 0.05468837633019402, "FinalMeanRMSE": -1}
{"TrainCount": 23, "MeanTrainLoss": 0.0550758253032247, "MeanValidationLoss": 0.05401927126305444, "FinalMeanRMSE": -1}
{"TrainCount": 23, "MeanTrainLoss": 0.055066313323318176, "MeanValidationLoss": 0.053491502290680296, "FinalMeanRMSE": -1}
{"TrainCount": 23, "MeanTrainLoss": 0.05492975857510931, "MeanValidationLoss": 0.05465970454471452, "FinalMeanRMSE": -1}
{"TrainCount": 23, "MeanTrainLoss": 0.05482773620826821, "MeanValidationLoss": 0.05461079290225392, "FinalMeanRMSE": -1}
{"TrainCount": 23, "MeanTrainLoss": 0.05477130910147981, "MeanValidationLoss": 0.05488236461366926, "FinalMeanRMSE": -1}
{"TrainCount": 23, "MeanTrainLoss": 0.05468508770616997, "MeanValidationLoss": 0.05535501028810229, "FinalMeanRMSE": -1}
{"TrainCount": 23, "MeanTrainLoss": 0.05461919395939982, "MeanValidationLoss": 0.05554668325930834, "FinalMeanRMSE": -1}
{"TrainCount": 23, "MeanTrainLoss": 0.05456288792562563, "MeanValidationLoss": 0.05585678312040511, "FinalMeanRMSE": -1}
{"TrainCount": 23, "MeanTrainLoss": 0.054504546914501836, "MeanValidationLoss": 0.05614644116056817, "FinalMeanRMSE": -1}
{"TrainCount": 23, "MeanTrainLoss": 0.05445459063247106, "MeanValidationLoss": 0.056391513551629725, "FinalMeanRMSE": -1}
{"TrainCount": 23, "MeanTrainLoss": 0.054405777546180235, "MeanValidationLoss": 0.056686188493456156, "FinalMeanRMSE": -1}
{"TrainCount": 23, "MeanTrainLoss": 0.05435084009572252, "MeanValidationLoss": 0.057042686002595086, "FinalMeanRMSE": -1}
{"TrainCount": 23, "MeanTrainLoss": 0.05428629549470998, "MeanValidationLoss": 0.05737190019516718, "FinalMeanRMSE": -1}
{"TrainCount": 23, "MeanTrainLoss": 0.054225075922254194, "MeanValidationLoss": 0.05767251391495977, "FinalMeanRMSE": 0.05767251332758731}
{"TrainCount": 24, "MeanTrainLoss": 0.051930500049434024, "MeanValidationLoss": 0.059855000790578865, "FinalMeanRMSE": -1}
{"TrainCount": 24, "MeanTrainLoss": 0.050405347730942116, "MeanValidationLoss": 0.059934615505387985, "FinalMeanRMSE": -1}
{"TrainCount": 24, "MeanTrainLoss": 0.049358016582663186, "MeanValidationLoss": 0.058613639983772135, "FinalMeanRMSE": -1}
{"TrainCount": 24, "MeanTrainLoss": 0.04982378008122929, "MeanValidationLoss": 0.0592214687761054, "FinalMeanRMSE": -1}
{"TrainCount": 24, "MeanTrainLoss": 0.04949005893961398, "MeanValidationLoss": 0.05886787195207484, "FinalMeanRMSE": -1}
{"TrainCount": 24, "MeanTrainLoss": 0.04939157819141171, "MeanValidationLoss": 0.05871496623920568, "FinalMeanRMSE": -1}
{"TrainCount": 24, "MeanTrainLoss": 0.04942713869724445, "MeanValidationLoss": 0.05881688214210143, "FinalMeanRMSE": -1}
{"TrainCount": 24, "MeanTrainLoss": 0.04929768561781524, "MeanValidationLoss": 0.058672893590417254, "FinalMeanRMSE": -1}
{"TrainCount": 24, "MeanTrainLoss": 0.04927747821558021, "MeanValidationLoss": 0.05865301263619618, "FinalMeanRMSE": -1}
{"TrainCount": 24, "MeanTrainLoss": 0.049241697538398695, "MeanValidationLoss": 0.05863169450537268, "FinalMeanRMSE": -1}
{"TrainCount": 24, "MeanTrainLoss": 0.04918883138609503, "MeanValidationLoss": 0.05857819956110184, "FinalMeanRMSE": -1}
{"TrainCount": 24, "MeanTrainLoss": 0.04916630939630691, "MeanValidationLoss": 0.05856002075036606, "FinalMeanRMSE": -1}
{"TrainCount": 24, "MeanTrainLoss": 0.04912744948785462, "MeanValidationLoss": 0.05852308460926435, "FinalMeanRMSE": -1}
{"TrainCount": 24, "MeanTrainLoss": 0.04909947295924147, "MeanValidationLoss": 0.05849823665367552, "FinalMeanRMSE": -1}
{"TrainCount": 24, "MeanTrainLoss": 0.049068997943115804, "MeanValidationLoss": 0.058470357613391186, "FinalMeanRMSE": 0.05847035662776879}
{"TrainCount": 25, "MeanTrainLoss": 0.052413880024023016, "MeanValidationLoss": 0.06812484152394639, "FinalMeanRMSE": -1}
{"TrainCount": 25, "MeanTrainLoss": 0.052284797936107345, "MeanValidationLoss": 0.07061383714513665, "FinalMeanRMSE": -1}
{"TrainCount": 25, "MeanTrainLoss": 0.05207907802402008, "MeanValidationLoss": 0.06964905778243696, "FinalMeanRMSE": -1}
{"TrainCount": 25, "MeanTrainLoss": 0.0518625842322306, "MeanValidationLoss": 0.06976907449008445, "FinalMeanRMSE": -1}
{"TrainCount": 25, "MeanTrainLoss": 0.051898389813299556, "MeanValidationLoss": 0.07017210363989046, "FinalMeanRMSE": -1}
{"TrainCount": 25, "MeanTrainLoss": 0.05181863229167655, "MeanValidationLoss": 0.06996172727168312, "FinalMeanRMSE": -1}
{"TrainCount": 25, "MeanTrainLoss": 0.05182313464790451, "MeanValidationLoss": 0.07030349079321122, "FinalMeanRMSE": -1}
{"TrainCount": 25, "MeanTrainLoss": 0.05179001688298842, "MeanValidationLoss": 0.07027259945164066, "FinalMeanRMSE": -1}
{"TrainCount": 25, "MeanTrainLoss": 0.05177285202911922, "MeanValidationLoss": 0.07044665378755366, "FinalMeanRMSE": -1}
{"TrainCount": 25, "MeanTrainLoss": 0.05175349964528442, "MeanValidationLoss": 0.0705018428170822, "FinalMeanRMSE": -1}
{"TrainCount": 25, "MeanTrainLoss": 0.051732900907698366, "MeanValidationLoss": 0.07059593425964462, "FinalMeanRMSE": -1}
{"TrainCount": 25, "MeanTrainLoss": 0.05171489863709954, "MeanValidationLoss": 0.07068754944222919, "FinalMeanRMSE": -1}
{"TrainCount": 25, "MeanTrainLoss": 0.05169504293856459, "MeanValidationLoss": 0.07075959084742874, "FinalMeanRMSE": -1}
{"TrainCount": 25, "MeanTrainLoss": 0.0516768783791778, "MeanValidationLoss": 0.07085616317902796, "FinalMeanRMSE": -1}
{"TrainCount": 25, "MeanTrainLoss": 0.05165756564033225, "MeanValidationLoss": 0.07093810867628403, "FinalMeanRMSE": 0.07093810933617371}
{"TrainCount": 26, "MeanTrainLoss": 0.05755310681233769, "MeanValidationLoss": 0.07577765236298244, "FinalMeanRMSE": -1}
{"TrainCount": 26, "MeanTrainLoss": 0.05663563149304547, "MeanValidationLoss": 0.07573248942693074, "FinalMeanRMSE": -1}
{"TrainCount": 26, "MeanTrainLoss": 0.05519017706304978, "MeanValidationLoss": 0.07743267502103533, "FinalMeanRMSE": -1}
{"TrainCount": 26, "MeanTrainLoss": 0.05455220567248364, "MeanValidationLoss": 0.07593554293825514, "FinalMeanRMSE": -1}
{"TrainCount": 26, "MeanTrainLoss": 0.054372753311024244, "MeanValidationLoss": 0.07634734282536167, "FinalMeanRMSE": -1}
{"TrainCount": 26, "MeanTrainLoss": 0.05389942302080721, "MeanValidationLoss": 0.07627009955190477, "FinalMeanRMSE": -1}
{"TrainCount": 26, "MeanTrainLoss": 0.053633868849938475, "MeanValidationLoss": 0.07614628881925628, "FinalMeanRMSE": -1}
{"TrainCount": 26, "MeanTrainLoss": 0.05334202780089776, "MeanValidationLoss": 0.07624039444046848, "FinalMeanRMSE": -1}
{"TrainCount": 26, "MeanTrainLoss": 0.05309306825520023, "MeanValidationLoss": 0.07613673806190491, "FinalMeanRMSE": -1}
{"TrainCount": 26, "MeanTrainLoss": 0.05288168107288241, "MeanValidationLoss": 0.07614811119579133, "FinalMeanRMSE": -1}
{"TrainCount": 26, "MeanTrainLoss": 0.05268113803660586, "MeanValidationLoss": 0.0761053864178913, "FinalMeanRMSE": -1}
{"TrainCount": 26, "MeanTrainLoss": 0.05250949988809336, "MeanValidationLoss": 0.07608403939576376, "FinalMeanRMSE": -1}
{"TrainCount": 26, "MeanTrainLoss": 0.05235316959352838, "MeanValidationLoss": 0.07605722617535364, "FinalMeanRMSE": -1}
{"TrainCount": 26, "MeanTrainLoss": 0.052211046635926066, "MeanValidationLoss": 0.07606619454565502, "FinalMeanRMSE": -1}
{"TrainCount": 26, "MeanTrainLoss": 0.05206734127529319, "MeanValidationLoss": 0.07611656863064993, "FinalMeanRMSE": 0.07611656758932075}
{"TrainCount": 27, "MeanTrainLoss": 0.06223855110663937, "MeanValidationLoss": 0.0630867411108578, "FinalMeanRMSE": -1}
{"TrainCount": 27, "MeanTrainLoss": 0.060872612439749126, "MeanValidationLoss": 0.06303525352302719, "FinalMeanRMSE": -1}
{"TrainCount": 27, "MeanTrainLoss": 0.05962666312858495, "MeanValidationLoss": 0.0632508107844521, "FinalMeanRMSE": -1}
{"TrainCount": 27, "MeanTrainLoss": 0.059689737525720855, "MeanValidationLoss": 0.06302765222156749, "FinalMeanRMSE": -1}
{"TrainCount": 27, "MeanTrainLoss": 0.05909085718507157, "MeanValidationLoss": 0.0630218266564257, "FinalMeanRMSE": -1}
{"TrainCount": 27, "MeanTrainLoss": 0.05888450919431641, "MeanValidationLoss": 0.06300636792884154, "FinalMeanRMSE": -1}
{"TrainCount": 27, "MeanTrainLoss": 0.05867021443938637, "MeanValidationLoss": 0.06300793645136496, "FinalMeanRMSE": -1}
{"TrainCount": 27, "MeanTrainLoss": 0.05845474014583686, "MeanValidationLoss": 0.06300283662207863, "FinalMeanRMSE": -1}
{"TrainCount": 27, "MeanTrainLoss": 0.058352551634367526, "MeanValidationLoss": 0.06301689253133887, "FinalMeanRMSE": -1}
{"TrainCount": 27, "MeanTrainLoss": 0.05822487203571346, "MeanValidationLoss": 0.06301766660283593, "FinalMeanRMSE": -1}
{"TrainCount": 27, "MeanTrainLoss": 0.05815484344285653, "MeanValidationLoss": 0.06302894441520467, "FinalMeanRMSE": -1}
{"TrainCount": 27, "MeanTrainLoss": 0.0580865300496042, "MeanValidationLoss": 0.0630345749504426, "FinalMeanRMSE": -1}
{"TrainCount": 27, "MeanTrainLoss": 0.05803866911574511, "MeanValidationLoss": 0.06304157910978093, "FinalMeanRMSE": -1}
{"TrainCount": 27, "MeanTrainLoss": 0.057997349722959966, "MeanValidationLoss": 0.06304515017306103, "FinalMeanRMSE": -1}
{"TrainCount": 27, "MeanTrainLoss": 0.057961697015729986, "MeanValidationLoss": 0.06304787975900314, "FinalMeanRMSE": 0.06304787861770102}
{"TrainCount": 28, "MeanTrainLoss": 0.06279740178946815, "MeanValidationLoss": 0.05085969750964364, "FinalMeanRMSE": -1}
{"TrainCount": 28, "MeanTrainLoss": 0.062397420018739096, "MeanValidationLoss": 0.04946587182754694, "FinalMeanRMSE": -1}
{"TrainCount": 28, "MeanTrainLoss": 0.06227120246759729, "MeanValidationLoss": 0.049572340970815615, "FinalMeanRMSE": -1}
{"TrainCount": 28, "MeanTrainLoss": 0.06222115177122844, "MeanValidationLoss": 0.04977115438601305, "FinalMeanRMSE": -1}
{"TrainCount": 28, "MeanTrainLoss": 0.0621193808239664, "MeanValidationLoss": 0.049588348196689475, "FinalMeanRMSE": -1}
{"TrainCount": 28, "MeanTrainLoss": 0.06210077566907585, "MeanValidationLoss": 0.04971206292163494, "FinalMeanRMSE": -1}
{"TrainCount": 28, "MeanTrainLoss": 0.062050433689459214, "MeanValidationLoss": 0.04969334494062634, "FinalMeanRMSE": -1}
{"TrainCount": 28, "MeanTrainLoss": 0.062012126421652776, "MeanValidationLoss": 0.04970922485687012, "FinalMeanRMSE": -1}
{"TrainCount": 28, "MeanTrainLoss": 0.06197813790657617, "MeanValidationLoss": 0.04974619814649571, "FinalMeanRMSE": -1}
{"TrainCount": 28, "MeanTrainLoss": 0.061940337192116446, "MeanValidationLoss": 0.04976114214852799, "FinalMeanRMSE": -1}
{"TrainCount": 28, "MeanTrainLoss": 0.06190830329163915, "MeanValidationLoss": 0.04979580398215804, "FinalMeanRMSE": -1}
{"TrainCount": 28, "MeanTrainLoss": 0.06187171807695675, "MeanValidationLoss": 0.04982601054186045, "FinalMeanRMSE": -1}
{"TrainCount": 28, "MeanTrainLoss": 0.06183685336498856, "MeanValidationLoss": 0.04985854731396187, "FinalMeanRMSE": -1}
{"TrainCount": 28, "MeanTrainLoss": 0.06180353893365474, "MeanValidationLoss": 0.04989520607646122, "FinalMeanRMSE": -1}
{"TrainCount": 28, "MeanTrainLoss": 0.06177001424952049, "MeanValidationLoss": 0.04993046973940245, "FinalMeanRMSE": 0.04993047097823084}
{"TrainCount": 29, "MeanTrainLoss": 0.06115832042737599, "MeanValidationLoss": 0.07373632904556063, "FinalMeanRMSE": -1}
{"TrainCount": 29, "MeanTrainLoss": 0.05820031742001102, "MeanValidationLoss": 0.0723812018700859, "FinalMeanRMSE": -1}
{"TrainCount": 29, "MeanTrainLoss": 0.05714756537527933, "MeanValidationLoss": 0.0687559460513076, "FinalMeanRMSE": -1}
{"TrainCount": 29, "MeanTrainLoss": 0.057416413985464695, "MeanValidationLoss": 0.07170685030634336, "FinalMeanRMSE": -1}
{"TrainCount": 29, "MeanTrainLoss": 0.057094786191073645, "MeanValidationLoss": 0.06943434746445794, "FinalMeanRMSE": -1}
{"TrainCount": 29, "MeanTrainLoss": 0.05718071666838479, "MeanValidationLoss": 0.07044639826169488, "FinalMeanRMSE": -1}
{"TrainCount": 29, "MeanTrainLoss": 0.057092794591057906, "MeanValidationLoss": 0.06993616677341405, "FinalMeanRMSE": -1}
{"TrainCount": 29, "MeanTrainLoss": 0.057057435419002586, "MeanValidationLoss": 0.0699394329162369, "FinalMeanRMSE": -1}
{"TrainCount": 29, "MeanTrainLoss": 0.05704086555072861, "MeanValidationLoss": 0.07000886483324899, "FinalMeanRMSE": -1}
{"TrainCount": 29, "MeanTrainLoss": 0.05698865866900361, "MeanValidationLoss": 0.06981336791612948, "FinalMeanRMSE": -1}
{"TrainCount": 29, "MeanTrainLoss": 0.0569749251225569, "MeanValidationLoss": 0.06989141224681983, "FinalMeanRMSE": -1}
{"TrainCount": 29, "MeanTrainLoss": 0.05693768978010129, "MeanValidationLoss": 0.06980974445043252, "FinalMeanRMSE": -1}
{"TrainCount": 29, "MeanTrainLoss": 0.056912948767634204, "MeanValidationLoss": 0.06981410593752972, "FinalMeanRMSE": -1}
{"TrainCount": 29, "MeanTrainLoss": 0.05688391776524321, "MeanValidationLoss": 0.06979402501070708, "FinalMeanRMSE": -1}
{"TrainCount": 29, "MeanTrainLoss": 0.056855681391745586, "MeanValidationLoss": 0.06976656300936178, "FinalMeanRMSE": 0.06976656370764002}
{"TrainCount": 30, "MeanTrainLoss": 2.1699761207552926, "MeanValidationLoss": 1.9514667350192403, "FinalMeanRMSE": -1}
{"TrainCount": 30, "MeanTrainLoss": 1.6088264600090358, "MeanValidationLoss": 1.3409393110940622, "FinalMeanRMSE": -1}
{"TrainCount": 30, "MeanTrainLoss": 1.2150915128597315, "MeanValidationLoss": 0.9935082335804784, "FinalMeanRMSE": -1}
{"TrainCount": 30, "MeanTrainLoss": 1.0286796010058858, "MeanValidationLoss": 0.8716032846375953, "FinalMeanRMSE": -1}
{"TrainCount": 30, "MeanTrainLoss": 0.9872816221437593, "MeanValidationLoss": 0.860276845825273, "FinalMeanRMSE": -1}
{"TrainCount": 30, "MeanTrainLoss": 0.9765055388644122, "MeanValidationLoss": 0.8524971886776215, "FinalMeanRMSE": -1}
{"TrainCount": 30, "MeanTrainLoss": 0.9658719613068346, "MeanValidationLoss": 0.8429782061382781, "FinalMeanRMSE": -1}
{"TrainCount": 30, "MeanTrainLoss": 0.955335445507713, "MeanValidationLoss": 0.8349194207856822, "FinalMeanRMSE": -1}
{"TrainCount": 30, "MeanTrainLoss": 0.9450557319150454, "MeanValidationLoss": 0.826978747754596, "FinalMeanRMSE": -1}
{"TrainCount": 30, "MeanTrainLoss": 0.9348598640897999, "MeanValidationLoss": 0.8185695418438246, "FinalMeanRMSE": -1}
{"TrainCount": 30, "MeanTrainLoss": 0.9247534905654796, "MeanValidationLoss": 0.8105139786074328, "FinalMeanRMSE": -1}
{"TrainCount": 30, "MeanTrainLoss": 0.9148267090320588, "MeanValidationLoss": 0.802278510273196, "FinalMeanRMSE": -1}
{"TrainCount": 30, "MeanTrainLoss": 0.9049601706905641, "MeanValidationLoss": 0.7943432743466178, "FinalMeanRMSE": -1}
{"TrainCount": 30, "MeanTrainLoss": 0.8952022005682406, "MeanValidationLoss": 0.7865671315338723, "FinalMeanRMSE": -1}
{"TrainCount": 30, "MeanTrainLoss": 0.8855874230896217, "MeanValidationLoss": 0.7789246433869351, "FinalMeanRMSE": 0.7789247308928646}
{"TrainCount": 31, "MeanTrainLoss": 0.7063953749360271, "MeanValidationLoss": 0.6398729310316198, "FinalMeanRMSE": -1}
{"TrainCount": 31, "MeanTrainLoss": 0.41545299788571, "MeanValidationLoss": 0.32407010706032024, "FinalMeanRMSE": -1}
{"TrainCount": 31, "MeanTrainLoss": 0.19492682862666347, "MeanValidationLoss": 0.13464617764248568, "FinalMeanRMSE": -1}
{"TrainCount": 31, "MeanTrainLoss": 0.08393322060545606, "MeanValidationLoss": 0.06398020421757418, "FinalMeanRMSE": -1}
{"TrainCount": 31, "MeanTrainLoss": 0.05794741038254891, "MeanValidationLoss": 0.060370172253426384, "FinalMeanRMSE": -1}
{"TrainCount": 31, "MeanTrainLoss": 0.05789025486214769, "MeanValidationLoss": 0.05894418954849243, "FinalMeanRMSE": -1}
{"TrainCount": 31, "MeanTrainLoss": 0.05673072557033332, "MeanValidationLoss": 0.059259925147189814, "FinalMeanRMSE": -1}
{"TrainCount": 31, "MeanTrainLoss": 0.05673549836091806, "MeanValidationLoss": 0.05804279898019398, "FinalMeanRMSE": -1}
{"TrainCount": 31, "MeanTrainLoss": 0.056623584784764, "MeanValidationLoss": 0.05787790654336705, "FinalMeanRMSE": -1}
{"TrainCount": 31, "MeanTrainLoss": 0.056482058665728814, "MeanValidationLoss": 0.05760972622562857, "FinalMeanRMSE": -1}
{"TrainCount": 31, "MeanTrainLoss": 0.05644873204665624, "MeanValidationLoss": 0.057137256071848025, "FinalMeanRMSE": -1}
{"TrainCount": 31, "MeanTrainLoss": 0.05638514387576986, "MeanValidationLoss": 0.05695821513586184, "FinalMeanRMSE": -1}
{"TrainCount": 31, "MeanTrainLoss": 0.05632419420455383, "MeanValidationLoss": 0.056705251774367166, "FinalMeanRMSE": -1}
{"TrainCount": 31, "MeanTrainLoss": 0.05628971054418083, "MeanValidationLoss": 0.05646666314672021, "FinalMeanRMSE": -1}
{"TrainCount": 31, "MeanTrainLoss": 0.05624512635182338, "MeanValidationLoss": 0.05631183889858863, "FinalMeanRMSE": 0.05631183937892278}
{"TrainCount": 32, "MeanTrainLoss": 0.0630846909350819, "MeanValidationLoss": 0.05255197519055235, "FinalMeanRMSE": -1}
{"TrainCount": 32, "MeanTrainLoss": 0.06268451140637983, "MeanValidationLoss": 0.0525625328048628, "FinalMeanRMSE": -1}
{"TrainCount": 32, "MeanTrainLoss": 0.06238572504262478, "MeanValidationLoss": 0.05254991875405897, "FinalMeanRMSE": -1}
{"TrainCount": 32, "MeanTrainLoss": 0.06200428276556974, "MeanValidationLoss": 0.05253039248156966, "FinalMeanRMSE": -1}
{"TrainCount": 32, "MeanTrainLoss": 0.06172064622068963, "MeanValidationLoss": 0.052529937168310954, "FinalMeanRMSE": -1}
{"TrainCount": 32, "MeanTrainLoss": 0.061489279899332255, "MeanValidationLoss": 0.05256087524674789, "FinalMeanRMSE": -1}
{"TrainCount": 32, "MeanTrainLoss": 0.06128269381690444, "MeanValidationLoss": 0.05256894078345327, "FinalMeanRMSE": -1}
{"TrainCount": 32, "MeanTrainLoss": 0.06111986813140891, "MeanValidationLoss": 0.0525877926259013, "FinalMeanRMSE": -1}
{"TrainCount": 32, "MeanTrainLoss": 0.06098859478332843, "MeanValidationLoss": 0.05261471499389375, "FinalMeanRMSE": -1}
{"TrainCount": 32, "MeanTrainLoss": 0.06087956777964419, "MeanValidationLoss": 0.052633548672828406, "FinalMeanRMSE": -1}
{"TrainCount": 32, "MeanTrainLoss": 0.06079103139757413, "MeanValidationLoss": 0.0526526316521112, "FinalMeanRMSE": -1}
{"TrainCount": 32, "MeanTrainLoss": 0.06071573147299694, "MeanValidationLoss": 0.05267222212594852, "FinalMeanRMSE": -1}
{"TrainCount": 32, "MeanTrainLoss": 0.060651250357864894, "MeanValidationLoss": 0.05268606322419922, "FinalMeanRMSE": -1}
{"TrainCount": 32, "MeanTrainLoss": 0.060593716713071566, "MeanValidationLoss": 0.05269772189053876, "FinalMeanRMSE": -1}
{"TrainCount": 32, "MeanTrainLoss": 0.060542094690060756, "MeanValidationLoss": 0.05270870332742295, "FinalMeanRMSE": 0.05270870196646566}
{"TrainCount": 33, "MeanTrainLoss": 0.059898771690150905, "MeanValidationLoss": 0.06338048958881742, "FinalMeanRMSE": -1}
{"TrainCount": 33, "MeanTrainLoss": 0.05956512917845235, "MeanValidationLoss": 0.06395432288419305, "FinalMeanRMSE": -1}
{"TrainCount": 33, "MeanTrainLoss": 0.05922502718564403, "MeanValidationLoss": 0.06415849110122361, "FinalMeanRMSE": -1}
{"TrainCount": 33, "MeanTrainLoss": 0.059168620261153736, "MeanValidationLoss": 0.0637448973135452, "FinalMeanRMSE": -1}
{"TrainCount": 33, "MeanTrainLoss": 0.05912369394922532, "MeanValidationLoss": 0.06407844335529846, "FinalMeanRMSE": -1}
{"TrainCount": 33, "MeanTrainLoss": 0.059075336838733256, "MeanValidationLoss": 0.06389293040154297, "FinalMeanRMSE": -1}
{"TrainCount": 33, "MeanTrainLoss": 0.0590466132139884, "MeanValidationLoss": 0.06396783776365952, "FinalMeanRMSE": -1}
{"TrainCount": 33, "MeanTrainLoss": 0.0590032774072162, "MeanValidationLoss": 0.06397088393138323, "FinalMeanRMSE": -1}
{"TrainCount": 33, "MeanTrainLoss": 0.05897093396310862, "MeanValidationLoss": 0.06395961841665251, "FinalMeanRMSE": -1}
{"TrainCount": 33, "MeanTrainLoss": 0.058934999511421074, "MeanValidationLoss": 0.06398045969319481, "FinalMeanRMSE": -1}
{"TrainCount": 33, "MeanTrainLoss": 0.058900124506454245, "MeanValidationLoss": 0.06397248218858863, "FinalMeanRMSE": -1}
{"TrainCount": 33, "MeanTrainLoss": 0.05886694866453292, "MeanValidationLoss": 0.06397998320057213, "FinalMeanRMSE": -1}
{"TrainCount": 33, "MeanTrainLoss": 0.05883317427828133, "MeanValidationLoss": 0.06398186836973091, "FinalMeanRMSE": -1}
{"TrainCount": 33, "MeanTrainLoss": 0.05880074151334046, "MeanValidationLoss": 0.06398158066103914, "FinalMeanRMSE": -1}
{"TrainCount": 33, "MeanTrainLoss": 0.05876797928630961, "MeanValidationLoss": 0.06398593722654215, "FinalMeanRMSE": 0.06398593696302401}
{"TrainCount": 34, "MeanTrainLoss": 0.061703172602823805, "MeanValidationLoss": 0.06850508703240032, "FinalMeanRMSE": -1}
{"TrainCount": 34, "MeanTrainLoss": 0.06019134630049978, "MeanValidationLoss": 0.06879257886060353, "FinalMeanRMSE": -1}
{"TrainCount": 34, "MeanTrainLoss": 0.06012276159865516, "MeanValidationLoss": 0.06806797474280171, "FinalMeanRMSE": -1}
{"TrainCount": 34, "MeanTrainLoss": 0.05995361922042711, "MeanValidationLoss": 0.068274959236726, "FinalMeanRMSE": -1}
{"TrainCount": 34, "MeanTrainLoss": 0.05980135236467634, "MeanValidationLoss": 0.06824290110119458, "FinalMeanRMSE": -1}
{"TrainCount": 34, "MeanTrainLoss": 0.059822695297854285, "MeanValidationLoss": 0.06811609003564408, "FinalMeanRMSE": -1}
{"TrainCount": 34, "MeanTrainLoss": 0.059741546596799575, "MeanValidationLoss": 0.0682025819417389, "FinalMeanRMSE": -1}
{"TrainCount": 34, "MeanTrainLoss": 0.05968431606888771, "MeanValidationLoss": 0.06817983938702221, "FinalMeanRMSE": -1}
{"TrainCount": 34, "MeanTrainLoss": 0.05965446878756796, "MeanValidationLoss": 0.0681569057720146, "FinalMeanRMSE": -1}
{"TrainCount": 34, "MeanTrainLoss": 0.059603355463062016, "MeanValidationLoss": 0.06818027764387515, "FinalMeanRMSE": -1}
{"TrainCount": 34, "MeanTrainLoss": 0.059558424523898534, "MeanValidationLoss": 0.06817187942650127, "FinalMeanRMSE": -1}
{"TrainCount": 34, "MeanTrainLoss": 0.05951938795191901, "MeanValidationLoss": 0.06816886408233094, "FinalMeanRMSE": -1}
{"TrainCount": 34, "MeanTrainLoss": 0.059477213280541556, "MeanValidationLoss": 0.0681735500265127, "FinalMeanRMSE": -1}
{"TrainCount": 34, "MeanTrainLoss": 0.059436444086687905, "MeanValidationLoss": 0.0681700223906972, "FinalMeanRMSE": -1}
{"TrainCount": 34, "MeanTrainLoss": 0.05939857957618577, "MeanValidationLoss": 0.06817172853083446, "FinalMeanRMSE": 0.06817172779922157}
{"TrainCount": 35, "MeanTrainLoss": 0.059537787138102864, "MeanValidationLoss": 0.07015636162284543, "FinalMeanRMSE": -1}
{"TrainCount": 35, "MeanTrainLoss": 0.0586180075806143, "MeanValidationLoss": 0.06902301940409576, "FinalMeanRMSE": -1}
{"TrainCount": 35, "MeanTrainLoss": 0.05855657779522754, "MeanValidationLoss": 0.06894133800969404, "FinalMeanRMSE": -1}
{"TrainCount": 35, "MeanTrainLoss": 0.05851346567251259, "MeanValidationLoss": 0.06934188104727688, "FinalMeanRMSE": -1}
{"TrainCount": 35, "MeanTrainLoss": 0.05841813780225146, "MeanValidationLoss": 0.06892387150403331, "FinalMeanRMSE": -1}
{"TrainCount": 35, "MeanTrainLoss": 0.0584329294038064, "MeanValidationLoss": 0.0692253407310037, "FinalMeanRMSE": -1}
{"TrainCount": 35, "MeanTrainLoss": 0.058359361495740614, "MeanValidationLoss": 0.06900174595853861, "FinalMeanRMSE": -1}
{"TrainCount": 35, "MeanTrainLoss": 0.05835216613855656, "MeanValidationLoss": 0.06911930963397026, "FinalMeanRMSE": -1}
{"TrainCount": 35, "MeanTrainLoss": 0.058306387167495075, "MeanValidationLoss": 0.06903826192240504, "FinalMeanRMSE": -1}
{"TrainCount": 35, "MeanTrainLoss": 0.05828333907540499, "MeanValidationLoss": 0.06906155663378098, "FinalMeanRMSE": -1}
{"TrainCount": 35, "MeanTrainLoss": 0.05825057531681005, "MeanValidationLoss": 0.06903220195980633, "FinalMeanRMSE": -1}
{"TrainCount": 35, "MeanTrainLoss": 0.05822352592377936, "MeanValidationLoss": 0.06903243468088262, "FinalMeanRMSE": -1}
{"TrainCount": 35, "MeanTrainLoss": 0.058193180989063786, "MeanValidationLoss": 0.0690116991453311, "FinalMeanRMSE": -1}
{"TrainCount": 35, "MeanTrainLoss": 0.058166382793287875, "MeanValidationLoss": 0.06900810616857865, "FinalMeanRMSE": -1}
{"TrainCount": 35, "MeanTrainLoss": 0.058136757206111576, "MeanValidationLoss": 0.06898929178714752, "FinalMeanRMSE": 0.0689892902681179}
{"TrainCount": 36, "MeanTrainLoss": 0.06047482344973294, "MeanValidationLoss": 0.05983867147409847, "FinalMeanRMSE": -1}
{"TrainCount": 36, "MeanTrainLoss": 0.059323162335708654, "MeanValidationLoss": 0.06051201485312743, "FinalMeanRMSE": -1}
{"TrainCount": 36, "MeanTrainLoss": 0.05965503824153388, "MeanValidationLoss": 0.0597982145956922, "FinalMeanRMSE": -1}
{"TrainCount": 36, "MeanTrainLoss": 0.05947739021540377, "MeanValidationLoss": 0.05979603690477465, "FinalMeanRMSE": -1}
{"TrainCount": 36, "MeanTrainLoss": 0.05927135213951155, "MeanValidationLoss": 0.05992337587596364, "FinalMeanRMSE": -1}
{"TrainCount": 36, "MeanTrainLoss": 0.059322104611665524, "MeanValidationLoss": 0.05987676034945284, "FinalMeanRMSE": -1}
{"TrainCount": 36, "MeanTrainLoss": 0.0593138097898464, "MeanValidationLoss": 0.05984296783201956, "FinalMeanRMSE": -1}
{"TrainCount": 36, "MeanTrainLoss": 0.05925167330427666, "MeanValidationLoss": 0.05986540036738953, "FinalMeanRMSE": -1}
{"TrainCount": 36, "MeanTrainLoss": 0.059225813372631296, "MeanValidationLoss": 0.0598719552417711, "FinalMeanRMSE": -1}
{"TrainCount": 36, "MeanTrainLoss": 0.05920767797038734, "MeanValidationLoss": 0.05986262660882721, "FinalMeanRMSE": -1}
{"TrainCount": 36, "MeanTrainLoss": 0.05917788049303038, "MeanValidationLoss": 0.05986304408897554, "FinalMeanRMSE": -1}
{"TrainCount": 36, "MeanTrainLoss": 0.05914850175552974, "MeanValidationLoss": 0.059865662989588835, "FinalMeanRMSE": -1}
{"TrainCount": 36, "MeanTrainLoss": 0.05912270041645607, "MeanValidationLoss": 0.05986666911943799, "FinalMeanRMSE": -1}
{"TrainCount": 36, "MeanTrainLoss": 0.05909719406438701, "MeanValidationLoss": 0.05986587998236535, "FinalMeanRMSE": -1}
{"TrainCount": 36, "MeanTrainLoss": 0.059070875146830015, "MeanValidationLoss": 0.05986780509611086, "FinalMeanRMSE": 0.059867804650131785}
{"TrainCount": 37, "MeanTrainLoss": 2.077263786613597, "MeanValidationLoss": 1.1123123603060066, "FinalMeanRMSE": -1}
{"TrainCount": 37, "MeanTrainLoss": 1.6657999016646017, "MeanValidationLoss": 0.626026332722923, "FinalMeanRMSE": -1}
{"TrainCount": 37, "MeanTrainLoss": 1.332849271035608, "MeanValidationLoss": 0.3047323418145924, "FinalMeanRMSE": -1}
{"TrainCount": 37, "MeanTrainLoss": 1.139267274754585, "MeanValidationLoss": 0.15120138736129496, "FinalMeanRMSE": -1}
{"TrainCount": 37, "MeanTrainLoss": 1.0664497984282544, "MeanValidationLoss": 0.12039917983071652, "FinalMeanRMSE": -1}
{"TrainCount": 37, "MeanTrainLoss": 1.0534921166180187, "MeanValidationLoss": 0.11992383115208907, "FinalMeanRMSE": -1}
{"TrainCount": 37, "MeanTrainLoss": 1.0421915784736588, "MeanValidationLoss": 0.12105981940995751, "FinalMeanRMSE": -1}
{"TrainCount": 37, "MeanTrainLoss": 1.031982188279918, "MeanValidationLoss": 0.11910737267119346, "FinalMeanRMSE": -1}
{"TrainCount": 37, "MeanTrainLoss": 1.021669276704678, "MeanValidationLoss": 0.11932346263545097, "FinalMeanRMSE": -1}
{"TrainCount": 37, "MeanTrainLoss": 1.0115086158920574, "MeanValidationLoss": 0.11827846939508625, "FinalMeanRMSE": -1}
{"TrainCount": 37, "MeanTrainLoss": 1.0013083998178471, "MeanValidationLoss": 0.11805660016107981, "FinalMeanRMSE": -1}
{"TrainCount": 37, "MeanTrainLoss": 0.9912358748085927, "MeanValidationLoss": 0.11735397865834264, "FinalMeanRMSE": -1}
{"TrainCount": 37, "MeanTrainLoss": 0.9812089824952142, "MeanValidationLoss": 0.11695338863168837, "FinalMeanRMSE": -1}
{"TrainCount": 37, "MeanTrainLoss": 0.9713035341287624, "MeanValidationLoss": 0.11637290405658628, "FinalMeanRMSE": -1}
{"TrainCount": 37, "MeanTrainLoss": 0.9614694826520247, "MeanValidationLoss": 0.1159136166763788, "FinalMeanRMSE": 0.11591362672063983}
{"TrainCount": 38, "MeanTrainLoss": 0.6558494352632098, "MeanValidationLoss": 0.6453810351633886, "FinalMeanRMSE": -1}
{"TrainCount": 38, "MeanTrainLoss": 0.413523790257716, "MeanValidationLoss": 0.35986796073746263, "FinalMeanRMSE": -1}
{"TrainCount": 38, "MeanTrainLoss": 0.2227659025038892, "MeanValidationLoss": 0.17090786095948246, "FinalMeanRMSE": -1}
{"TrainCount": 38, "MeanTrainLoss": 0.11070931999132647, "MeanValidationLoss": 0.07679854829016833, "FinalMeanRMSE": -1}
{"TrainCount": 38, "MeanTrainLoss": 0.06735828335870776, "MeanValidationLoss": 0.05530494551735315, "FinalMeanRMSE": -1}
{"TrainCount": 38, "MeanTrainLoss": 0.06389622385913168, "MeanValidationLoss": 0.0559259850902167, "FinalMeanRMSE": -1}
{"TrainCount": 38, "MeanTrainLoss": 0.06305949342006828, "MeanValidationLoss": 0.055701283443915214, "FinalMeanRMSE": -1}
{"TrainCount": 38, "MeanTrainLoss": 0.06273171371012404, "MeanValidationLoss": 0.05529639731591556, "FinalMeanRMSE": -1}
{"TrainCount": 38, "MeanTrainLoss": 0.06266697561531737, "MeanValidationLoss": 0.05528597406258708, "FinalMeanRMSE": -1}
{"TrainCount": 38, "MeanTrainLoss": 0.0624666716358815, "MeanValidationLoss": 0.05532552776803747, "FinalMeanRMSE": -1}
{"TrainCount": 38, "MeanTrainLoss": 0.06235530262279232, "MeanValidationLoss": 0.05527682964041916, "FinalMeanRMSE": -1}
{"TrainCount": 38, "MeanTrainLoss": 0.062257744023325845, "MeanValidationLoss": 0.055280077744994244, "FinalMeanRMSE": -1}
{"TrainCount": 38, "MeanTrainLoss": 0.06214510836796454, "MeanValidationLoss": 0.05527061650976103, "FinalMeanRMSE": -1}
{"TrainCount": 38, "MeanTrainLoss": 0.0620554428090129, "MeanValidationLoss": 0.055262531801971077, "FinalMeanRMSE": -1}
{"TrainCount": 38, "MeanTrainLoss": 0.06196526481568465, "MeanValidationLoss": 0.05525699216458532, "FinalMeanRMSE": 0.055256991603778574}
{"TrainCount": 39, "MeanTrainLoss": 0.056377051839594204, "MeanValidationLoss": 0.06155164037332978, "FinalMeanRMSE": -1}
{"TrainCount": 39, "MeanTrainLoss": 0.05625255573863928, "MeanValidationLoss": 0.062376489646213, "FinalMeanRMSE": -1}
{"TrainCount": 39, "MeanTrainLoss": 0.05627909642940312, "MeanValidationLoss": 0.06199148678502371, "FinalMeanRMSE": -1}
{"TrainCount": 39, "MeanTrainLoss": 0.05623392853347552, "MeanValidationLoss": 0.06204843746368275, "FinalMeanRMSE": -1}
{"TrainCount": 39, "MeanTrainLoss": 0.05623180457966865, "MeanValidationLoss": 0.06210550353970638, "FinalMeanRMSE": -1}
{"TrainCount": 39, "MeanTrainLoss": 0.05622027174844218, "MeanValidationLoss": 0.06203616029301355, "FinalMeanRMSE": -1}
{"TrainCount": 39, "MeanTrainLoss": 0.056208249267642896, "MeanValidationLoss": 0.06211117204538612, "FinalMeanRMSE": -1}
{"TrainCount": 39, "MeanTrainLoss": 0.05620145530714465, "MeanValidationLoss": 0.06208811570392098, "FinalMeanRMSE": -1}
{"TrainCount": 39, "MeanTrainLoss": 0.05619027271780665, "MeanValidationLoss": 0.06211100228477356, "FinalMeanRMSE": -1}
{"TrainCount": 39, "MeanTrainLoss": 0.05618191770993905, "MeanValidationLoss": 0.06212591570477153, "FinalMeanRMSE": -1}
{"TrainCount": 39, "MeanTrainLoss": 0.056172738659244055, "MeanValidationLoss": 0.062133138068020344, "FinalMeanRMSE": -1}
{"TrainCount": 39, "MeanTrainLoss": 0.056162768038194304, "MeanValidationLoss": 0.06215103273821432, "FinalMeanRMSE": -1}
{"TrainCount": 39, "MeanTrainLoss": 0.056154282149896456, "MeanValidationLoss": 0.06216075431642144, "FinalMeanRMSE": -1}
{"TrainCount": 39, "MeanTrainLoss": 0.05614472197831711, "MeanValidationLoss": 0.062176193175620814, "FinalMeanRMSE": -1}
{"TrainCount": 39, "MeanTrainLoss": 0.05613542175878679, "MeanValidationLoss": 0.06218810110937718, "FinalMeanRMSE": 0.062188100086778116}
{"TrainCount": 40, "MeanTrainLoss": 0.06117753675857256, "MeanValidationLoss": 0.07322159981311754, "FinalMeanRMSE": -1}
{"TrainCount": 40, "MeanTrainLoss": 0.05988371346232503, "MeanValidationLoss": 0.07382419376179229, "FinalMeanRMSE": -1}
{"TrainCount": 40, "MeanTrainLoss": 0.060093724883573, "MeanValidationLoss": 0.07268352278096732, "FinalMeanRMSE": -1}
{"TrainCount": 40, "MeanTrainLoss": 0.05959683258173078, "MeanValidationLoss": 0.07242246266714363, "FinalMeanRMSE": -1}
{"TrainCount": 40, "MeanTrainLoss": 0.0592576922892138, "MeanValidationLoss": 0.07221147885849309, "FinalMeanRMSE": -1}
{"TrainCount": 40, "MeanTrainLoss": 0.05931870249468227, "MeanValidationLoss": 0.07195220740382062, "FinalMeanRMSE": -1}
{"TrainCount": 40, "MeanTrainLoss": 0.059213708999545075, "MeanValidationLoss": 0.07175110592398533, "FinalMeanRMSE": -1}
{"TrainCount": 40, "MeanTrainLoss": 0.05906630645311156, "MeanValidationLoss": 0.07158085916104705, "FinalMeanRMSE": -1}
{"TrainCount": 40, "MeanTrainLoss": 0.059007461854191715, "MeanValidationLoss": 0.07142851241799288, "FinalMeanRMSE": -1}
{"TrainCount": 40, "MeanTrainLoss": 0.058946836479874545, "MeanValidationLoss": 0.07129620864640834, "FinalMeanRMSE": -1}
{"TrainCount": 40, "MeanTrainLoss": 0.0588693821499514, "MeanValidationLoss": 0.07118224681809891, "FinalMeanRMSE": -1}
{"TrainCount": 40, "MeanTrainLoss": 0.05880859797430593, "MeanValidationLoss": 0.07108186497244724, "FinalMeanRMSE": -1}
{"TrainCount": 40, "MeanTrainLoss": 0.058758411209943684, "MeanValidationLoss": 0.07099805789631466, "FinalMeanRMSE": -1}
{"TrainCount": 40, "MeanTrainLoss": 0.05870610874059588, "MeanValidationLoss": 0.07092598652423815, "FinalMeanRMSE": -1}
{"TrainCount": 40, "MeanTrainLoss": 0.05865977565909541, "MeanValidationLoss": 0.07086285091070242, "FinalMeanRMSE": 0.07086285286566577}
{"TrainCount": 41, "MeanTrainLoss": 0.07378499782837959, "MeanValidationLoss": 0.0602330485380244, "FinalMeanRMSE": -1}
{"TrainCount": 41, "MeanTrainLoss": 0.06077197033222471, "MeanValidationLoss": 0.05794603655906929, "FinalMeanRMSE": -1}
{"TrainCount": 41, "MeanTrainLoss": 0.06111420100953008, "MeanValidationLoss": 0.05714863251851893, "FinalMeanRMSE": -1}
{"TrainCount": 41, "MeanTrainLoss": 0.060762087569987584, "MeanValidationLoss": 0.05694860434052588, "FinalMeanRMSE": -1}
{"TrainCount": 41, "MeanTrainLoss": 0.06053155993072682, "MeanValidationLoss": 0.05693405459838352, "FinalMeanRMSE": -1}
{"TrainCount": 41, "MeanTrainLoss": 0.0606132093148902, "MeanValidationLoss": 0.056975605672803416, "FinalMeanRMSE": -1}
{"TrainCount": 41, "MeanTrainLoss": 0.06048259761189799, "MeanValidationLoss": 0.056929944618337454, "FinalMeanRMSE": -1}
{"TrainCount": 41, "MeanTrainLoss": 0.060523645981740065, "MeanValidationLoss": 0.0569531327948488, "FinalMeanRMSE": -1}
{"TrainCount": 41, "MeanTrainLoss": 0.06046400158806374, "MeanValidationLoss": 0.056932335141403924, "FinalMeanRMSE": -1}
{"TrainCount": 41, "MeanTrainLoss": 0.0604643538230803, "MeanValidationLoss": 0.05694251490392904, "FinalMeanRMSE": -1}
{"TrainCount": 41, "MeanTrainLoss": 0.06043312610414312, "MeanValidationLoss": 0.056933097498512816, "FinalMeanRMSE": -1}
{"TrainCount": 41, "MeanTrainLoss": 0.06041929194733094, "MeanValidationLoss": 0.056936684953070235, "FinalMeanRMSE": -1}
{"TrainCount": 41, "MeanTrainLoss": 0.06039779575560322, "MeanValidationLoss": 0.0569321448518627, "FinalMeanRMSE": -1}
{"TrainCount": 41, "MeanTrainLoss": 0.06037871127512568, "MeanValidationLoss": 0.05693096183668608, "FinalMeanRMSE": -1}
{"TrainCount": 41, "MeanTrainLoss": 0.060360556118286494, "MeanValidationLoss": 0.05692958750430195, "FinalMeanRMSE": 0.05692958905566115}
{"TrainCount": 42, "MeanTrainLoss": 0.06076696192403491, "MeanValidationLoss": 0.0752690672616049, "FinalMeanRMSE": -1}
{"TrainCount": 42, "MeanTrainLoss": 0.0555272132801495, "MeanValidationLoss": 0.07282415514736507, "FinalMeanRMSE": -1}
{"TrainCount": 42, "MeanTrainLoss": 0.05606950076578333, "MeanValidationLoss": 0.07416667302564389, "FinalMeanRMSE": -1}
{"TrainCount": 42, "MeanTrainLoss": 0.055266080796718596, "MeanValidationLoss": 0.07393448433779568, "FinalMeanRMSE": -1}
{"TrainCount": 42, "MeanTrainLoss": 0.05512443117314963, "MeanValidationLoss": 0.07324365283109549, "FinalMeanRMSE": -1}
{"TrainCount": 42, "MeanTrainLoss": 0.05522612354738249, "MeanValidationLoss": 0.0736080941265029, "FinalMeanRMSE": -1}
{"TrainCount": 42, "MeanTrainLoss": 0.055044352386495195, "MeanValidationLoss": 0.07342649923066873, "FinalMeanRMSE": -1}
{"TrainCount": 42, "MeanTrainLoss": 0.05501281452907933, "MeanValidationLoss": 0.07326482321173383, "FinalMeanRMSE": -1}
{"TrainCount": 42, "MeanTrainLoss": 0.0549903451002759, "MeanValidationLoss": 0.07329693962039285, "FinalMeanRMSE": -1}
{"TrainCount": 42, "MeanTrainLoss": 0.05491616575837993, "MeanValidationLoss": 0.07319175301259653, "FinalMeanRMSE": -1}
{"TrainCount": 42, "MeanTrainLoss": 0.05488164176186212, "MeanValidationLoss": 0.07311788442506956, "FinalMeanRMSE": -1}
{"TrainCount": 42, "MeanTrainLoss": 0.05484272394892123, "MeanValidationLoss": 0.07307923158813763, "FinalMeanRMSE": -1}
{"TrainCount": 42, "MeanTrainLoss": 0.05479604069063132, "MeanValidationLoss": 0.07300904789411952, "FinalMeanRMSE": -1}
{"TrainCount": 42, "MeanTrainLoss": 0.05476061604220232, "MeanValidationLoss": 0.07295405864715576, "FinalMeanRMSE": -1}
{"TrainCount": 42, "MeanTrainLoss": 0.05472267053538947, "MeanValidationLoss": 0.07290595765575508, "FinalMeanRMSE": 0.07290595715986892}
{"TrainCount": 43, "MeanTrainLoss": 0.05981265583208629, "MeanValidationLoss": 0.06494919572557722, "FinalMeanRMSE": -1}
{"TrainCount": 43, "MeanTrainLoss": 0.057989488286631447, "MeanValidationLoss": 0.06533581512314933, "FinalMeanRMSE": -1}
{"TrainCount": 43, "MeanTrainLoss": 0.05806731815849032, "MeanValidationLoss": 0.065022135249206, "FinalMeanRMSE": -1}
{"TrainCount": 43, "MeanTrainLoss": 0.05768457331827709, "MeanValidationLoss": 0.06505149564572743, "FinalMeanRMSE": -1}
{"TrainCount": 43, "MeanTrainLoss": 0.057795401087829046, "MeanValidationLoss": 0.06492525117737906, "FinalMeanRMSE": -1}
{"TrainCount": 43, "MeanTrainLoss": 0.05771189131907054, "MeanValidationLoss": 0.06493457837828569, "FinalMeanRMSE": -1}
{"TrainCount": 43, "MeanTrainLoss": 0.05767485499382019, "MeanValidationLoss": 0.06493183932134083, "FinalMeanRMSE": -1}
{"TrainCount": 43, "MeanTrainLoss": 0.05767015495470592, "MeanValidationLoss": 0.06491342152867999, "FinalMeanRMSE": -1}
{"TrainCount": 43, "MeanTrainLoss": 0.05762538254261017, "MeanValidationLoss": 0.06491816857031414, "FinalMeanRMSE": -1}
{"TrainCount": 43, "MeanTrainLoss": 0.05761421356882368, "MeanValidationLoss": 0.06490404256752559, "FinalMeanRMSE": -1}
{"TrainCount": 43, "MeanTrainLoss": 0.0575854886003903, "MeanValidationLoss": 0.06490108741181237, "FinalMeanRMSE": -1}
{"TrainCount": 43, "MeanTrainLoss": 0.057564129786831994, "MeanValidationLoss": 0.06489371376378196, "FinalMeanRMSE": -1}
{"TrainCount": 43, "MeanTrainLoss": 0.057543329851967945, "MeanValidationLoss": 0.06488526178257806, "FinalMeanRMSE": -1}
{"TrainCount": 43, "MeanTrainLoss": 0.05751945691449301, "MeanValidationLoss": 0.06487964966467448, "FinalMeanRMSE": -1}
{"TrainCount": 43, "MeanTrainLoss": 0.05750031441450119, "MeanValidationLoss": 0.06487223540033613, "FinalMeanRMSE": 0.06487223777764665}
{"TrainCount": 44, "MeanTrainLoss": 0.062493725595149124, "MeanValidationLoss": 0.057272971059594835, "FinalMeanRMSE": -1}
{"TrainCount": 44, "MeanTrainLoss": 0.06248916109854525, "MeanValidationLoss": 0.057028894552162715, "FinalMeanRMSE": -1}
{"TrainCount": 44, "MeanTrainLoss": 0.06233026104217226, "MeanValidationLoss": 0.05902502834796906, "FinalMeanRMSE": -1}
{"TrainCount": 44, "MeanTrainLoss": 0.06195880032398484, "MeanValidationLoss": 0.057723762478147235, "FinalMeanRMSE": -1}
{"TrainCount": 44, "MeanTrainLoss": 0.06203843822533434, "MeanValidationLoss": 0.05790537570204054, "FinalMeanRMSE": -1}
{"TrainCount": 44, "MeanTrainLoss": 0.06196489168161696, "MeanValidationLoss": 0.058235925074134554, "FinalMeanRMSE": -1}
{"TrainCount": 44, "MeanTrainLoss": 0.06185662627897479, "MeanValidationLoss": 0.05794435458523887, "FinalMeanRMSE": -1}
{"TrainCount": 44, "MeanTrainLoss": 0.06184245629066771, "MeanValidationLoss": 0.058054879137447904, "FinalMeanRMSE": -1}
{"TrainCount": 44, "MeanTrainLoss": 0.06178008849647912, "MeanValidationLoss": 0.05809211496795927, "FinalMeanRMSE": -1}
{"TrainCount": 44, "MeanTrainLoss": 0.06172426282004877, "MeanValidationLoss": 0.058030607742922645, "FinalMeanRMSE": -1}
{"TrainCount": 44, "MeanTrainLoss": 0.06168443862010132, "MeanValidationLoss": 0.05806767340217318, "FinalMeanRMSE": -1}
{"TrainCount": 44, "MeanTrainLoss": 0.06163338520987467, "MeanValidationLoss": 0.05806561022996903, "FinalMeanRMSE": -1}
{"TrainCount": 44, "MeanTrainLoss": 0.061587349427017296, "MeanValidationLoss": 0.058046971729823524, "FinalMeanRMSE": -1}
{"TrainCount": 44, "MeanTrainLoss": 0.06154514104127884, "MeanValidationLoss": 0.05805964092058795, "FinalMeanRMSE": -1}
{"TrainCount": 44, "MeanTrainLoss": 0.061499547213315964, "MeanValidationLoss": 0.05804504652108465, "FinalMeanRMSE": 0.05804504770786464}
{"TrainCount": 45, "MeanTrainLoss": 0.05980346073807145, "MeanValidationLoss": 0.06621325894587302, "FinalMeanRMSE": -1}
{"TrainCount": 45, "MeanTrainLoss": 0.059208740064235515, "MeanValidationLoss": 0.06583998601000778, "FinalMeanRMSE": -1}
{"TrainCount": 45, "MeanTrainLoss": 0.059158343950592475, "MeanValidationLoss": 0.06583069966879883, "FinalMeanRMSE": -1}
{"TrainCount": 45, "MeanTrainLoss": 0.0591579744919748, "MeanValidationLoss": 0.0659347511612611, "FinalMeanRMSE": -1}
{"TrainCount": 45, "MeanTrainLoss": 0.05898044506350924, "MeanValidationLoss": 0.06585601962715215, "FinalMeanRMSE": -1}
{"TrainCount": 45, "MeanTrainLoss": 0.058972805609620614, "MeanValidationLoss": 0.06588860343861787, "FinalMeanRMSE": -1}
{"TrainCount": 45, "MeanTrainLoss": 0.05891754613486078, "MeanValidationLoss": 0.06590740059669307, "FinalMeanRMSE": -1}
{"TrainCount": 45, "MeanTrainLoss": 0.05885818593139607, "MeanValidationLoss": 0.06589412013058028, "FinalMeanRMSE": -1}
{"TrainCount": 45, "MeanTrainLoss": 0.05883317631843798, "MeanValidationLoss": 0.0659155099292022, "FinalMeanRMSE": -1}
{"TrainCount": 45, "MeanTrainLoss": 0.0587900193027014, "MeanValidationLoss": 0.06591874593599684, "FinalMeanRMSE": -1}
{"TrainCount": 45, "MeanTrainLoss": 0.058756213366813546, "MeanValidationLoss": 0.06592812259934541, "FinalMeanRMSE": -1}
{"TrainCount": 45, "MeanTrainLoss": 0.0587242471875478, "MeanValidationLoss": 0.06593594678564568, "FinalMeanRMSE": -1}
{"TrainCount": 45, "MeanTrainLoss": 0.05869214816464471, "MeanValidationLoss": 0.06594062725760344, "FinalMeanRMSE": -1}
{"TrainCount": 45, "MeanTrainLoss": 0.05866478606843811, "MeanValidationLoss": 0.06594853385249315, "FinalMeanRMSE": -1}
{"TrainCount": 45, "MeanTrainLoss": 0.05863687799712079, "MeanValidationLoss": 0.06595300677410096, "FinalMeanRMSE": 0.06595300639543025}
{"TrainCount": 46, "MeanTrainLoss": 0.06419535994529724, "MeanValidationLoss": 0.061388162970542906, "FinalMeanRMSE": -1}
{"TrainCount": 46, "MeanTrainLoss": 0.06333274717841829, "MeanValidationLoss": 0.05943266410912786, "FinalMeanRMSE": -1}
{"TrainCount": 46, "MeanTrainLoss": 0.06319211849144526, "MeanValidationLoss": 0.0586020957997867, "FinalMeanRMSE": -1}
{"TrainCount": 46, "MeanTrainLoss": 0.06325194235358919, "MeanValidationLoss": 0.059686861634254455, "FinalMeanRMSE": -1}
{"TrainCount": 46, "MeanTrainLoss": 0.06302219497306007, "MeanValidationLoss": 0.05920272569571223, "FinalMeanRMSE": -1}
{"TrainCount": 46, "MeanTrainLoss": 0.06299647991146361, "MeanValidationLoss": 0.059122874529234, "FinalMeanRMSE": -1}
{"TrainCount": 46, "MeanTrainLoss": 0.06294552551848548, "MeanValidationLoss": 0.059325033894607, "FinalMeanRMSE": -1}
{"TrainCount": 46, "MeanTrainLoss": 0.06285796506064278, "MeanValidationLoss": 0.05918039470911026, "FinalMeanRMSE": -1}
{"TrainCount": 46, "MeanTrainLoss": 0.06281708947249821, "MeanValidationLoss": 0.05919522127934865, "FinalMeanRMSE": -1}
{"TrainCount": 46, "MeanTrainLoss": 0.06276374025004251, "MeanValidationLoss": 0.05919864799295153, "FinalMeanRMSE": -1}
{"TrainCount": 46, "MeanTrainLoss": 0.06271308681794575, "MeanValidationLoss": 0.0591591340303421, "FinalMeanRMSE": -1}
{"TrainCount": 46, "MeanTrainLoss": 0.06266989201307296, "MeanValidationLoss": 0.05915048196911812, "FinalMeanRMSE": -1}
{"TrainCount": 46, "MeanTrainLoss": 0.06262541336672647, "MeanValidationLoss": 0.05912934281996318, "FinalMeanRMSE": -1}
{"TrainCount": 46, "MeanTrainLoss": 0.06258329170090812, "MeanValidationLoss": 0.05910646208695003, "FinalMeanRMSE": -1}
{"TrainCount": 46, "MeanTrainLoss": 0.06254435173102788, "MeanValidationLoss": 0.05909230023622513, "FinalMeanRMSE": 0.059092301518715105}
{"TrainCount": 47, "MeanTrainLoss": 0.06355395193868901, "MeanValidationLoss": 0.0755205842197975, "FinalMeanRMSE": -1}
{"TrainCount": 47, "MeanTrainLoss": 0.06252238260848182, "MeanValidationLoss": 0.07468066299926339, "FinalMeanRMSE": -1}
{"TrainCount": 47, "MeanTrainLoss": 0.062392772104144956, "MeanValidationLoss": 0.07454268358690891, "FinalMeanRMSE": -1}
{"TrainCount": 47, "MeanTrainLoss": 0.06238357434627126, "MeanValidationLoss": 0.07489947044435953, "FinalMeanRMSE": -1}
{"TrainCount": 47, "MeanTrainLoss": 0.06215718926117362, "MeanValidationLoss": 0.0746424026744214, "FinalMeanRMSE": -1}
{"TrainCount": 47, "MeanTrainLoss": 0.062168496199930555, "MeanValidationLoss": 0.07479099197194755, "FinalMeanRMSE": -1}
{"TrainCount": 47, "MeanTrainLoss": 0.062050363804182794, "MeanValidationLoss": 0.07475167525813758, "FinalMeanRMSE": -1}
{"TrainCount": 47, "MeanTrainLoss": 0.061995560784446554, "MeanValidationLoss": 0.07478008725050557, "FinalMeanRMSE": -1}
{"TrainCount": 47, "MeanTrainLoss": 0.06192676114485549, "MeanValidationLoss": 0.07480568925424808, "FinalMeanRMSE": -1}
{"TrainCount": 47, "MeanTrainLoss": 0.06186020883904907, "MeanValidationLoss": 0.07480551573754735, "FinalMeanRMSE": -1}
{"TrainCount": 47, "MeanTrainLoss": 0.061802991723687445, "MeanValidationLoss": 0.07482928296045072, "FinalMeanRMSE": -1}
{"TrainCount": 47, "MeanTrainLoss": 0.06174142304996048, "MeanValidationLoss": 0.07483324688466299, "FinalMeanRMSE": -1}
{"TrainCount": 47, "MeanTrainLoss": 0.0616878837798581, "MeanValidationLoss": 0.07484688127488759, "FinalMeanRMSE": -1}
{"TrainCount": 47, "MeanTrainLoss": 0.06163288102435515, "MeanValidationLoss": 0.07485484017457576, "FinalMeanRMSE": -1}
{"TrainCount": 47, "MeanTrainLoss": 0.061581345756160574, "MeanValidationLoss": 0.07486457377672195, "FinalMeanRMSE": 0.07486457341088615}
{"TrainCount": 48, "MeanTrainLoss": 0.06278367165638053, "MeanValidationLoss": 0.07513185178990973, "FinalMeanRMSE": -1}
{"TrainCount": 48, "MeanTrainLoss": 0.061743616442317545, "MeanValidationLoss": 0.07292321125088735, "FinalMeanRMSE": -1}
{"TrainCount": 48, "MeanTrainLoss": 0.06155133148034413, "MeanValidationLoss": 0.07239492038308187, "FinalMeanRMSE": -1}
{"TrainCount": 48, "MeanTrainLoss": 0.061635712598976884, "MeanValidationLoss": 0.07334594757750977, "FinalMeanRMSE": -1}
{"TrainCount": 48, "MeanTrainLoss": 0.06143291888461597, "MeanValidationLoss": 0.07255664814350217, "FinalMeanRMSE": -1}
{"TrainCount": 48, "MeanTrainLoss": 0.061485111097926676, "MeanValidationLoss": 0.07279366493051828, "FinalMeanRMSE": -1}
{"TrainCount": 48, "MeanTrainLoss": 0.06142114167628081, "MeanValidationLoss": 0.07270421642203663, "FinalMeanRMSE": -1}
{"TrainCount": 48, "MeanTrainLoss": 0.06137988426979037, "MeanValidationLoss": 0.07256711083789204, "FinalMeanRMSE": -1}
{"TrainCount": 48, "MeanTrainLoss": 0.06136450834464336, "MeanValidationLoss": 0.07259792236741199, "FinalMeanRMSE": -1}
{"TrainCount": 48, "MeanTrainLoss": 0.06132000438545061, "MeanValidationLoss": 0.07249731310578279, "FinalMeanRMSE": -1}
{"TrainCount": 48, "MeanTrainLoss": 0.0612932751900044, "MeanValidationLoss": 0.07245655981607216, "FinalMeanRMSE": -1}
{"TrainCount": 48, "MeanTrainLoss": 0.06126315310813379, "MeanValidationLoss": 0.0724194626822028, "FinalMeanRMSE": -1}
{"TrainCount": 48, "MeanTrainLoss": 0.061230485659578573, "MeanValidationLoss": 0.07236024390819461, "FinalMeanRMSE": -1}
{"TrainCount": 48, "MeanTrainLoss": 0.061201025621182674, "MeanValidationLoss": 0.07231836592735247, "FinalMeanRMSE": -1}
{"TrainCount": 48, "MeanTrainLoss": 0.06116988120087679, "MeanValidationLoss": 0.07227259406516719, "FinalMeanRMSE": 0.07227259518356803}
{"TrainCount": 49, "MeanTrainLoss": 0.06691048441188677, "MeanValidationLoss": 0.05958319155649207, "FinalMeanRMSE": -1}
{"TrainCount": 49, "MeanTrainLoss": 0.0656889910357339, "MeanValidationLoss": 0.05853362831062284, "FinalMeanRMSE": -1}
{"TrainCount": 49, "MeanTrainLoss": 0.06560612033520426, "MeanValidationLoss": 0.05816413487853675, "FinalMeanRMSE": -1}
{"TrainCount": 49, "MeanTrainLoss": 0.0657237817985671, "MeanValidationLoss": 0.058843072075610875, "FinalMeanRMSE": -1}
{"TrainCount": 49, "MeanTrainLoss": 0.06544019422360829, "MeanValidationLoss": 0.05832858220941719, "FinalMeanRMSE": -1}
{"TrainCount": 49, "MeanTrainLoss": 0.06554539952959333, "MeanValidationLoss": 0.058531115409629096, "FinalMeanRMSE": -1}
{"TrainCount": 49, "MeanTrainLoss": 0.06546576470136642, "MeanValidationLoss": 0.05853900214892694, "FinalMeanRMSE": -1}
{"TrainCount": 49, "MeanTrainLoss": 0.06542739744697298, "MeanValidationLoss": 0.05846652157347778, "FinalMeanRMSE": -1}
{"TrainCount": 49, "MeanTrainLoss": 0.06542966859681265, "MeanValidationLoss": 0.05854801730862979, "FinalMeanRMSE": -1}
{"TrainCount": 49, "MeanTrainLoss": 0.06538545489311218, "MeanValidationLoss": 0.05849828386957618, "FinalMeanRMSE": -1}
{"TrainCount": 49, "MeanTrainLoss": 0.0653770532991205, "MeanValidationLoss": 0.05851552078778716, "FinalMeanRMSE": -1}
{"TrainCount": 49, "MeanTrainLoss": 0.06535508724195617, "MeanValidationLoss": 0.05851212334444468, "FinalMeanRMSE": -1}
{"TrainCount": 49, "MeanTrainLoss": 0.06533616395933288, "MeanValidationLoss": 0.058502633852520206, "FinalMeanRMSE": -1}
{"TrainCount": 49, "MeanTrainLoss": 0.06532072478107044, "MeanValidationLoss": 0.05850376265830007, "FinalMeanRMSE": -1}
{"TrainCount": 49, "MeanTrainLoss": 0.06530210978218487, "MeanValidationLoss": 0.05849175557665441, "FinalMeanRMSE": 0.05849175542565244}
{"TrainCount": 50, "MeanTrainLoss": 0.052959527954351986, "MeanValidationLoss": 0.0680900160330913, "FinalMeanRMSE": -1}
{"TrainCount": 50, "MeanTrainLoss": 0.05235482140196313, "MeanValidationLoss": 0.06588063572097376, "FinalMeanRMSE": -1}
{"TrainCount": 50, "MeanTrainLoss": 0.052541062418076635, "MeanValidationLoss": 0.0662059121350677, "FinalMeanRMSE": -1}
{"TrainCount": 50, "MeanTrainLoss": 0.05249778746808176, "MeanValidationLoss": 0.06670360482497022, "FinalMeanRMSE": -1}
{"TrainCount": 50, "MeanTrainLoss": 0.0523594641320997, "MeanValidationLoss": 0.06625288065975111, "FinalMeanRMSE": -1}
{"TrainCount": 50, "MeanTrainLoss": 0.0524129061014961, "MeanValidationLoss": 0.06645681377435696, "FinalMeanRMSE": -1}
{"TrainCount": 50, "MeanTrainLoss": 0.052369248641909456, "MeanValidationLoss": 0.06649863427084994, "FinalMeanRMSE": -1}
{"TrainCount": 50, "MeanTrainLoss": 0.05233605661087756, "MeanValidationLoss": 0.06643460820176009, "FinalMeanRMSE": -1}
{"TrainCount": 50, "MeanTrainLoss": 0.05233374578918484, "MeanValidationLoss": 0.06651069271254402, "FinalMeanRMSE": -1}
{"TrainCount": 50, "MeanTrainLoss": 0.05230691351478906, "MeanValidationLoss": 0.06652201100580954, "FinalMeanRMSE": -1}
{"TrainCount": 50, "MeanTrainLoss": 0.052288239009731965, "MeanValidationLoss": 0.06652553887725565, "FinalMeanRMSE": -1}
{"TrainCount": 50, "MeanTrainLoss": 0.05227533447013485, "MeanValidationLoss": 0.0665604370091692, "FinalMeanRMSE": -1}
{"TrainCount": 50, "MeanTrainLoss": 0.05225615715272992, "MeanValidationLoss": 0.06657259037039873, "FinalMeanRMSE": -1}
{"TrainCount": 50, "MeanTrainLoss": 0.05224162051789195, "MeanValidationLoss": 0.06659008181422432, "FinalMeanRMSE": -1}
{"TrainCount": 50, "MeanTrainLoss": 0.05222616447068804, "MeanValidationLoss": 0.06660743548690928, "FinalMeanRMSE": 0.06660743426793647}
{"TrainCount": 51, "MeanTrainLoss": 0.06494262533267679, "MeanValidationLoss": 0.06411834542240415, "FinalMeanRMSE": -1}
{"TrainCount": 51, "MeanTrainLoss": 0.06476320191538572, "MeanValidationLoss": 0.06406226852110454, "FinalMeanRMSE": -1}
{"TrainCount": 51, "MeanTrainLoss": 0.06470703988460734, "MeanValidationLoss": 0.06401030566011157, "FinalMeanRMSE": -1}
{"TrainCount": 51, "MeanTrainLoss": 0.06462527134394713, "MeanValidationLoss": 0.06404572376183101, "FinalMeanRMSE": -1}
{"TrainCount": 51, "MeanTrainLoss": 0.06460100194794839, "MeanValidationLoss": 0.06400815227202007, "FinalMeanRMSE": -1}
{"TrainCount": 51, "MeanTrainLoss": 0.06455000580163762, "MeanValidationLoss": 0.0640136913742338, "FinalMeanRMSE": -1}
{"TrainCount": 51, "MeanTrainLoss": 0.06452046959870561, "MeanValidationLoss": 0.06399590768984385, "FinalMeanRMSE": -1}
{"TrainCount": 51, "MeanTrainLoss": 0.06448306966880787, "MeanValidationLoss": 0.06398826284067971, "FinalMeanRMSE": -1}
{"TrainCount": 51, "MeanTrainLoss": 0.06445321462984778, "MeanValidationLoss": 0.06397726018513952, "FinalMeanRMSE": -1}
{"TrainCount": 51, "MeanTrainLoss": 0.06442128813844121, "MeanValidationLoss": 0.06396576004368919, "FinalMeanRMSE": -1}
{"TrainCount": 51, "MeanTrainLoss": 0.06439175275273812, "MeanValidationLoss": 0.06395849055477551, "FinalMeanRMSE": -1}
{"TrainCount": 51, "MeanTrainLoss": 0.06436420569562504, "MeanValidationLoss": 0.06394638018948691, "FinalMeanRMSE": -1}
{"TrainCount": 51, "MeanTrainLoss": 0.06433657486724038, "MeanValidationLoss": 0.06394013217517308, "FinalMeanRMSE": -1}
{"TrainCount": 51, "MeanTrainLoss": 0.06431084685558268, "MeanValidationLoss": 0.06392999746969769, "FinalMeanRMSE": -1}
{"TrainCount": 51, "MeanTrainLoss": 0.06428412516784464, "MeanValidationLoss": 0.06392335646918841, "FinalMeanRMSE": 0.06392335801255089}
