{"Log_count": 0, "Log_time": "04-06-2021 17:29:20", "Iteration": 99, "EpisodFramesNumber": 490, "TMCount": 99, "RTMCount": 0, "Epsilon": 0.9950793074282303, "Episodes": 0, "EndOfEpisod": false, "CurrenteEpisodRewardSum": 0, "EpisodRewardsSum": 0.0, "AverageEpisodReturn": NaN, "AverageDiscountedepisodReturn": NaN, "TDError2": NaN, "TotalFramesNumber": 490}
{"Log_count": 1, "Log_time": "04-06-2021 17:29:58", "Iteration": 199, "EpisodFramesNumber": 990, "TMCount": 199, "RTMCount": 0, "Epsilon": 0.9901089108910891, "Episodes": 0, "EndOfEpisod": false, "CurrenteEpisodRewardSum": 0, "EpisodRewardsSum": 0.0, "AverageEpisodReturn": NaN, "AverageDiscountedepisodReturn": NaN, "TDError2": 0.004574911743837339, "TotalFramesNumber": 990}
{"Log_count": 2, "Log_time": "04-06-2021 17:31:30", "Iteration": 299, "EpisodFramesNumber": 1490, "TMCount": 299, "RTMCount": 200, "Epsilon": 0.985138514353948, "Episodes": 0, "EndOfEpisod": false, "CurrenteEpisodRewardSum": 0, "EpisodRewardsSum": 0.0, "AverageEpisodReturn": NaN, "AverageDiscountedepisodReturn": NaN, "TDError2": 0.03983344439089765, "TotalFramesNumber": 1490}
{"Log_count": 3, "Log_time": "04-06-2021 17:33:20", "Iteration": 399, "EpisodFramesNumber": 1990, "TMCount": 399, "RTMCount": 300, "Epsilon": 0.9801681178168068, "Episodes": 0, "EndOfEpisod": false, "CurrenteEpisodRewardSum": 0, "EpisodRewardsSum": 0.0, "AverageEpisodReturn": NaN, "AverageDiscountedepisodReturn": NaN, "TDError2": 0.11002077011576133, "TotalFramesNumber": 1990}
{"Log_count": 4, "Log_time": "04-06-2021 17:35:38", "Iteration": 499, "EpisodFramesNumber": 2490, "TMCount": 499, "RTMCount": 400, "Epsilon": 0.9751977212796656, "Episodes": 0, "EndOfEpisod": false, "CurrenteEpisodRewardSum": 0, "EpisodRewardsSum": 0.0, "AverageEpisodReturn": NaN, "AverageDiscountedepisodReturn": NaN, "TDError2": 0.17178783876753875, "TotalFramesNumber": 2490}
{"Log_count": 5, "Log_time": "04-06-2021 17:38:25", "Iteration": 599, "EpisodFramesNumber": 2990, "TMCount": 599, "RTMCount": 500, "Epsilon": 0.9702273247425245, "Episodes": 0, "EndOfEpisod": false, "CurrenteEpisodRewardSum": 1, "EpisodRewardsSum": 1.0, "AverageEpisodReturn": NaN, "AverageDiscountedepisodReturn": NaN, "TDError2": 0.21492482862049997, "TotalFramesNumber": 2990}
{"Log_count": 6, "Log_time": "04-06-2021 17:41:41", "Iteration": 699, "EpisodFramesNumber": 3490, "TMCount": 699, "RTMCount": 600, "Epsilon": 0.9652569282053833, "Episodes": 0, "EndOfEpisod": false, "CurrenteEpisodRewardSum": 2, "EpisodRewardsSum": 2.0, "AverageEpisodReturn": NaN, "AverageDiscountedepisodReturn": NaN, "TDError2": 0.22897846563603325, "TotalFramesNumber": 3490}
{"Log_count": 7, "Log_time": "04-06-2021 17:45:27", "Iteration": 799, "EpisodFramesNumber": 3990, "TMCount": 799, "RTMCount": 700, "Epsilon": 0.9602865316682422, "Episodes": 0, "EndOfEpisod": false, "CurrenteEpisodRewardSum": 0, "EpisodRewardsSum": 0.0, "AverageEpisodReturn": NaN, "AverageDiscountedepisodReturn": NaN, "TDError2": 0.24006588279594512, "TotalFramesNumber": 3990}
{"Log_count": 8, "Log_time": "04-06-2021 17:49:41", "Iteration": 899, "EpisodFramesNumber": 4490, "TMCount": 899, "RTMCount": 800, "Epsilon": 0.955316135131101, "Episodes": 0, "EndOfEpisod": false, "CurrenteEpisodRewardSum": 1, "EpisodRewardsSum": 1.0, "AverageEpisodReturn": NaN, "AverageDiscountedepisodReturn": NaN, "TDError2": 0.2512387118214319, "TotalFramesNumber": 4490}
{"Log_count": 9, "Log_time": "04-06-2021 17:54:27", "Iteration": 999, "EpisodFramesNumber": 4990, "TMCount": 999, "RTMCount": 900, "Epsilon": 0.9503457385939599, "Episodes": 0, "EndOfEpisod": false, "CurrenteEpisodRewardSum": 6, "EpisodRewardsSum": 6.0, "AverageEpisodReturn": NaN, "AverageDiscountedepisodReturn": NaN, "TDError2": 0.2616081881314921, "TotalFramesNumber": 4990}
{"Log_count": 10, "Log_time": "04-06-2021 17:59:39", "Iteration": 1099, "EpisodFramesNumber": 5490, "TMCount": 1099, "RTMCount": 1000, "Epsilon": 0.9453753420568187, "Episodes": 0, "EndOfEpisod": false, "CurrenteEpisodRewardSum": 6, "EpisodRewardsSum": 6.0, "AverageEpisodReturn": NaN, "AverageDiscountedepisodReturn": NaN, "TDError2": 0.27411085013309283, "TotalFramesNumber": 5490}
{"Log_count": 11, "Log_time": "04-06-2021 18:04:55", "Iteration": 1199, "EpisodFramesNumber": 5990, "TMCount": 1199, "RTMCount": 1000, "Epsilon": 0.9404049455196776, "Episodes": 0, "EndOfEpisod": false, "CurrenteEpisodRewardSum": 5, "EpisodRewardsSum": 5.0, "AverageEpisodReturn": NaN, "AverageDiscountedepisodReturn": NaN, "TDError2": 0.28299414278340485, "TotalFramesNumber": 5990}
{"Log_count": 12, "Log_time": "04-06-2021 18:10:27", "Iteration": 1299, "EpisodFramesNumber": 6490, "TMCount": 1299, "RTMCount": 1000, "Epsilon": 0.9354345489825364, "Episodes": 0, "EndOfEpisod": false, "CurrenteEpisodRewardSum": 0, "EpisodRewardsSum": 0.0, "AverageEpisodReturn": NaN, "AverageDiscountedepisodReturn": NaN, "TDError2": 0.2901529174422216, "TotalFramesNumber": 6490}
{"Log_count": 13, "Log_time": "04-06-2021 18:16:23", "Iteration": 1399, "EpisodFramesNumber": 6990, "TMCount": 1399, "RTMCount": 1000, "Epsilon": 0.9304641524453953, "Episodes": 0, "EndOfEpisod": false, "CurrenteEpisodRewardSum": 0, "EpisodRewardsSum": 0.0, "AverageEpisodReturn": NaN, "AverageDiscountedepisodReturn": NaN, "TDError2": 0.29723076980348595, "TotalFramesNumber": 6990}
{"Log_count": 14, "Log_time": "04-06-2021 18:22:33", "Iteration": 1499, "EpisodFramesNumber": 7490, "TMCount": 1499, "RTMCount": 1000, "Epsilon": 0.9254937559082541, "Episodes": 0, "EndOfEpisod": false, "CurrenteEpisodRewardSum": 0, "EpisodRewardsSum": 0.0, "AverageEpisodReturn": NaN, "AverageDiscountedepisodReturn": NaN, "TDError2": 0.3031018745245332, "TotalFramesNumber": 7490}
{"Log_count": 15, "Log_time": "04-06-2021 18:29:03", "Iteration": 1599, "EpisodFramesNumber": 7990, "TMCount": 1599, "RTMCount": 1000, "Epsilon": 0.920523359371113, "Episodes": 0, "EndOfEpisod": false, "CurrenteEpisodRewardSum": 0, "EpisodRewardsSum": 0.0, "AverageEpisodReturn": NaN, "AverageDiscountedepisodReturn": NaN, "TDError2": 0.30710707111409635, "TotalFramesNumber": 7990}
{"Log_count": 16, "Log_time": "04-06-2021 18:35:49", "Iteration": 1699, "EpisodFramesNumber": 8490, "TMCount": 1699, "RTMCount": 1000, "Epsilon": 0.9155529628339718, "Episodes": 0, "EndOfEpisod": false, "CurrenteEpisodRewardSum": 0, "EpisodRewardsSum": 0.0, "AverageEpisodReturn": NaN, "AverageDiscountedepisodReturn": NaN, "TDError2": 0.3095347305185745, "TotalFramesNumber": 8490}
{"Log_count": 17, "Log_time": "04-06-2021 18:42:58", "Iteration": 1799, "EpisodFramesNumber": 8990, "TMCount": 1799, "RTMCount": 1000, "Epsilon": 0.9105825662968307, "Episodes": 0, "EndOfEpisod": false, "CurrenteEpisodRewardSum": 0, "EpisodRewardsSum": 0.0, "AverageEpisodReturn": NaN, "AverageDiscountedepisodReturn": NaN, "TDError2": 0.313517130794268, "TotalFramesNumber": 8990}
{"Log_count": 18, "Log_time": "04-06-2021 18:50:22", "Iteration": 1899, "EpisodFramesNumber": 9490, "TMCount": 1899, "RTMCount": 1000, "Epsilon": 0.9056121697596895, "Episodes": 0, "EndOfEpisod": false, "CurrenteEpisodRewardSum": 3, "EpisodRewardsSum": 3.0, "AverageEpisodReturn": NaN, "AverageDiscountedepisodReturn": NaN, "TDError2": 0.3151688106857799, "TotalFramesNumber": 9490}
{"Log_count": 19, "Log_time": "04-06-2021 18:58:04", "Iteration": 1999, "EpisodFramesNumber": 9990, "TMCount": 1999, "RTMCount": 1000, "Epsilon": 0.9006417732225483, "Episodes": 0, "EndOfEpisod": false, "CurrenteEpisodRewardSum": 0, "EpisodRewardsSum": 0.0, "AverageEpisodReturn": NaN, "AverageDiscountedepisodReturn": NaN, "TDError2": 0.3175203448964522, "TotalFramesNumber": 9990}
{"Log_count": 20, "Log_time": "04-06-2021 19:06:12", "Iteration": 2099, "EpisodFramesNumber": 10490, "TMCount": 2099, "RTMCount": 1000, "Epsilon": 0.8956713766854072, "Episodes": 0, "EndOfEpisod": false, "CurrenteEpisodRewardSum": 0, "EpisodRewardsSum": 0.0, "AverageEpisodReturn": NaN, "AverageDiscountedepisodReturn": NaN, "TDError2": 0.31834842670254626, "TotalFramesNumber": 10490}
{"Log_count": 21, "Log_time": "04-06-2021 19:11:57", "Iteration": 2199, "EpisodFramesNumber": 10990, "TMCount": 1755, "RTMCount": 1000, "Epsilon": 0.890700980148266, "Episodes": 0, "EndOfEpisod": false, "CurrenteEpisodRewardSum": 1, "EpisodRewardsSum": 1.0, "AverageEpisodReturn": NaN, "AverageDiscountedepisodReturn": NaN, "TDError2": 0.3202500813248623, "TotalFramesNumber": 10990}
{"Log_count": 22, "Log_time": "04-06-2021 19:18:18", "Iteration": 2299, "EpisodFramesNumber": 11490, "TMCount": 1981, "RTMCount": 2000, "Epsilon": 0.8857305836111249, "Episodes": 0, "EndOfEpisod": false, "CurrenteEpisodRewardSum": 1, "EpisodRewardsSum": 1.0, "AverageEpisodReturn": NaN, "AverageDiscountedepisodReturn": NaN, "TDError2": 0.3183568972306966, "TotalFramesNumber": 11490}
{"Log_count": 23, "Log_time": "04-06-2021 19:24:15", "Iteration": 2399, "EpisodFramesNumber": 11990, "TMCount": 2192, "RTMCount": 2000, "Epsilon": 0.8807601870739837, "Episodes": 0, "EndOfEpisod": false, "CurrenteEpisodRewardSum": 0, "EpisodRewardsSum": 0.0, "AverageEpisodReturn": NaN, "AverageDiscountedepisodReturn": NaN, "TDError2": 0.3164022873761799, "TotalFramesNumber": 11990}
{"Log_count": 24, "Log_time": "04-06-2021 19:30:20", "Iteration": 2499, "EpisodFramesNumber": 12490, "TMCount": 1691, "RTMCount": 2000, "Epsilon": 0.8757897905368426, "Episodes": 0, "EndOfEpisod": false, "CurrenteEpisodRewardSum": 5, "EpisodRewardsSum": 5.0, "AverageEpisodReturn": NaN, "AverageDiscountedepisodReturn": NaN, "TDError2": 0.3147780135810508, "TotalFramesNumber": 12490}
{"Log_count": 25, "Log_time": "04-06-2021 19:37:18", "Iteration": 2599, "EpisodFramesNumber": 12990, "TMCount": 2025, "RTMCount": 2306, "Epsilon": 0.8708193939997015, "Episodes": 0, "EndOfEpisod": false, "CurrenteEpisodRewardSum": 0, "EpisodRewardsSum": 0.0, "AverageEpisodReturn": NaN, "AverageDiscountedepisodReturn": NaN, "TDError2": 0.3147912585457435, "TotalFramesNumber": 12990}
{"Log_count": 26, "Log_time": "04-06-2021 19:42:03", "Iteration": 2663, "EpisodFramesNumber": 13310, "TMCount": 1406, "RTMCount": 2488, "Epsilon": 0.8676383402159311, "Episodes": 0, "EndOfEpisod": true, "CurrenteEpisodRewardSum": 0, "EpisodRewardsSum": 0.0, "AverageEpisodReturn": 0.0, "AverageDiscountedepisodReturn": 0.005029232425373168, "TDError2": 0.3148588691529125, "TotalFramesNumber": 13310}
{"Log_count": 27, "Log_time": "04-06-2021 19:43:59", "Iteration": 2699, "EpisodFramesNumber": 175, "TMCount": 1583, "RTMCount": 2488, "Epsilon": 0.8658489974625603, "Episodes": 1, "EndOfEpisod": false, "CurrenteEpisodRewardSum": 0, "EpisodRewardsSum": 0.0, "AverageEpisodReturn": 0.0, "AverageDiscountedepisodReturn": 0.005029232425373168, "TDError2": 0.3146811396908499, "TotalFramesNumber": 13487}
{"Log_count": 28, "Log_time": "04-06-2021 19:51:29", "Iteration": 2799, "EpisodFramesNumber": 675, "TMCount": 1962, "RTMCount": 2774, "Epsilon": 0.8608786009254192, "Episodes": 1, "EndOfEpisod": false, "CurrenteEpisodRewardSum": 0, "EpisodRewardsSum": 0.0, "AverageEpisodReturn": 0.0, "AverageDiscountedepisodReturn": 0.005029232425373168, "TDError2": 0.307582155780331, "TotalFramesNumber": 13987}
{"Log_count": 29, "Log_time": "04-06-2021 19:59:18", "Iteration": 2899, "EpisodFramesNumber": 1175, "TMCount": 2295, "RTMCount": 2774, "Epsilon": 0.855908204388278, "Episodes": 1, "EndOfEpisod": false, "CurrenteEpisodRewardSum": 0, "EpisodRewardsSum": 0.0, "AverageEpisodReturn": 0.0, "AverageDiscountedepisodReturn": 0.005029232425373168, "TDError2": 0.30132542102295473, "TotalFramesNumber": 14487}
{"Log_count": 30, "Log_time": "04-06-2021 20:07:01", "Iteration": 2999, "EpisodFramesNumber": 1675, "TMCount": 1792, "RTMCount": 2774, "Epsilon": 0.8509378078511369, "Episodes": 1, "EndOfEpisod": false, "CurrenteEpisodRewardSum": 0, "EpisodRewardsSum": 0.0, "AverageEpisodReturn": 0.0, "AverageDiscountedepisodReturn": 0.005029232425373168, "TDError2": 0.29557207097787913, "TotalFramesNumber": 14987}
{"Log_count": 31, "Log_time": "04-06-2021 20:15:11", "Iteration": 3099, "EpisodFramesNumber": 2175, "TMCount": 2178, "RTMCount": 2994, "Epsilon": 0.8459674113139957, "Episodes": 1, "EndOfEpisod": false, "CurrenteEpisodRewardSum": 0, "EpisodRewardsSum": 0.0, "AverageEpisodReturn": 0.0, "AverageDiscountedepisodReturn": 0.005029232425373168, "TDError2": 0.2961315693279917, "TotalFramesNumber": 15487}
{"Log_count": 32, "Log_time": "04-06-2021 20:23:12", "Iteration": 3199, "EpisodFramesNumber": 2675, "TMCount": 1748, "RTMCount": 2994, "Epsilon": 0.8409970147768546, "Episodes": 1, "EndOfEpisod": false, "CurrenteEpisodRewardSum": 0, "EpisodRewardsSum": 0.0, "AverageEpisodReturn": 0.0, "AverageDiscountedepisodReturn": 0.005029232425373168, "TDError2": 0.2966590604801981, "TotalFramesNumber": 15987}
{"Log_count": 33, "Log_time": "04-06-2021 20:31:44", "Iteration": 3299, "EpisodFramesNumber": 3175, "TMCount": 2193, "RTMCount": 3231, "Epsilon": 0.8360266182397134, "Episodes": 1, "EndOfEpisod": false, "CurrenteEpisodRewardSum": 0, "EpisodRewardsSum": 0.0, "AverageEpisodReturn": 0.0, "AverageDiscountedepisodReturn": 0.005029232425373168, "TDError2": 0.298236036842356, "TotalFramesNumber": 16487}
{"Log_count": 34, "Log_time": "04-06-2021 20:40:12", "Iteration": 3399, "EpisodFramesNumber": 3675, "TMCount": 1782, "RTMCount": 3231, "Epsilon": 0.8310562217025723, "Episodes": 1, "EndOfEpisod": false, "CurrenteEpisodRewardSum": 1, "EpisodRewardsSum": 1.0, "AverageEpisodReturn": 0.0, "AverageDiscountedepisodReturn": 0.005029232425373168, "TDError2": 0.29994375301755727, "TotalFramesNumber": 16987}
{"Log_count": 35, "Log_time": "04-06-2021 20:49:03", "Iteration": 3499, "EpisodFramesNumber": 4175, "TMCount": 2218, "RTMCount": 3434, "Epsilon": 0.826085825165431, "Episodes": 1, "EndOfEpisod": false, "CurrenteEpisodRewardSum": 1, "EpisodRewardsSum": 1.0, "AverageEpisodReturn": 0.0, "AverageDiscountedepisodReturn": 0.005029232425373168, "TDError2": 0.3002513124139743, "TotalFramesNumber": 17487}
{"Log_count": 36, "Log_time": "04-06-2021 20:57:53", "Iteration": 3599, "EpisodFramesNumber": 4675, "TMCount": 1814, "RTMCount": 3434, "Epsilon": 0.82111542862829, "Episodes": 1, "EndOfEpisod": false, "CurrenteEpisodRewardSum": 0, "EpisodRewardsSum": 0.0, "AverageEpisodReturn": 0.0, "AverageDiscountedepisodReturn": 0.005029232425373168, "TDError2": 0.30092498436204096, "TotalFramesNumber": 17987}
{"Log_count": 37, "Log_time": "04-06-2021 21:07:10", "Iteration": 3699, "EpisodFramesNumber": 5175, "TMCount": 2292, "RTMCount": 3626, "Epsilon": 0.8161450320911487, "Episodes": 1, "EndOfEpisod": false, "CurrenteEpisodRewardSum": 0, "EpisodRewardsSum": 0.0, "AverageEpisodReturn": 0.0, "AverageDiscountedepisodReturn": 0.005029232425373168, "TDError2": 0.3019723111084846, "TotalFramesNumber": 18487}
{"Log_count": 38, "Log_time": "04-06-2021 21:16:27", "Iteration": 3799, "EpisodFramesNumber": 5675, "TMCount": 1897, "RTMCount": 3626, "Epsilon": 0.8111746355540077, "Episodes": 1, "EndOfEpisod": false, "CurrenteEpisodRewardSum": 0, "EpisodRewardsSum": 0.0, "AverageEpisodReturn": 0.0, "AverageDiscountedepisodReturn": 0.005029232425373168, "TDError2": 0.3038380280889314, "TotalFramesNumber": 18987}
{"Log_count": 39, "Log_time": "04-06-2021 21:26:05", "Iteration": 3899, "EpisodFramesNumber": 6175, "TMCount": 2372, "RTMCount": 3818, "Epsilon": 0.8062042390168666, "Episodes": 1, "EndOfEpisod": false, "CurrenteEpisodRewardSum": 0, "EpisodRewardsSum": 0.0, "AverageEpisodReturn": 0.0, "AverageDiscountedepisodReturn": 0.005029232425373168, "TDError2": 0.30447377238008494, "TotalFramesNumber": 19487}
{"Log_count": 40, "Log_time": "04-06-2021 21:35:49", "Iteration": 3999, "EpisodFramesNumber": 6675, "TMCount": 1961, "RTMCount": 3818, "Epsilon": 0.8012338424797254, "Episodes": 1, "EndOfEpisod": false, "CurrenteEpisodRewardSum": 0, "EpisodRewardsSum": 0.0, "AverageEpisodReturn": 0.0, "AverageDiscountedepisodReturn": 0.005029232425373168, "TDError2": 0.3054280010270722, "TotalFramesNumber": 19987}
{"Log_count": 41, "Log_time": "04-06-2021 21:46:09", "Iteration": 4099, "EpisodFramesNumber": 7175, "TMCount": 2465, "RTMCount": 4002, "Epsilon": 0.7962634459425842, "Episodes": 1, "EndOfEpisod": false, "CurrenteEpisodRewardSum": 0, "EpisodRewardsSum": 0.0, "AverageEpisodReturn": 0.0, "AverageDiscountedepisodReturn": 0.005029232425373168, "TDError2": 0.3016226507405397, "TotalFramesNumber": 20487}
{"Log_count": 42, "Log_time": "04-06-2021 21:56:20", "Iteration": 4199, "EpisodFramesNumber": 7675, "TMCount": 2082, "RTMCount": 4002, "Epsilon": 0.7912930494054431, "Episodes": 1, "EndOfEpisod": false, "CurrenteEpisodRewardSum": 0, "EpisodRewardsSum": 0.0, "AverageEpisodReturn": 0.0, "AverageDiscountedepisodReturn": 0.005029232425373168, "TDError2": 0.2978438183123827, "TotalFramesNumber": 20987}
{"Log_count": 43, "Log_time": "04-06-2021 22:06:35", "Iteration": 4299, "EpisodFramesNumber": 8175, "TMCount": 1724, "RTMCount": 4186, "Epsilon": 0.7863226528683019, "Episodes": 1, "EndOfEpisod": false, "CurrenteEpisodRewardSum": 0, "EpisodRewardsSum": 0.0, "AverageEpisodReturn": 0.0, "AverageDiscountedepisodReturn": 0.005029232425373168, "TDError2": 0.29779066328800585, "TotalFramesNumber": 21487}
{"Log_count": 44, "Log_time": "04-06-2021 22:17:12", "Iteration": 4399, "EpisodFramesNumber": 8675, "TMCount": 2271, "RTMCount": 4367, "Epsilon": 0.7813522563311608, "Episodes": 1, "EndOfEpisod": false, "CurrenteEpisodRewardSum": 0, "EpisodRewardsSum": 0.0, "AverageEpisodReturn": 0.0, "AverageDiscountedepisodReturn": 0.005029232425373168, "TDError2": 0.2985341361303089, "TotalFramesNumber": 21987}
{"Log_count": 45, "Log_time": "04-06-2021 22:27:51", "Iteration": 4499, "EpisodFramesNumber": 9175, "TMCount": 1921, "RTMCount": 4367, "Epsilon": 0.7763818597940196, "Episodes": 1, "EndOfEpisod": false, "CurrenteEpisodRewardSum": 0, "EpisodRewardsSum": 0.0, "AverageEpisodReturn": 0.0, "AverageDiscountedepisodReturn": 0.005029232425373168, "TDError2": 0.29862880294560945, "TotalFramesNumber": 22487}
{"Log_count": 46, "Log_time": "04-06-2021 22:38:58", "Iteration": 4599, "EpisodFramesNumber": 9675, "TMCount": 2449, "RTMCount": 4528, "Epsilon": 0.7714114632568785, "Episodes": 1, "EndOfEpisod": false, "CurrenteEpisodRewardSum": 0, "EpisodRewardsSum": 0.0, "AverageEpisodReturn": 0.0, "AverageDiscountedepisodReturn": 0.005029232425373168, "TDError2": 0.29961512666945195, "TotalFramesNumber": 22987}
{"Log_count": 47, "Log_time": "04-06-2021 22:50:04", "Iteration": 4699, "EpisodFramesNumber": 10175, "TMCount": 2076, "RTMCount": 4528, "Epsilon": 0.7664410667197373, "Episodes": 1, "EndOfEpisod": false, "CurrenteEpisodRewardSum": 0, "EpisodRewardsSum": 0.0, "AverageEpisodReturn": 0.0, "AverageDiscountedepisodReturn": 0.005029232425373168, "TDError2": 0.30018304099198173, "TotalFramesNumber": 23487}
{"Log_count": 48, "Log_time": "04-06-2021 23:01:18", "Iteration": 4799, "EpisodFramesNumber": 10675, "TMCount": 1761, "RTMCount": 4694, "Epsilon": 0.7614706701825962, "Episodes": 1, "EndOfEpisod": false, "CurrenteEpisodRewardSum": 0, "EpisodRewardsSum": 0.0, "AverageEpisodReturn": 0.0, "AverageDiscountedepisodReturn": 0.005029232425373168, "TDError2": 0.3012485135169702, "TotalFramesNumber": 23987}
{"Log_count": 49, "Log_time": "04-06-2021 23:12:54", "Iteration": 4899, "EpisodFramesNumber": 11175, "TMCount": 2315, "RTMCount": 4869, "Epsilon": 0.756500273645455, "Episodes": 1, "EndOfEpisod": false, "CurrenteEpisodRewardSum": 0, "EpisodRewardsSum": 0.0, "AverageEpisodReturn": 0.0, "AverageDiscountedepisodReturn": 0.005029232425373168, "TDError2": 0.3019575719055129, "TotalFramesNumber": 24487}
{"Log_count": 50, "Log_time": "04-06-2021 23:24:34", "Iteration": 4999, "EpisodFramesNumber": 11675, "TMCount": 1958, "RTMCount": 4869, "Epsilon": 0.7515298771083139, "Episodes": 1, "EndOfEpisod": false, "CurrenteEpisodRewardSum": 0, "EpisodRewardsSum": 0.0, "AverageEpisodReturn": 0.0, "AverageDiscountedepisodReturn": 0.005029232425373168, "TDError2": 0.30282857362188426, "TotalFramesNumber": 24987}
{"Log_count": 51, "Log_time": "04-06-2021 23:36:53", "Iteration": 5099, "EpisodFramesNumber": 12175, "TMCount": 2490, "RTMCount": 5018, "Epsilon": 0.7465594805711726, "Episodes": 1, "EndOfEpisod": false, "CurrenteEpisodRewardSum": 0, "EpisodRewardsSum": 0.0, "AverageEpisodReturn": 0.0, "AverageDiscountedepisodReturn": 0.005029232425373168, "TDError2": 0.30291418953011395, "TotalFramesNumber": 25487}
{"Log_count": 52, "Log_time": "04-06-2021 23:49:08", "Iteration": 5199, "EpisodFramesNumber": 12675, "TMCount": 2122, "RTMCount": 5018, "Epsilon": 0.7415890840340316, "Episodes": 1, "EndOfEpisod": false, "CurrenteEpisodRewardSum": 0, "EpisodRewardsSum": 0.0, "AverageEpisodReturn": 0.0, "AverageDiscountedepisodReturn": 0.005029232425373168, "TDError2": 0.30349008184121445, "TotalFramesNumber": 25987}
{"Log_count": 53, "Log_time": "05-06-2021 00:01:26", "Iteration": 5299, "EpisodFramesNumber": 13175, "TMCount": 1831, "RTMCount": 5186, "Epsilon": 0.7366186874968904, "Episodes": 1, "EndOfEpisod": false, "CurrenteEpisodRewardSum": 0, "EpisodRewardsSum": 0.0, "AverageEpisodReturn": 0.0, "AverageDiscountedepisodReturn": 0.005029232425373168, "TDError2": 0.30382522905335224, "TotalFramesNumber": 26487}
{"Log_count": 54, "Log_time": "05-06-2021 00:06:42", "Iteration": 5326, "EpisodFramesNumber": 13310, "TMCount": 2001, "RTMCount": 5358, "Epsilon": 0.7352766804318622, "Episodes": 1, "EndOfEpisod": true, "CurrenteEpisodRewardSum": 0, "EpisodRewardsSum": 0.0, "AverageEpisodReturn": 0.0, "AverageDiscountedepisodReturn": 0.005029232425394736, "TDError2": 0.30366816799568774, "TotalFramesNumber": 26622}
{"Log_count": 55, "Log_time": "05-06-2021 00:14:04", "Iteration": 5399, "EpisodFramesNumber": 360, "TMCount": 2429, "RTMCount": 5358, "Epsilon": 0.7316482909597493, "Episodes": 2, "EndOfEpisod": false, "CurrenteEpisodRewardSum": 1, "EpisodRewardsSum": 1.0, "AverageEpisodReturn": 0.0, "AverageDiscountedepisodReturn": 0.005029232425394736, "TDError2": 0.30295398654819056, "TotalFramesNumber": 26984}
{"Log_count": 56, "Log_time": "05-06-2021 00:26:46", "Iteration": 5499, "EpisodFramesNumber": 860, "TMCount": 2096, "RTMCount": 5358, "Epsilon": 0.7266778944226081, "Episodes": 2, "EndOfEpisod": false, "CurrenteEpisodRewardSum": 0, "EpisodRewardsSum": 0.0, "AverageEpisodReturn": 0.0, "AverageDiscountedepisodReturn": 0.005029232425394736, "TDError2": 0.30245204044156665, "TotalFramesNumber": 27484}
{"Log_count": 57, "Log_time": "05-06-2021 00:39:34", "Iteration": 5599, "EpisodFramesNumber": 1360, "TMCount": 1803, "RTMCount": 5507, "Epsilon": 0.721707497885467, "Episodes": 2, "EndOfEpisod": false, "CurrenteEpisodRewardSum": 0, "EpisodRewardsSum": 0.0, "AverageEpisodReturn": 0.0, "AverageDiscountedepisodReturn": 0.005029232425394736, "TDError2": 0.2994134600766684, "TotalFramesNumber": 27984}
{"Log_count": 58, "Log_time": "05-06-2021 00:52:46", "Iteration": 5699, "EpisodFramesNumber": 1860, "TMCount": 2422, "RTMCount": 5666, "Epsilon": 0.7167371013483258, "Episodes": 2, "EndOfEpisod": false, "CurrenteEpisodRewardSum": 0, "EpisodRewardsSum": 0.0, "AverageEpisodReturn": 0.0, "AverageDiscountedepisodReturn": 0.005029232425394736, "TDError2": 0.30023439872882307, "TotalFramesNumber": 28484}
{"Log_count": 59, "Log_time": "05-06-2021 01:06:02", "Iteration": 5799, "EpisodFramesNumber": 2360, "TMCount": 2080, "RTMCount": 5666, "Epsilon": 0.7117667048111846, "Episodes": 2, "EndOfEpisod": false, "CurrenteEpisodRewardSum": 0, "EpisodRewardsSum": 0.0, "AverageEpisodReturn": 0.0, "AverageDiscountedepisodReturn": 0.005029232425394736, "TDError2": 0.30095846469936854, "TotalFramesNumber": 28984}
{"Log_count": 60, "Log_time": "05-06-2021 01:19:23", "Iteration": 5899, "EpisodFramesNumber": 2860, "TMCount": 1813, "RTMCount": 5810, "Epsilon": 0.7067963082740435, "Episodes": 2, "EndOfEpisod": false, "CurrenteEpisodRewardSum": 0, "EpisodRewardsSum": 0.0, "AverageEpisodReturn": 0.0, "AverageDiscountedepisodReturn": 0.005029232425394736, "TDError2": 0.30127694441047104, "TotalFramesNumber": 29484}
{"Log_count": 61, "Log_time": "05-06-2021 01:33:09", "Iteration": 5999, "EpisodFramesNumber": 3360, "TMCount": 2454, "RTMCount": 5966, "Epsilon": 0.7018259117369023, "Episodes": 2, "EndOfEpisod": false, "CurrenteEpisodRewardSum": 0, "EpisodRewardsSum": 0.0, "AverageEpisodReturn": 0.0, "AverageDiscountedepisodReturn": 0.005029232425394736, "TDError2": 0.3007442475534342, "TotalFramesNumber": 29984}
{"Log_count": 62, "Log_time": "05-06-2021 01:47:21", "Iteration": 6099, "EpisodFramesNumber": 3860, "TMCount": 2123, "RTMCount": 5966, "Epsilon": 0.6968555151997612, "Episodes": 2, "EndOfEpisod": false, "CurrenteEpisodRewardSum": 0, "EpisodRewardsSum": 0.0, "AverageEpisodReturn": 0.0, "AverageDiscountedepisodReturn": 0.005029232425394736, "TDError2": 0.3002694824641326, "TotalFramesNumber": 30484}
{"Log_count": 63, "Log_time": "05-06-2021 02:01:21", "Iteration": 6199, "EpisodFramesNumber": 4360, "TMCount": 1844, "RTMCount": 6110, "Epsilon": 0.69188511866262, "Episodes": 2, "EndOfEpisod": false, "CurrenteEpisodRewardSum": 0, "EpisodRewardsSum": 0.0, "AverageEpisodReturn": 0.0, "AverageDiscountedepisodReturn": 0.005029232425394736, "TDError2": 0.3002033136863615, "TotalFramesNumber": 30984}
{"Log_count": 64, "Log_time": "05-06-2021 02:15:55", "Iteration": 6299, "EpisodFramesNumber": 4860, "TMCount": 2483, "RTMCount": 6258, "Epsilon": 0.6869147221254789, "Episodes": 2, "EndOfEpisod": false, "CurrenteEpisodRewardSum": 0, "EpisodRewardsSum": 0.0, "AverageEpisodReturn": 0.0, "AverageDiscountedepisodReturn": 0.005029232425394736, "TDError2": 0.3003082628139635, "TotalFramesNumber": 31484}
{"Log_count": 65, "Log_time": "05-06-2021 02:30:32", "Iteration": 6399, "EpisodFramesNumber": 5360, "TMCount": 2176, "RTMCount": 6258, "Epsilon": 0.6819443255883377, "Episodes": 2, "EndOfEpisod": false, "CurrenteEpisodRewardSum": 1, "EpisodRewardsSum": 1.0, "AverageEpisodReturn": 0.0, "AverageDiscountedepisodReturn": 0.005029232425394736, "TDError2": 0.3005240490359529, "TotalFramesNumber": 31984}
{"Log_count": 66, "Log_time": "05-06-2021 02:45:13", "Iteration": 6499, "EpisodFramesNumber": 5860, "TMCount": 1913, "RTMCount": 6403, "Epsilon": 0.6769739290511966, "Episodes": 2, "EndOfEpisod": false, "CurrenteEpisodRewardSum": 2, "EpisodRewardsSum": 2.0, "AverageEpisodReturn": 0.0, "AverageDiscountedepisodReturn": 0.005029232425394736, "TDError2": 0.30149455124131874, "TotalFramesNumber": 32484}
{"Log_count": 67, "Log_time": "05-06-2021 03:00:19", "Iteration": 6599, "EpisodFramesNumber": 6360, "TMCount": 2542, "RTMCount": 6553, "Epsilon": 0.6720035325140554, "Episodes": 2, "EndOfEpisod": false, "CurrenteEpisodRewardSum": 0, "EpisodRewardsSum": 0.0, "AverageEpisodReturn": 0.0, "AverageDiscountedepisodReturn": 0.005029232425394736, "TDError2": 0.3016893019922985, "TotalFramesNumber": 32984}
{"Log_count": 68, "Log_time": "05-06-2021 03:15:38", "Iteration": 6699, "EpisodFramesNumber": 6860, "TMCount": 2241, "RTMCount": 6553, "Epsilon": 0.6670331359769143, "Episodes": 2, "EndOfEpisod": false, "CurrenteEpisodRewardSum": 2, "EpisodRewardsSum": 2.0, "AverageEpisodReturn": 0.0, "AverageDiscountedepisodReturn": 0.005029232425394736, "TDError2": 0.30184942817310256, "TotalFramesNumber": 33484}
{"Log_count": 69, "Log_time": "05-06-2021 03:30:55", "Iteration": 6799, "EpisodFramesNumber": 7360, "TMCount": 1981, "RTMCount": 6694, "Epsilon": 0.6620627394397731, "Episodes": 2, "EndOfEpisod": false, "CurrenteEpisodRewardSum": 0, "EpisodRewardsSum": 0.0, "AverageEpisodReturn": 0.0, "AverageDiscountedepisodReturn": 0.005029232425394736, "TDError2": 0.302058181820323, "TotalFramesNumber": 33984}
{"Log_count": 70, "Log_time": "05-06-2021 03:46:48", "Iteration": 6899, "EpisodFramesNumber": 7860, "TMCount": 2610, "RTMCount": 6846, "Epsilon": 0.657092342902632, "Episodes": 2, "EndOfEpisod": false, "CurrenteEpisodRewardSum": 0, "EpisodRewardsSum": 0.0, "AverageEpisodReturn": 0.0, "AverageDiscountedepisodReturn": 0.005029232425394736, "TDError2": 0.30279308655572157, "TotalFramesNumber": 34484}
{"Log_count": 71, "Log_time": "05-06-2021 04:02:46", "Iteration": 6999, "EpisodFramesNumber": 8360, "TMCount": 2294, "RTMCount": 6846, "Epsilon": 0.6521219463654908, "Episodes": 2, "EndOfEpisod": false, "CurrenteEpisodRewardSum": 0, "EpisodRewardsSum": 0.0, "AverageEpisodReturn": 0.0, "AverageDiscountedepisodReturn": 0.005029232425394736, "TDError2": 0.3031624083769619, "TotalFramesNumber": 34984}
{"Log_count": 72, "Log_time": "05-06-2021 04:19:11", "Iteration": 7099, "EpisodFramesNumber": 8860, "TMCount": 2009, "RTMCount": 6982, "Epsilon": 0.6471515498283497, "Episodes": 2, "EndOfEpisod": false, "CurrenteEpisodRewardSum": 0, "EpisodRewardsSum": 0.0, "AverageEpisodReturn": 0.0, "AverageDiscountedepisodReturn": 0.005029232425394736, "TDError2": 0.303592132600583, "TotalFramesNumber": 35484}
{"Log_count": 73, "Log_time": "05-06-2021 04:35:28", "Iteration": 7199, "EpisodFramesNumber": 9360, "TMCount": 1777, "RTMCount": 7134, "Epsilon": 0.6421811532912085, "Episodes": 2, "EndOfEpisod": false, "CurrenteEpisodRewardSum": 0, "EpisodRewardsSum": 0.0, "AverageEpisodReturn": 0.0, "AverageDiscountedepisodReturn": 0.005029232425394736, "TDError2": 0.3008545524826534, "TotalFramesNumber": 35984}
{"Log_count": 74, "Log_time": "05-06-2021 04:52:09", "Iteration": 7299, "EpisodFramesNumber": 9860, "TMCount": 2445, "RTMCount": 7278, "Epsilon": 0.6372107567540674, "Episodes": 2, "EndOfEpisod": false, "CurrenteEpisodRewardSum": 2, "EpisodRewardsSum": 2.0, "AverageEpisodReturn": 0.0, "AverageDiscountedepisodReturn": 0.005029232425394736, "TDError2": 0.3011961476742495, "TotalFramesNumber": 36484}
{"Log_count": 75, "Log_time": "05-06-2021 05:08:53", "Iteration": 7399, "EpisodFramesNumber": 10360, "TMCount": 2155, "RTMCount": 7278, "Epsilon": 0.6322403602169262, "Episodes": 2, "EndOfEpisod": false, "CurrenteEpisodRewardSum": 6, "EpisodRewardsSum": 6.0, "AverageEpisodReturn": 0.0, "AverageDiscountedepisodReturn": 0.005029232425394736, "TDError2": 0.301418144318495, "TotalFramesNumber": 36984}
{"Log_count": 76, "Log_time": "05-06-2021 05:25:41", "Iteration": 7499, "EpisodFramesNumber": 10860, "TMCount": 1917, "RTMCount": 7410, "Epsilon": 0.627269963679785, "Episodes": 2, "EndOfEpisod": false, "CurrenteEpisodRewardSum": 2, "EpisodRewardsSum": 2.0, "AverageEpisodReturn": 0.0, "AverageDiscountedepisodReturn": 0.005029232425394736, "TDError2": 0.3020175982763396, "TotalFramesNumber": 37484}
{"Log_count": 77, "Log_time": "05-06-2021 05:43:01", "Iteration": 7599, "EpisodFramesNumber": 11360, "TMCount": 2580, "RTMCount": 7558, "Epsilon": 0.6222995671426439, "Episodes": 2, "EndOfEpisod": false, "CurrenteEpisodRewardSum": 6, "EpisodRewardsSum": 6.0, "AverageEpisodReturn": 0.0, "AverageDiscountedepisodReturn": 0.005029232425394736, "TDError2": 0.3023914298555384, "TotalFramesNumber": 37984}
{"Log_count": 78, "Log_time": "05-06-2021 06:00:23", "Iteration": 7699, "EpisodFramesNumber": 11860, "TMCount": 2320, "RTMCount": 7558, "Epsilon": 0.6173291706055027, "Episodes": 2, "EndOfEpisod": false, "CurrenteEpisodRewardSum": 8, "EpisodRewardsSum": 8.0, "AverageEpisodReturn": 0.0, "AverageDiscountedepisodReturn": 0.005029232425394736, "TDError2": 0.3027264437303867, "TotalFramesNumber": 38484}
{"Log_count": 79, "Log_time": "05-06-2021 06:17:46", "Iteration": 7799, "EpisodFramesNumber": 12360, "TMCount": 2064, "RTMCount": 7690, "Epsilon": 0.6123587740683616, "Episodes": 2, "EndOfEpisod": false, "CurrenteEpisodRewardSum": 2, "EpisodRewardsSum": 2.0, "AverageEpisodReturn": 0.0, "AverageDiscountedepisodReturn": 0.005029232425394736, "TDError2": 0.30281025265558026, "TotalFramesNumber": 38984}
{"Log_count": 80, "Log_time": "05-06-2021 06:35:20", "Iteration": 7899, "EpisodFramesNumber": 12860, "TMCount": 1846, "RTMCount": 7834, "Epsilon": 0.6073883775312204, "Episodes": 2, "EndOfEpisod": false, "CurrenteEpisodRewardSum": 1, "EpisodRewardsSum": 1.0, "AverageEpisodReturn": 0.0, "AverageDiscountedepisodReturn": 0.005029232425394736, "TDError2": 0.3026532461069827, "TotalFramesNumber": 39484}
{"Log_count": 81, "Log_time": "05-06-2021 06:52:03", "Iteration": 7989, "EpisodFramesNumber": 13310, "TMCount": 2451, "RTMCount": 7970, "Epsilon": 0.6029150206477935, "Episodes": 2, "EndOfEpisod": true, "CurrenteEpisodRewardSum": 1, "EpisodRewardsSum": 1.0, "AverageEpisodReturn": 0.3333333333333333, "AverageDiscountedepisodReturn": 0.005029232425401924, "TDError2": 0.3003034273573653, "TotalFramesNumber": 39934}
{"Log_count": 82, "Log_time": "05-06-2021 06:53:17", "Iteration": 7999, "EpisodFramesNumber": 45, "TMCount": 2513, "RTMCount": 7970, "Epsilon": 0.6024179809940793, "Episodes": 3, "EndOfEpisod": false, "CurrenteEpisodRewardSum": 0, "EpisodRewardsSum": 1.0, "AverageEpisodReturn": 0.3333333333333333, "AverageDiscountedepisodReturn": 0.005029232425401924, "TDError2": 0.30013040336782254, "TotalFramesNumber": 39981}
{"Log_count": 83, "Log_time": "05-06-2021 07:12:09", "Iteration": 8099, "EpisodFramesNumber": 545, "TMCount": 2230, "RTMCount": 7970, "Epsilon": 0.5974475844569381, "Episodes": 3, "EndOfEpisod": false, "CurrenteEpisodRewardSum": 0, "EpisodRewardsSum": 1.0, "AverageEpisodReturn": 0.3333333333333333, "AverageDiscountedepisodReturn": 0.005029232425401924, "TDError2": 0.29780472049844653, "TotalFramesNumber": 40481}
{"Log_count": 84, "Log_time": "05-06-2021 07:30:30", "Iteration": 8199, "EpisodFramesNumber": 1045, "TMCount": 1980, "RTMCount": 8102, "Epsilon": 0.592477187919797, "Episodes": 3, "EndOfEpisod": false, "CurrenteEpisodRewardSum": 0, "EpisodRewardsSum": 1.0, "AverageEpisodReturn": 0.3333333333333333, "AverageDiscountedepisodReturn": 0.005029232425401924, "TDError2": 0.2976931027591462, "TotalFramesNumber": 40981}
{"Log_count": 85, "Log_time": "05-06-2021 07:49:16", "Iteration": 8299, "EpisodFramesNumber": 1545, "TMCount": 2645, "RTMCount": 8244, "Epsilon": 0.5875067913826559, "Episodes": 3, "EndOfEpisod": false, "CurrenteEpisodRewardSum": 1, "EpisodRewardsSum": 2.0, "AverageEpisodReturn": 0.3333333333333333, "AverageDiscountedepisodReturn": 0.005029232425401924, "TDError2": 0.29810933412534263, "TotalFramesNumber": 41481}
{"Log_count": 86, "Log_time": "05-06-2021 08:08:27", "Iteration": 8399, "EpisodFramesNumber": 2045, "TMCount": 2389, "RTMCount": 8244, "Epsilon": 0.5825363948455147, "Episodes": 3, "EndOfEpisod": false, "CurrenteEpisodRewardSum": 0, "EpisodRewardsSum": 1.0, "AverageEpisodReturn": 0.3333333333333333, "AverageDiscountedepisodReturn": 0.005029232425401924, "TDError2": 0.2985727672006192, "TotalFramesNumber": 41981}
{"Log_count": 87, "Log_time": "05-06-2021 08:27:23", "Iteration": 8499, "EpisodFramesNumber": 2545, "TMCount": 2134, "RTMCount": 8380, "Epsilon": 0.5775659983083736, "Episodes": 3, "EndOfEpisod": false, "CurrenteEpisodRewardSum": 0, "EpisodRewardsSum": 1.0, "AverageEpisodReturn": 0.3333333333333333, "AverageDiscountedepisodReturn": 0.005029232425401924, "TDError2": 0.2965340610350809, "TotalFramesNumber": 42481}
{"Log_count": 88, "Log_time": "05-06-2021 08:46:31", "Iteration": 8599, "EpisodFramesNumber": 3045, "TMCount": 1916, "RTMCount": 8524, "Epsilon": 0.5725956017712324, "Episodes": 3, "EndOfEpisod": false, "CurrenteEpisodRewardSum": 1, "EpisodRewardsSum": 2.0, "AverageEpisodReturn": 0.3333333333333333, "AverageDiscountedepisodReturn": 0.005029232425401924, "TDError2": 0.29447830866391883, "TotalFramesNumber": 42981}
{"Log_count": 89, "Log_time": "05-06-2021 09:06:18", "Iteration": 8699, "EpisodFramesNumber": 3545, "TMCount": 2616, "RTMCount": 8660, "Epsilon": 0.5676252052340913, "Episodes": 3, "EndOfEpisod": false, "CurrenteEpisodRewardSum": 5, "EpisodRewardsSum": 6.0, "AverageEpisodReturn": 0.3333333333333333, "AverageDiscountedepisodReturn": 0.005029232425401924, "TDError2": 0.2924654424768132, "TotalFramesNumber": 43481}
{"Log_count": 90, "Log_time": "05-06-2021 09:25:53", "Iteration": 8799, "EpisodFramesNumber": 4045, "TMCount": 2355, "RTMCount": 8660, "Epsilon": 0.5626548086969501, "Episodes": 3, "EndOfEpisod": false, "CurrenteEpisodRewardSum": 3, "EpisodRewardsSum": 4.0, "AverageEpisodReturn": 0.3333333333333333, "AverageDiscountedepisodReturn": 0.005029232425401924, "TDError2": 0.2904797000826396, "TotalFramesNumber": 43981}
{"Log_count": 91, "Log_time": "05-06-2021 09:45:35", "Iteration": 8899, "EpisodFramesNumber": 4545, "TMCount": 2117, "RTMCount": 8788, "Epsilon": 0.557684412159809, "Episodes": 3, "EndOfEpisod": false, "CurrenteEpisodRewardSum": 5, "EpisodRewardsSum": 6.0, "AverageEpisodReturn": 0.3333333333333333, "AverageDiscountedepisodReturn": 0.005029232425401924, "TDError2": 0.2889635712173568, "TotalFramesNumber": 44481}
{"Log_count": 92, "Log_time": "05-06-2021 10:05:40", "Iteration": 8999, "EpisodFramesNumber": 5045, "TMCount": 1904, "RTMCount": 8928, "Epsilon": 0.5527140156226678, "Episodes": 3, "EndOfEpisod": false, "CurrenteEpisodRewardSum": 2, "EpisodRewardsSum": 3.0, "AverageEpisodReturn": 0.3333333333333333, "AverageDiscountedepisodReturn": 0.005029232425401924, "TDError2": 0.28922308396622365, "TotalFramesNumber": 44981}
{"Log_count": 93, "Log_time": "05-06-2021 10:26:33", "Iteration": 9099, "EpisodFramesNumber": 5545, "TMCount": 2630, "RTMCount": 9064, "Epsilon": 0.5477436190855267, "Episodes": 3, "EndOfEpisod": false, "CurrenteEpisodRewardSum": 2, "EpisodRewardsSum": 3.0, "AverageEpisodReturn": 0.3333333333333333, "AverageDiscountedepisodReturn": 0.005029232425401924, "TDError2": 0.28769041192525896, "TotalFramesNumber": 45481}
{"Log_count": 94, "Log_time": "05-06-2021 10:47:01", "Iteration": 9199, "EpisodFramesNumber": 6045, "TMCount": 2373, "RTMCount": 9064, "Epsilon": 0.5427732225483854, "Episodes": 3, "EndOfEpisod": false, "CurrenteEpisodRewardSum": 2, "EpisodRewardsSum": 3.0, "AverageEpisodReturn": 0.3333333333333333, "AverageDiscountedepisodReturn": 0.005029232425401924, "TDError2": 0.286079780465149, "TotalFramesNumber": 45981}
{"Log_count": 95, "Log_time": "05-06-2021 11:07:55", "Iteration": 9299, "EpisodFramesNumber": 6545, "TMCount": 2124, "RTMCount": 9192, "Epsilon": 0.5378028260112444, "Episodes": 3, "EndOfEpisod": false, "CurrenteEpisodRewardSum": 2, "EpisodRewardsSum": 3.0, "AverageEpisodReturn": 0.3333333333333333, "AverageDiscountedepisodReturn": 0.005029232425401924, "TDError2": 0.2845279314938936, "TotalFramesNumber": 46481}
{"Log_count": 96, "Log_time": "05-06-2021 11:28:41", "Iteration": 9399, "EpisodFramesNumber": 7045, "TMCount": 1919, "RTMCount": 9328, "Epsilon": 0.5328324294741031, "Episodes": 3, "EndOfEpisod": false, "CurrenteEpisodRewardSum": 8, "EpisodRewardsSum": 9.0, "AverageEpisodReturn": 0.3333333333333333, "AverageDiscountedepisodReturn": 0.005029232425401924, "TDError2": 0.2847983199027406, "TotalFramesNumber": 46981}
{"Log_count": 97, "Log_time": "05-06-2021 11:50:01", "Iteration": 9499, "EpisodFramesNumber": 7545, "TMCount": 2618, "RTMCount": 9460, "Epsilon": 0.5278620329369621, "Episodes": 3, "EndOfEpisod": false, "CurrenteEpisodRewardSum": 1, "EpisodRewardsSum": 2.0, "AverageEpisodReturn": 0.3333333333333333, "AverageDiscountedepisodReturn": 0.005029232425401924, "TDError2": 0.2833414496335832, "TotalFramesNumber": 47481}
{"Log_count": 98, "Log_time": "05-06-2021 12:11:48", "Iteration": 9599, "EpisodFramesNumber": 8045, "TMCount": 2367, "RTMCount": 9460, "Epsilon": 0.5228916363998208, "Episodes": 3, "EndOfEpisod": false, "CurrenteEpisodRewardSum": 0, "EpisodRewardsSum": 1.0, "AverageEpisodReturn": 0.3333333333333333, "AverageDiscountedepisodReturn": 0.005029232425401924, "TDError2": 0.2821761195276264, "TotalFramesNumber": 47981}
{"Log_count": 99, "Log_time": "05-06-2021 12:33:17", "Iteration": 9699, "EpisodFramesNumber": 8545, "TMCount": 2146, "RTMCount": 9588, "Epsilon": 0.5179212398626798, "Episodes": 3, "EndOfEpisod": false, "CurrenteEpisodRewardSum": 0, "EpisodRewardsSum": 1.0, "AverageEpisodReturn": 0.3333333333333333, "AverageDiscountedepisodReturn": 0.005029232425401924, "TDError2": 0.28272499942730056, "TotalFramesNumber": 48481}
{"Log_count": 100, "Log_time": "05-06-2021 12:54:49", "Iteration": 9799, "EpisodFramesNumber": 9045, "TMCount": 1945, "RTMCount": 9728, "Epsilon": 0.5129508433255385, "Episodes": 3, "EndOfEpisod": false, "CurrenteEpisodRewardSum": 0, "EpisodRewardsSum": 1.0, "AverageEpisodReturn": 0.3333333333333333, "AverageDiscountedepisodReturn": 0.005029232425401924, "TDError2": 0.2828749989592839, "TotalFramesNumber": 48981}
{"Log_count": 101, "Log_time": "05-06-2021 13:17:06", "Iteration": 9899, "EpisodFramesNumber": 9545, "TMCount": 2683, "RTMCount": 9860, "Epsilon": 0.5079804467883975, "Episodes": 3, "EndOfEpisod": false, "CurrenteEpisodRewardSum": 0, "EpisodRewardsSum": 1.0, "AverageEpisodReturn": 0.3333333333333333, "AverageDiscountedepisodReturn": 0.005029232425401924, "TDError2": 0.2813147318577318, "TotalFramesNumber": 49481}
{"Log_count": 102, "Log_time": "05-06-2021 13:39:12", "Iteration": 9999, "EpisodFramesNumber": 10045, "TMCount": 2447, "RTMCount": 9860, "Epsilon": 0.5030100502512562, "Episodes": 3, "EndOfEpisod": false, "CurrenteEpisodRewardSum": 1, "EpisodRewardsSum": 2.0, "AverageEpisodReturn": 0.3333333333333333, "AverageDiscountedepisodReturn": 0.005029232425401924, "TDError2": 0.2799925152536614, "TotalFramesNumber": 49981}
{"Log_count": 103, "Log_time": "05-06-2021 14:02:11", "Iteration": 10099, "EpisodFramesNumber": 10545, "TMCount": 2215, "RTMCount": 9984, "Epsilon": 0.49803965371411507, "Episodes": 3, "EndOfEpisod": false, "CurrenteEpisodRewardSum": 0, "EpisodRewardsSum": 1.0, "AverageEpisodReturn": 0.3333333333333333, "AverageDiscountedepisodReturn": 0.005029232425401924, "TDError2": 0.2805468041506399, "TotalFramesNumber": 50481}
{"Log_count": 104, "Log_time": "05-06-2021 14:25:04", "Iteration": 10199, "EpisodFramesNumber": 11045, "TMCount": 2013, "RTMCount": 10120, "Epsilon": 0.49306925717697403, "Episodes": 3, "EndOfEpisod": false, "CurrenteEpisodRewardSum": 3, "EpisodRewardsSum": 4.0, "AverageEpisodReturn": 0.3333333333333333, "AverageDiscountedepisodReturn": 0.005029232425401924, "TDError2": 0.2809581295795715, "TotalFramesNumber": 50981}
{"Log_count": 105, "Log_time": "05-06-2021 14:47:41", "Iteration": 10299, "EpisodFramesNumber": 11545, "TMCount": 1814, "RTMCount": 10248, "Epsilon": 0.4880988606398329, "Episodes": 3, "EndOfEpisod": false, "CurrenteEpisodRewardSum": 1, "EpisodRewardsSum": 2.0, "AverageEpisodReturn": 0.3333333333333333, "AverageDiscountedepisodReturn": 0.005029232425401924, "TDError2": 0.2814365190489433, "TotalFramesNumber": 51481}
{"Log_count": 106, "Log_time": "05-06-2021 15:11:00", "Iteration": 10399, "EpisodFramesNumber": 12045, "TMCount": 2548, "RTMCount": 10376, "Epsilon": 0.4831284641026916, "Episodes": 3, "EndOfEpisod": false, "CurrenteEpisodRewardSum": 0, "EpisodRewardsSum": 1.0, "AverageEpisodReturn": 0.3333333333333333, "AverageDiscountedepisodReturn": 0.005029232425401924, "TDError2": 0.2812677779702215, "TotalFramesNumber": 51981}
{"Log_count": 107, "Log_time": "05-06-2021 15:34:10", "Iteration": 10499, "EpisodFramesNumber": 12545, "TMCount": 2304, "RTMCount": 10376, "Epsilon": 0.47815806756555046, "Episodes": 3, "EndOfEpisod": false, "CurrenteEpisodRewardSum": 0, "EpisodRewardsSum": 1.0, "AverageEpisodReturn": 0.3333333333333333, "AverageDiscountedepisodReturn": 0.005029232425401924, "TDError2": 0.2813310098099688, "TotalFramesNumber": 52481}
{"Log_count": 108, "Log_time": "05-06-2021 15:57:25", "Iteration": 10599, "EpisodFramesNumber": 13045, "TMCount": 2101, "RTMCount": 10504, "Epsilon": 0.4731876710284094, "Episodes": 3, "EndOfEpisod": false, "CurrenteEpisodRewardSum": 0, "EpisodRewardsSum": 1.0, "AverageEpisodReturn": 0.3333333333333333, "AverageDiscountedepisodReturn": 0.005029232425401924, "TDError2": 0.28146908717527724, "TotalFramesNumber": 52981}
{"Log_count": 109, "Log_time": "05-06-2021 16:11:33", "Iteration": 10652, "EpisodFramesNumber": 13310, "TMCount": 1520, "RTMCount": 10636, "Epsilon": 0.47055336086372457, "Episodes": 3, "EndOfEpisod": true, "CurrenteEpisodRewardSum": 0, "EpisodRewardsSum": 1.0, "AverageEpisodReturn": 0.5, "AverageDiscountedepisodReturn": 0.00502923242540552, "TDError2": 0.28159455980164627, "TotalFramesNumber": 53246}
{"Log_count": 110, "Log_time": "05-06-2021 16:20:58", "Iteration": 10699, "EpisodFramesNumber": 230, "TMCount": 1893, "RTMCount": 10636, "Epsilon": 0.46821727449126826, "Episodes": 4, "EndOfEpisod": false, "CurrenteEpisodRewardSum": 0, "EpisodRewardsSum": 1.0, "AverageEpisodReturn": 0.5, "AverageDiscountedepisodReturn": 0.00502923242540552, "TDError2": 0.2816014179212649, "TotalFramesNumber": 53478}
{"Log_count": 111, "Log_time": "05-06-2021 16:44:46", "Iteration": 10799, "EpisodFramesNumber": 730, "TMCount": 2627, "RTMCount": 10764, "Epsilon": 0.463246877954127, "Episodes": 4, "EndOfEpisod": false, "CurrenteEpisodRewardSum": 4, "EpisodRewardsSum": 5.0, "AverageEpisodReturn": 0.5, "AverageDiscountedepisodReturn": 0.00502923242540552, "TDError2": 0.2813702045217666, "TotalFramesNumber": 53978}
{"Log_count": 112, "Log_time": "05-06-2021 17:08:38", "Iteration": 10899, "EpisodFramesNumber": 1230, "TMCount": 2393, "RTMCount": 10764, "Epsilon": 0.45827648141698585, "Episodes": 4, "EndOfEpisod": false, "CurrenteEpisodRewardSum": 2, "EpisodRewardsSum": 3.0, "AverageEpisodReturn": 0.5, "AverageDiscountedepisodReturn": 0.00502923242540552, "TDError2": 0.28139755072209943, "TotalFramesNumber": 54478}
{"Log_count": 113, "Log_time": "05-06-2021 17:32:29", "Iteration": 10999, "EpisodFramesNumber": 1730, "TMCount": 2169, "RTMCount": 10891, "Epsilon": 0.4533060848798448, "Episodes": 4, "EndOfEpisod": false, "CurrenteEpisodRewardSum": 3, "EpisodRewardsSum": 4.0, "AverageEpisodReturn": 0.5, "AverageDiscountedepisodReturn": 0.00502923242540552, "TDError2": 0.2813315232297794, "TotalFramesNumber": 54978}
{"Log_count": 114, "Log_time": "05-06-2021 17:57:22", "Iteration": 11099, "EpisodFramesNumber": 2230, "TMCount": 1958, "RTMCount": 11026, "Epsilon": 0.44833568834270365, "Episodes": 4, "EndOfEpisod": false, "CurrenteEpisodRewardSum": 0, "EpisodRewardsSum": 1.0, "AverageEpisodReturn": 0.5, "AverageDiscountedepisodReturn": 0.00502923242540552, "TDError2": 0.28015765152426647, "TotalFramesNumber": 55478}
{"Log_count": 115, "Log_time": "05-06-2021 18:22:02", "Iteration": 11199, "EpisodFramesNumber": 2730, "TMCount": 2719, "RTMCount": 11155, "Epsilon": 0.4433652918055625, "Episodes": 4, "EndOfEpisod": false, "CurrenteEpisodRewardSum": 1, "EpisodRewardsSum": 2.0, "AverageEpisodReturn": 0.5, "AverageDiscountedepisodReturn": 0.00502923242540552, "TDError2": 0.27894058469577554, "TotalFramesNumber": 55978}
{"Log_count": 116, "Log_time": "05-06-2021 18:46:44", "Iteration": 11299, "EpisodFramesNumber": 3230, "TMCount": 2476, "RTMCount": 11155, "Epsilon": 0.43839489526842124, "Episodes": 4, "EndOfEpisod": false, "CurrenteEpisodRewardSum": 0, "EpisodRewardsSum": 1.0, "AverageEpisodReturn": 0.5, "AverageDiscountedepisodReturn": 0.00502923242540552, "TDError2": 0.2776072767154177, "TotalFramesNumber": 56478}
{"Log_count": 117, "Log_time": "05-06-2021 19:11:44", "Iteration": 11399, "EpisodFramesNumber": 3730, "TMCount": 2257, "RTMCount": 11283, "Epsilon": 0.4334244987312802, "Episodes": 4, "EndOfEpisod": false, "CurrenteEpisodRewardSum": 4, "EpisodRewardsSum": 5.0, "AverageEpisodReturn": 0.5, "AverageDiscountedepisodReturn": 0.00502923242540552, "TDError2": 0.2779837091716353, "TotalFramesNumber": 56978}
{"Log_count": 118, "Log_time": "05-06-2021 19:36:54", "Iteration": 11499, "EpisodFramesNumber": 4230, "TMCount": 2050, "RTMCount": 11415, "Epsilon": 0.42845410219413904, "Episodes": 4, "EndOfEpisod": false, "CurrenteEpisodRewardSum": 6, "EpisodRewardsSum": 7.0, "AverageEpisodReturn": 0.5, "AverageDiscountedepisodReturn": 0.00502923242540552, "TDError2": 0.27818169202297843, "TotalFramesNumber": 57478}
{"Log_count": 119, "Log_time": "05-06-2021 20:02:06", "Iteration": 11599, "EpisodFramesNumber": 4730, "TMCount": 1863, "RTMCount": 11543, "Epsilon": 0.4234837056569979, "Episodes": 4, "EndOfEpisod": false, "CurrenteEpisodRewardSum": 4, "EpisodRewardsSum": 5.0, "AverageEpisodReturn": 0.5, "AverageDiscountedepisodReturn": 0.00502923242540552, "TDError2": 0.27834844251799906, "TotalFramesNumber": 57978}
{"Log_count": 120, "Log_time": "05-06-2021 20:27:41", "Iteration": 11699, "EpisodFramesNumber": 5230, "TMCount": 2629, "RTMCount": 11671, "Epsilon": 0.4185133091198566, "Episodes": 4, "EndOfEpisod": false, "CurrenteEpisodRewardSum": 6, "EpisodRewardsSum": 7.0, "AverageEpisodReturn": 0.5, "AverageDiscountedepisodReturn": 0.00502923242540552, "TDError2": 0.27865085132668105, "TotalFramesNumber": 58478}
{"Log_count": 121, "Log_time": "05-06-2021 20:53:28", "Iteration": 11799, "EpisodFramesNumber": 5730, "TMCount": 2408, "RTMCount": 11671, "Epsilon": 0.4135429125827156, "Episodes": 4, "EndOfEpisod": false, "CurrenteEpisodRewardSum": 1, "EpisodRewardsSum": 2.0, "AverageEpisodReturn": 0.5, "AverageDiscountedepisodReturn": 0.00502923242540552, "TDError2": 0.278810602726468, "TotalFramesNumber": 58978}
{"Log_count": 122, "Log_time": "05-06-2021 21:19:19", "Iteration": 11899, "EpisodFramesNumber": 6230, "TMCount": 2214, "RTMCount": 11795, "Epsilon": 0.40857251604557443, "Episodes": 4, "EndOfEpisod": false, "CurrenteEpisodRewardSum": 0, "EpisodRewardsSum": 1.0, "AverageEpisodReturn": 0.5, "AverageDiscountedepisodReturn": 0.00502923242540552, "TDError2": 0.27930100045722334, "TotalFramesNumber": 59478}
{"Log_count": 123, "Log_time": "05-06-2021 21:45:18", "Iteration": 11999, "EpisodFramesNumber": 6730, "TMCount": 2012, "RTMCount": 11927, "Epsilon": 0.4036021195084333, "Episodes": 4, "EndOfEpisod": false, "CurrenteEpisodRewardSum": 0, "EpisodRewardsSum": 1.0, "AverageEpisodReturn": 0.5, "AverageDiscountedepisodReturn": 0.00502923242540552, "TDError2": 0.27928100800119043, "TotalFramesNumber": 59978}
{"Log_count": 124, "Log_time": "05-06-2021 22:12:03", "Iteration": 12099, "EpisodFramesNumber": 7230, "TMCount": 1832, "RTMCount": 12051, "Epsilon": 0.398631722971292, "Episodes": 4, "EndOfEpisod": false, "CurrenteEpisodRewardSum": 0, "EpisodRewardsSum": 1.0, "AverageEpisodReturn": 0.5, "AverageDiscountedepisodReturn": 0.00502923242540552, "TDError2": 0.27791973379405865, "TotalFramesNumber": 60478}
{"Log_count": 125, "Log_time": "05-06-2021 22:38:52", "Iteration": 12199, "EpisodFramesNumber": 7730, "TMCount": 2573, "RTMCount": 12175, "Epsilon": 0.39366132643415097, "Episodes": 4, "EndOfEpisod": false, "CurrenteEpisodRewardSum": 0, "EpisodRewardsSum": 1.0, "AverageEpisodReturn": 0.5, "AverageDiscountedepisodReturn": 0.00502923242540552, "TDError2": 0.2765937229707064, "TotalFramesNumber": 60978}
{"Log_count": 126, "Log_time": "05-06-2021 23:05:46", "Iteration": 12299, "EpisodFramesNumber": 8230, "TMCount": 2364, "RTMCount": 12175, "Epsilon": 0.3886909298970098, "Episodes": 4, "EndOfEpisod": false, "CurrenteEpisodRewardSum": 0, "EpisodRewardsSum": 1.0, "AverageEpisodReturn": 0.5, "AverageDiscountedepisodReturn": 0.00502923242540552, "TDError2": 0.2753782043817391, "TotalFramesNumber": 61478}
{"Log_count": 127, "Log_time": "05-06-2021 23:32:43", "Iteration": 12399, "EpisodFramesNumber": 8730, "TMCount": 2160, "RTMCount": 12299, "Epsilon": 0.38372053335986867, "Episodes": 4, "EndOfEpisod": false, "CurrenteEpisodRewardSum": 0, "EpisodRewardsSum": 1.0, "AverageEpisodReturn": 0.5, "AverageDiscountedepisodReturn": 0.00502923242540552, "TDError2": 0.2759915643503161, "TotalFramesNumber": 61978}
{"Log_count": 128, "Log_time": "06-06-2021 00:00:03", "Iteration": 12499, "EpisodFramesNumber": 9230, "TMCount": 1977, "RTMCount": 12431, "Epsilon": 0.3787501368227275, "Episodes": 4, "EndOfEpisod": false, "CurrenteEpisodRewardSum": 0, "EpisodRewardsSum": 1.0, "AverageEpisodReturn": 0.5, "AverageDiscountedepisodReturn": 0.00502923242540552, "TDError2": 0.27492535447869443, "TotalFramesNumber": 62478}
{"Log_count": 129, "Log_time": "06-06-2021 00:27:43", "Iteration": 12599, "EpisodFramesNumber": 9730, "TMCount": 2734, "RTMCount": 12555, "Epsilon": 0.37377974028558636, "Episodes": 4, "EndOfEpisod": false, "CurrenteEpisodRewardSum": 0, "EpisodRewardsSum": 1.0, "AverageEpisodReturn": 0.5, "AverageDiscountedepisodReturn": 0.00502923242540552, "TDError2": 0.27478557619951927, "TotalFramesNumber": 62978}
{"Log_count": 130, "Log_time": "06-06-2021 00:55:16", "Iteration": 12699, "EpisodFramesNumber": 10230, "TMCount": 2513, "RTMCount": 12555, "Epsilon": 0.3688093437484452, "Episodes": 4, "EndOfEpisod": false, "CurrenteEpisodRewardSum": 4, "EpisodRewardsSum": 5.0, "AverageEpisodReturn": 0.5, "AverageDiscountedepisodReturn": 0.00502923242540552, "TDError2": 0.27486954455832174, "TotalFramesNumber": 63478}
{"Log_count": 131, "Log_time": "06-06-2021 01:23:09", "Iteration": 12799, "EpisodFramesNumber": 10730, "TMCount": 2298, "RTMCount": 12679, "Epsilon": 0.36383894721130405, "Episodes": 4, "EndOfEpisod": false, "CurrenteEpisodRewardSum": 0, "EpisodRewardsSum": 1.0, "AverageEpisodReturn": 0.5, "AverageDiscountedepisodReturn": 0.00502923242540552, "TDError2": 0.27510939587410377, "TotalFramesNumber": 63978}
{"Log_count": 132, "Log_time": "06-06-2021 01:51:09", "Iteration": 12899, "EpisodFramesNumber": 11230, "TMCount": 2090, "RTMCount": 12811, "Epsilon": 0.3588685506741629, "Episodes": 4, "EndOfEpisod": false, "CurrenteEpisodRewardSum": 0, "EpisodRewardsSum": 1.0, "AverageEpisodReturn": 0.5, "AverageDiscountedepisodReturn": 0.00502923242540552, "TDError2": 0.27557385877169993, "TotalFramesNumber": 64478}
{"Log_count": 133, "Log_time": "06-06-2021 02:19:16", "Iteration": 12999, "EpisodFramesNumber": 11730, "TMCount": 1892, "RTMCount": 12939, "Epsilon": 0.35389815413702175, "Episodes": 4, "EndOfEpisod": false, "CurrenteEpisodRewardSum": 3, "EpisodRewardsSum": 4.0, "AverageEpisodReturn": 0.5, "AverageDiscountedepisodReturn": 0.00502923242540552, "TDError2": 0.2758417222756804, "TotalFramesNumber": 64978}
{"Log_count": 134, "Log_time": "06-06-2021 02:48:40", "Iteration": 13099, "EpisodFramesNumber": 12230, "TMCount": 2664, "RTMCount": 13067, "Epsilon": 0.3489277575998806, "Episodes": 4, "EndOfEpisod": false, "CurrenteEpisodRewardSum": 0, "EpisodRewardsSum": 1.0, "AverageEpisodReturn": 0.5, "AverageDiscountedepisodReturn": 0.00502923242540552, "TDError2": 0.27594841919763674, "TotalFramesNumber": 65478}
{"Log_count": 135, "Log_time": "06-06-2021 03:17:37", "Iteration": 13199, "EpisodFramesNumber": 12730, "TMCount": 2442, "RTMCount": 13067, "Epsilon": 0.34395736106273944, "Episodes": 4, "EndOfEpisod": false, "CurrenteEpisodRewardSum": 0, "EpisodRewardsSum": 1.0, "AverageEpisodReturn": 0.5, "AverageDiscountedepisodReturn": 0.00502923242540552, "TDError2": 0.27634500228348763, "TotalFramesNumber": 65978}
{"Log_count": 136, "Log_time": "06-06-2021 03:46:44", "Iteration": 13299, "EpisodFramesNumber": 13230, "TMCount": 2253, "RTMCount": 13191, "Epsilon": 0.3389869645255983, "Episodes": 4, "EndOfEpisod": false, "CurrenteEpisodRewardSum": 0, "EpisodRewardsSum": 1.0, "AverageEpisodReturn": 0.5, "AverageDiscountedepisodReturn": 0.00502923242540552, "TDError2": 0.27660005269924237, "TotalFramesNumber": 66478}
{"Log_count": 137, "Log_time": "06-06-2021 03:55:11", "Iteration": 13315, "EpisodFramesNumber": 13310, "TMCount": 1387, "RTMCount": 13319, "Epsilon": 0.3381917010796557, "Episodes": 4, "EndOfEpisod": true, "CurrenteEpisodRewardSum": 1, "EpisodRewardsSum": 2.0, "AverageEpisodReturn": 0.8, "AverageDiscountedepisodReturn": 0.005029232425407676, "TDError2": 0.2764213784238852, "TotalFramesNumber": 66558}
{"Log_count": 138, "Log_time": "06-06-2021 04:16:03", "Iteration": 13399, "EpisodFramesNumber": 415, "TMCount": 2058, "RTMCount": 13319, "Epsilon": 0.33401656798845714, "Episodes": 5, "EndOfEpisod": false, "CurrenteEpisodRewardSum": 1, "EpisodRewardsSum": 3.0, "AverageEpisodReturn": 0.8, "AverageDiscountedepisodReturn": 0.005029232425407676, "TDError2": 0.27547447886565574, "TotalFramesNumber": 66975}
{"Log_count": 139, "Log_time": "06-06-2021 04:45:19", "Iteration": 13499, "EpisodFramesNumber": 915, "TMCount": 1885, "RTMCount": 13447, "Epsilon": 0.329046171451316, "Episodes": 5, "EndOfEpisod": false, "CurrenteEpisodRewardSum": 1, "EpisodRewardsSum": 3.0, "AverageEpisodReturn": 0.8, "AverageDiscountedepisodReturn": 0.005029232425407676, "TDError2": 0.2756624227428529, "TotalFramesNumber": 67475}
{"Log_count": 140, "Log_time": "06-06-2021 05:15:08", "Iteration": 13599, "EpisodFramesNumber": 1415, "TMCount": 2651, "RTMCount": 13570, "Epsilon": 0.32407577491417483, "Episodes": 5, "EndOfEpisod": false, "CurrenteEpisodRewardSum": 1, "EpisodRewardsSum": 3.0, "AverageEpisodReturn": 0.8, "AverageDiscountedepisodReturn": 0.005029232425407676, "TDError2": 0.27602206325894213, "TotalFramesNumber": 67975}
{"Log_count": 141, "Log_time": "06-06-2021 05:44:59", "Iteration": 13699, "EpisodFramesNumber": 1915, "TMCount": 2440, "RTMCount": 13570, "Epsilon": 0.3191053783770337, "Episodes": 5, "EndOfEpisod": false, "CurrenteEpisodRewardSum": 0, "EpisodRewardsSum": 2.0, "AverageEpisodReturn": 0.8, "AverageDiscountedepisodReturn": 0.005029232425407676, "TDError2": 0.27621647182525694, "TotalFramesNumber": 68475}
{"Log_count": 142, "Log_time": "06-06-2021 06:15:12", "Iteration": 13799, "EpisodFramesNumber": 2415, "TMCount": 2260, "RTMCount": 13690, "Epsilon": 0.3141349818398925, "Episodes": 5, "EndOfEpisod": false, "CurrenteEpisodRewardSum": 0, "EpisodRewardsSum": 2.0, "AverageEpisodReturn": 0.8, "AverageDiscountedepisodReturn": 0.005029232425407676, "TDError2": 0.2750651814685927, "TotalFramesNumber": 68975}
{"Log_count": 143, "Log_time": "06-06-2021 06:45:06", "Iteration": 13899, "EpisodFramesNumber": 2915, "TMCount": 2073, "RTMCount": 13818, "Epsilon": 0.30916458530275137, "Episodes": 5, "EndOfEpisod": false, "CurrenteEpisodRewardSum": 0, "EpisodRewardsSum": 2.0, "AverageEpisodReturn": 0.8, "AverageDiscountedepisodReturn": 0.005029232425407676, "TDError2": 0.27528649950669065, "TotalFramesNumber": 69475}
{"Log_count": 144, "Log_time": "06-06-2021 07:15:21", "Iteration": 13999, "EpisodFramesNumber": 3415, "TMCount": 1883, "RTMCount": 13942, "Epsilon": 0.3041941887656102, "Episodes": 5, "EndOfEpisod": false, "CurrenteEpisodRewardSum": 0, "EpisodRewardsSum": 2.0, "AverageEpisodReturn": 0.8, "AverageDiscountedepisodReturn": 0.005029232425407676, "TDError2": 0.27430058368888605, "TotalFramesNumber": 69975}
{"Log_count": 145, "Log_time": "06-06-2021 07:46:21", "Iteration": 14099, "EpisodFramesNumber": 3915, "TMCount": 2666, "RTMCount": 14066, "Epsilon": 0.29922379222846907, "Episodes": 5, "EndOfEpisod": false, "CurrenteEpisodRewardSum": 5, "EpisodRewardsSum": 7.0, "AverageEpisodReturn": 0.8, "AverageDiscountedepisodReturn": 0.005029232425407676, "TDError2": 0.2733200820876238, "TotalFramesNumber": 70475}
{"Log_count": 146, "Log_time": "06-06-2021 08:17:15", "Iteration": 14199, "EpisodFramesNumber": 4415, "TMCount": 2478, "RTMCount": 14066, "Epsilon": 0.2942533956913279, "Episodes": 5, "EndOfEpisod": false, "CurrenteEpisodRewardSum": 5, "EpisodRewardsSum": 7.0, "AverageEpisodReturn": 0.8, "AverageDiscountedepisodReturn": 0.005029232425407676, "TDError2": 0.2723661314760842, "TotalFramesNumber": 70975}
{"Log_count": 147, "Log_time": "06-06-2021 08:47:54", "Iteration": 14299, "EpisodFramesNumber": 4915, "TMCount": 2264, "RTMCount": 14190, "Epsilon": 0.28928299915418676, "Episodes": 5, "EndOfEpisod": false, "CurrenteEpisodRewardSum": 6, "EpisodRewardsSum": 8.0, "AverageEpisodReturn": 0.8, "AverageDiscountedepisodReturn": 0.005029232425407676, "TDError2": 0.27301033967699206, "TotalFramesNumber": 71475}
{"Log_count": 148, "Log_time": "06-06-2021 09:19:07", "Iteration": 14399, "EpisodFramesNumber": 5415, "TMCount": 2078, "RTMCount": 14318, "Epsilon": 0.2843126026170456, "Episodes": 5, "EndOfEpisod": false, "CurrenteEpisodRewardSum": 4, "EpisodRewardsSum": 6.0, "AverageEpisodReturn": 0.8, "AverageDiscountedepisodReturn": 0.005029232425407676, "TDError2": 0.27350942914484294, "TotalFramesNumber": 71975}
{"Log_count": 149, "Log_time": "06-06-2021 09:50:14", "Iteration": 14499, "EpisodFramesNumber": 5915, "TMCount": 1895, "RTMCount": 14442, "Epsilon": 0.27934220607990456, "Episodes": 5, "EndOfEpisod": false, "CurrenteEpisodRewardSum": 3, "EpisodRewardsSum": 5.0, "AverageEpisodReturn": 0.8, "AverageDiscountedepisodReturn": 0.005029232425407676, "TDError2": 0.2724655762337375, "TotalFramesNumber": 72475}
{"Log_count": 150, "Log_time": "06-06-2021 10:22:08", "Iteration": 14599, "EpisodFramesNumber": 6415, "TMCount": 2658, "RTMCount": 14566, "Epsilon": 0.2743718095427633, "Episodes": 5, "EndOfEpisod": false, "CurrenteEpisodRewardSum": 2, "EpisodRewardsSum": 4.0, "AverageEpisodReturn": 0.8, "AverageDiscountedepisodReturn": 0.005029232425407676, "TDError2": 0.27165575611478404, "TotalFramesNumber": 72975}
{"Log_count": 151, "Log_time": "06-06-2021 10:53:59", "Iteration": 14699, "EpisodFramesNumber": 6915, "TMCount": 2446, "RTMCount": 14566, "Epsilon": 0.26940141300562215, "Episodes": 5, "EndOfEpisod": false, "CurrenteEpisodRewardSum": 4, "EpisodRewardsSum": 6.0, "AverageEpisodReturn": 0.8, "AverageDiscountedepisodReturn": 0.005029232425407676, "TDError2": 0.2706861254349097, "TotalFramesNumber": 73475}
{"Log_count": 152, "Log_time": "06-06-2021 11:26:19", "Iteration": 14799, "EpisodFramesNumber": 7415, "TMCount": 2250, "RTMCount": 14690, "Epsilon": 0.264431016468481, "Episodes": 5, "EndOfEpisod": false, "CurrenteEpisodRewardSum": 4, "EpisodRewardsSum": 6.0, "AverageEpisodReturn": 0.8, "AverageDiscountedepisodReturn": 0.005029232425407676, "TDError2": 0.26991091829979047, "TotalFramesNumber": 73975}
{"Log_count": 153, "Log_time": "06-06-2021 11:58:39", "Iteration": 14899, "EpisodFramesNumber": 7915, "TMCount": 2073, "RTMCount": 14818, "Epsilon": 0.25946061993133995, "Episodes": 5, "EndOfEpisod": false, "CurrenteEpisodRewardSum": 0, "EpisodRewardsSum": 2.0, "AverageEpisodReturn": 0.8, "AverageDiscountedepisodReturn": 0.005029232425407676, "TDError2": 0.2702487673667823, "TotalFramesNumber": 74475}
{"Log_count": 154, "Log_time": "06-06-2021 12:31:11", "Iteration": 14999, "EpisodFramesNumber": 8415, "TMCount": 1913, "RTMCount": 14946, "Epsilon": 0.2544902233941987, "Episodes": 5, "EndOfEpisod": false, "CurrenteEpisodRewardSum": 0, "EpisodRewardsSum": 2.0, "AverageEpisodReturn": 0.8, "AverageDiscountedepisodReturn": 0.005029232425407676, "TDError2": 0.27072676085724984, "TotalFramesNumber": 74975}
{"Log_count": 155, "Log_time": "06-06-2021 13:04:57", "Iteration": 15099, "EpisodFramesNumber": 8915, "TMCount": 2699, "RTMCount": 15066, "Epsilon": 0.24951982685705754, "Episodes": 5, "EndOfEpisod": false, "CurrenteEpisodRewardSum": 0, "EpisodRewardsSum": 2.0, "AverageEpisodReturn": 0.8, "AverageDiscountedepisodReturn": 0.005029232425407676, "TDError2": 0.2697589460520503, "TotalFramesNumber": 75475}
{"Log_count": 156, "Log_time": "06-06-2021 13:38:26", "Iteration": 15199, "EpisodFramesNumber": 9415, "TMCount": 2488, "RTMCount": 15066, "Epsilon": 0.24454943031991638, "Episodes": 5, "EndOfEpisod": false, "CurrenteEpisodRewardSum": 3, "EpisodRewardsSum": 5.0, "AverageEpisodReturn": 0.8, "AverageDiscountedepisodReturn": 0.005029232425407676, "TDError2": 0.26892097779982466, "TotalFramesNumber": 75975}
{"Log_count": 157, "Log_time": "06-06-2021 14:11:48", "Iteration": 15299, "EpisodFramesNumber": 9915, "TMCount": 2297, "RTMCount": 15186, "Epsilon": 0.23957903378277534, "Episodes": 5, "EndOfEpisod": false, "CurrenteEpisodRewardSum": 2, "EpisodRewardsSum": 4.0, "AverageEpisodReturn": 0.8, "AverageDiscountedepisodReturn": 0.005029232425407676, "TDError2": 0.26796586523543775, "TotalFramesNumber": 76475}
{"Log_count": 158, "Log_time": "06-06-2021 14:44:55", "Iteration": 15399, "EpisodFramesNumber": 10415, "TMCount": 2123, "RTMCount": 15314, "Epsilon": 0.23460863724563408, "Episodes": 5, "EndOfEpisod": false, "CurrenteEpisodRewardSum": 0, "EpisodRewardsSum": 2.0, "AverageEpisodReturn": 0.8, "AverageDiscountedepisodReturn": 0.005029232425407676, "TDError2": 0.2683576341658357, "TotalFramesNumber": 76975}
{"Log_count": 159, "Log_time": "06-06-2021 15:18:28", "Iteration": 15499, "EpisodFramesNumber": 10915, "TMCount": 1967, "RTMCount": 15438, "Epsilon": 0.22963824070849292, "Episodes": 5, "EndOfEpisod": false, "CurrenteEpisodRewardSum": 3, "EpisodRewardsSum": 5.0, "AverageEpisodReturn": 0.8, "AverageDiscountedepisodReturn": 0.005029232425407676, "TDError2": 0.2688610968171099, "TotalFramesNumber": 77475}
{"Log_count": 160, "Log_time": "06-06-2021 15:52:33", "Iteration": 15599, "EpisodFramesNumber": 11415, "TMCount": 2747, "RTMCount": 15561, "Epsilon": 0.22466784417135177, "Episodes": 5, "EndOfEpisod": false, "CurrenteEpisodRewardSum": 0, "EpisodRewardsSum": 2.0, "AverageEpisodReturn": 0.8, "AverageDiscountedepisodReturn": 0.005029232425407676, "TDError2": 0.2689744546744387, "TotalFramesNumber": 77975}
{"Log_count": 161, "Log_time": "06-06-2021 16:26:48", "Iteration": 15699, "EpisodFramesNumber": 11915, "TMCount": 2538, "RTMCount": 15561, "Epsilon": 0.21969744763421073, "Episodes": 5, "EndOfEpisod": false, "CurrenteEpisodRewardSum": 9, "EpisodRewardsSum": 11.0, "AverageEpisodReturn": 0.8, "AverageDiscountedepisodReturn": 0.005029232425407676, "TDError2": 0.2691184449364838, "TotalFramesNumber": 78475}
{"Log_count": 162, "Log_time": "06-06-2021 17:01:14", "Iteration": 15799, "EpisodFramesNumber": 12415, "TMCount": 2368, "RTMCount": 15682, "Epsilon": 0.21472705109706947, "Episodes": 5, "EndOfEpisod": false, "CurrenteEpisodRewardSum": 4, "EpisodRewardsSum": 6.0, "AverageEpisodReturn": 0.8, "AverageDiscountedepisodReturn": 0.005029232425407676, "TDError2": 0.2682244779408909, "TotalFramesNumber": 78975}
{"Log_count": 163, "Log_time": "06-06-2021 17:35:40", "Iteration": 15899, "EpisodFramesNumber": 12915, "TMCount": 2181, "RTMCount": 15806, "Epsilon": 0.2097566545599283, "Episodes": 5, "EndOfEpisod": false, "CurrenteEpisodRewardSum": 0, "EpisodRewardsSum": 2.0, "AverageEpisodReturn": 0.8, "AverageDiscountedepisodReturn": 0.005029232425407676, "TDError2": 0.268583550014263, "TotalFramesNumber": 79475}
{"Log_count": 164, "Log_time": "06-06-2021 18:04:18", "Iteration": 15978, "EpisodFramesNumber": 13310, "TMCount": 1848, "RTMCount": 15930, "Epsilon": 0.2058300412955869, "Episodes": 5, "EndOfEpisod": true, "CurrenteEpisodRewardSum": 0, "EpisodRewardsSum": 2.0, "AverageEpisodReturn": 1.0, "AverageDiscountedepisodReturn": 0.005029232425409113, "TDError2": 0.26886467900561145, "TotalFramesNumber": 79870}
{"Log_count": 165, "Log_time": "06-06-2021 18:10:14", "Iteration": 15999, "EpisodFramesNumber": 100, "TMCount": 2015, "RTMCount": 15930, "Epsilon": 0.20478625802278716, "Episodes": 6, "EndOfEpisod": false, "CurrenteEpisodRewardSum": 0, "EpisodRewardsSum": 2.0, "AverageEpisodReturn": 1.0, "AverageDiscountedepisodReturn": 0.005029232425409113, "TDError2": 0.26893161947988786, "TotalFramesNumber": 79972}
{"Log_count": 166, "Log_time": "06-06-2021 18:45:46", "Iteration": 16099, "EpisodFramesNumber": 600, "TMCount": 1843, "RTMCount": 16054, "Epsilon": 0.19981586148564612, "Episodes": 6, "EndOfEpisod": false, "CurrenteEpisodRewardSum": 1, "EpisodRewardsSum": 3.0, "AverageEpisodReturn": 1.0, "AverageDiscountedepisodReturn": 0.005029232425409113, "TDError2": 0.2680923537905957, "TotalFramesNumber": 80472}
{"Log_count": 167, "Log_time": "06-06-2021 19:21:26", "Iteration": 16199, "EpisodFramesNumber": 1100, "TMCount": 2630, "RTMCount": 16172, "Epsilon": 0.19484546494850485, "Episodes": 6, "EndOfEpisod": false, "CurrenteEpisodRewardSum": 4, "EpisodRewardsSum": 6.0, "AverageEpisodReturn": 1.0, "AverageDiscountedepisodReturn": 0.005029232425409113, "TDError2": 0.2671924733268923, "TotalFramesNumber": 80972}
{"Log_count": 168, "Log_time": "06-06-2021 19:57:02", "Iteration": 16299, "EpisodFramesNumber": 1600, "TMCount": 2432, "RTMCount": 16172, "Epsilon": 0.1898750684113637, "Episodes": 6, "EndOfEpisod": false, "CurrenteEpisodRewardSum": 2, "EpisodRewardsSum": 4.0, "AverageEpisodReturn": 1.0, "AverageDiscountedepisodReturn": 0.005029232425409113, "TDError2": 0.2663397610280097, "TotalFramesNumber": 81472}
{"Log_count": 169, "Log_time": "06-06-2021 20:32:55", "Iteration": 16399, "EpisodFramesNumber": 2100, "TMCount": 2255, "RTMCount": 16292, "Epsilon": 0.18490467187422266, "Episodes": 6, "EndOfEpisod": false, "CurrenteEpisodRewardSum": 2, "EpisodRewardsSum": 4.0, "AverageEpisodReturn": 1.0, "AverageDiscountedepisodReturn": 0.005029232425409113, "TDError2": 0.2656914211706108, "TotalFramesNumber": 81972}
{"Log_count": 170, "Log_time": "06-06-2021 21:08:40", "Iteration": 16499, "EpisodFramesNumber": 2600, "TMCount": 2098, "RTMCount": 16420, "Epsilon": 0.1799342753370815, "Episodes": 6, "EndOfEpisod": false, "CurrenteEpisodRewardSum": 3, "EpisodRewardsSum": 5.0, "AverageEpisodReturn": 1.0, "AverageDiscountedepisodReturn": 0.005029232425409113, "TDError2": 0.2650254022324958, "TotalFramesNumber": 82472}
{"Log_count": 171, "Log_time": "06-06-2021 21:44:41", "Iteration": 16599, "EpisodFramesNumber": 3100, "TMCount": 1943, "RTMCount": 16544, "Epsilon": 0.17496387879994024, "Episodes": 6, "EndOfEpisod": false, "CurrenteEpisodRewardSum": 0, "EpisodRewardsSum": 2.0, "AverageEpisodReturn": 1.0, "AverageDiscountedepisodReturn": 0.005029232425409113, "TDError2": 0.26421976324411744, "TotalFramesNumber": 82972}
{"Log_count": 172, "Log_time": "06-06-2021 22:21:06", "Iteration": 16699, "EpisodFramesNumber": 3600, "TMCount": 2754, "RTMCount": 16664, "Epsilon": 0.1699934822627991, "Episodes": 6, "EndOfEpisod": false, "CurrenteEpisodRewardSum": 2, "EpisodRewardsSum": 4.0, "AverageEpisodReturn": 1.0, "AverageDiscountedepisodReturn": 0.005029232425409113, "TDError2": 0.26358143621364394, "TotalFramesNumber": 83472}
{"Log_count": 173, "Log_time": "06-06-2021 22:57:39", "Iteration": 16799, "EpisodFramesNumber": 4100, "TMCount": 2566, "RTMCount": 16664, "Epsilon": 0.16502308572565805, "Episodes": 6, "EndOfEpisod": false, "CurrenteEpisodRewardSum": 3, "EpisodRewardsSum": 5.0, "AverageEpisodReturn": 1.0, "AverageDiscountedepisodReturn": 0.005029232425409113, "TDError2": 0.2627188373231403, "TotalFramesNumber": 83972}
{"Log_count": 174, "Log_time": "06-06-2021 23:34:18", "Iteration": 16899, "EpisodFramesNumber": 4600, "TMCount": 2386, "RTMCount": 16780, "Epsilon": 0.1600526891885169, "Episodes": 6, "EndOfEpisod": false, "CurrenteEpisodRewardSum": 3, "EpisodRewardsSum": 5.0, "AverageEpisodReturn": 1.0, "AverageDiscountedepisodReturn": 0.005029232425409113, "TDError2": 0.26296431894455047, "TotalFramesNumber": 84472}
{"Log_count": 175, "Log_time": "07-06-2021 00:11:06", "Iteration": 16999, "EpisodFramesNumber": 5100, "TMCount": 2222, "RTMCount": 16904, "Epsilon": 0.15508229265137563, "Episodes": 6, "EndOfEpisod": false, "CurrenteEpisodRewardSum": 5, "EpisodRewardsSum": 7.0, "AverageEpisodReturn": 1.0, "AverageDiscountedepisodReturn": 0.005029232425409113, "TDError2": 0.2622139573451846, "TotalFramesNumber": 84972}
{"Log_count": 176, "Log_time": "07-06-2021 00:49:06", "Iteration": 17099, "EpisodFramesNumber": 5600, "TMCount": 2055, "RTMCount": 17028, "Epsilon": 0.15011189611423448, "Episodes": 6, "EndOfEpisod": false, "CurrenteEpisodRewardSum": 0, "EpisodRewardsSum": 2.0, "AverageEpisodReturn": 1.0, "AverageDiscountedepisodReturn": 0.005029232425409113, "TDError2": 0.2627582989226238, "TotalFramesNumber": 85472}
{"Log_count": 177, "Log_time": "07-06-2021 01:26:41", "Iteration": 17199, "EpisodFramesNumber": 6100, "TMCount": 1891, "RTMCount": 17148, "Epsilon": 0.14514149957709344, "Episodes": 6, "EndOfEpisod": false, "CurrenteEpisodRewardSum": 0, "EpisodRewardsSum": 2.0, "AverageEpisodReturn": 1.0, "AverageDiscountedepisodReturn": 0.005029232425409113, "TDError2": 0.26195917025547094, "TotalFramesNumber": 85972}
{"Log_count": 178, "Log_time": "07-06-2021 02:04:32", "Iteration": 17299, "EpisodFramesNumber": 6600, "TMCount": 2698, "RTMCount": 17268, "Epsilon": 0.14017110303995228, "Episodes": 6, "EndOfEpisod": false, "CurrenteEpisodRewardSum": 2, "EpisodRewardsSum": 4.0, "AverageEpisodReturn": 1.0, "AverageDiscountedepisodReturn": 0.005029232425409113, "TDError2": 0.26105290533769465, "TotalFramesNumber": 86472}
{"Log_count": 179, "Log_time": "07-06-2021 02:42:38", "Iteration": 17399, "EpisodFramesNumber": 7100, "TMCount": 2523, "RTMCount": 17268, "Epsilon": 0.13520070650281113, "Episodes": 6, "EndOfEpisod": false, "CurrenteEpisodRewardSum": 1, "EpisodRewardsSum": 3.0, "AverageEpisodReturn": 1.0, "AverageDiscountedepisodReturn": 0.005029232425409113, "TDError2": 0.2602155192893624, "TotalFramesNumber": 86972}
{"Log_count": 180, "Log_time": "07-06-2021 03:20:41", "Iteration": 17499, "EpisodFramesNumber": 7600, "TMCount": 2337, "RTMCount": 17388, "Epsilon": 0.13023030996566987, "Episodes": 6, "EndOfEpisod": false, "CurrenteEpisodRewardSum": 0, "EpisodRewardsSum": 2.0, "AverageEpisodReturn": 1.0, "AverageDiscountedepisodReturn": 0.005029232425409113, "TDError2": 0.2604776834459113, "TotalFramesNumber": 87472}
{"Log_count": 181, "Log_time": "07-06-2021 03:58:51", "Iteration": 17599, "EpisodFramesNumber": 8100, "TMCount": 2162, "RTMCount": 17509, "Epsilon": 0.12525991342852882, "Episodes": 6, "EndOfEpisod": false, "CurrenteEpisodRewardSum": 1, "EpisodRewardsSum": 3.0, "AverageEpisodReturn": 1.0, "AverageDiscountedepisodReturn": 0.005029232425409113, "TDError2": 0.2608310264941832, "TotalFramesNumber": 87972}
{"Log_count": 182, "Log_time": "07-06-2021 04:37:23", "Iteration": 17699, "EpisodFramesNumber": 8600, "TMCount": 2003, "RTMCount": 17632, "Epsilon": 0.12028951689138767, "Episodes": 6, "EndOfEpisod": false, "CurrenteEpisodRewardSum": 0, "EpisodRewardsSum": 2.0, "AverageEpisodReturn": 1.0, "AverageDiscountedepisodReturn": 0.005029232425409113, "TDError2": 0.2609028646007281, "TotalFramesNumber": 88472}
{"Log_count": 183, "Log_time": "07-06-2021 05:15:51", "Iteration": 17799, "EpisodFramesNumber": 9100, "TMCount": 1857, "RTMCount": 17752, "Epsilon": 0.11531912035424652, "Episodes": 6, "EndOfEpisod": false, "CurrenteEpisodRewardSum": 0, "EpisodRewardsSum": 2.0, "AverageEpisodReturn": 1.0, "AverageDiscountedepisodReturn": 0.005029232425409113, "TDError2": 0.26121047634900113, "TotalFramesNumber": 88972}
{"Log_count": 184, "Log_time": "07-06-2021 05:55:02", "Iteration": 17899, "EpisodFramesNumber": 9600, "TMCount": 2668, "RTMCount": 17872, "Epsilon": 0.11034872381710525, "Episodes": 6, "EndOfEpisod": false, "CurrenteEpisodRewardSum": 4, "EpisodRewardsSum": 6.0, "AverageEpisodReturn": 1.0, "AverageDiscountedepisodReturn": 0.005029232425409113, "TDError2": 0.26154380084992845, "TotalFramesNumber": 89472}
{"Log_count": 185, "Log_time": "07-06-2021 06:34:14", "Iteration": 17999, "EpisodFramesNumber": 10100, "TMCount": 2480, "RTMCount": 17872, "Epsilon": 0.10537832727996421, "Episodes": 6, "EndOfEpisod": false, "CurrenteEpisodRewardSum": 10, "EpisodRewardsSum": 12.0, "AverageEpisodReturn": 1.0, "AverageDiscountedepisodReturn": 0.005029232425409113, "TDError2": 0.2618608909787133, "TotalFramesNumber": 89972}
{"Log_count": 186, "Log_time": "07-06-2021 07:14:52", "Iteration": 18099, "EpisodFramesNumber": 10600, "TMCount": 2303, "RTMCount": 17992, "Epsilon": 0.10040793074282306, "Episodes": 6, "EndOfEpisod": false, "CurrenteEpisodRewardSum": 6, "EpisodRewardsSum": 8.0, "AverageEpisodReturn": 1.0, "AverageDiscountedepisodReturn": 0.005029232425409113, "TDError2": 0.2621414676046906, "TotalFramesNumber": 90472}
{"Log_count": 187, "Log_time": "07-06-2021 07:54:46", "Iteration": 18199, "EpisodFramesNumber": 11100, "TMCount": 2129, "RTMCount": 18115, "Epsilon": 0.0954375342056819, "Episodes": 6, "EndOfEpisod": false, "CurrenteEpisodRewardSum": 4, "EpisodRewardsSum": 6.0, "AverageEpisodReturn": 1.0, "AverageDiscountedepisodReturn": 0.005029232425409113, "TDError2": 0.26249434396775845, "TotalFramesNumber": 90972}
{"Log_count": 188, "Log_time": "07-06-2021 08:34:47", "Iteration": 18299, "EpisodFramesNumber": 11600, "TMCount": 1973, "RTMCount": 18236, "Epsilon": 0.09046713766854064, "Episodes": 6, "EndOfEpisod": false, "CurrenteEpisodRewardSum": 0, "EpisodRewardsSum": 2.0, "AverageEpisodReturn": 1.0, "AverageDiscountedepisodReturn": 0.005029232425409113, "TDError2": 0.2616717326657972, "TotalFramesNumber": 91472}
{"Log_count": 189, "Log_time": "07-06-2021 09:15:23", "Iteration": 18399, "EpisodFramesNumber": 12100, "TMCount": 2774, "RTMCount": 18360, "Epsilon": 0.0854967411313996, "Episodes": 6, "EndOfEpisod": false, "CurrenteEpisodRewardSum": 0, "EpisodRewardsSum": 2.0, "AverageEpisodReturn": 1.0, "AverageDiscountedepisodReturn": 0.005029232425409113, "TDError2": 0.26197373805650215, "TotalFramesNumber": 91972}
{"Log_count": 190, "Log_time": "07-06-2021 09:55:02", "Iteration": 18499, "EpisodFramesNumber": 12600, "TMCount": 2581, "RTMCount": 18360, "Epsilon": 0.08052634459425845, "Episodes": 6, "EndOfEpisod": false, "CurrenteEpisodRewardSum": 0, "EpisodRewardsSum": 2.0, "AverageEpisodReturn": 1.0, "AverageDiscountedepisodReturn": 0.005029232425409113, "TDError2": 0.2623271889605786, "TotalFramesNumber": 92472}
{"Log_count": 191, "Log_time": "07-06-2021 10:34:48", "Iteration": 18599, "EpisodFramesNumber": 13100, "TMCount": 2406, "RTMCount": 18476, "Epsilon": 0.0755559480571173, "Episodes": 6, "EndOfEpisod": false, "CurrenteEpisodRewardSum": 0, "EpisodRewardsSum": 2.0, "AverageEpisodReturn": 1.0, "AverageDiscountedepisodReturn": 0.005029232425409113, "TDError2": 0.2616726693877445, "TotalFramesNumber": 92972}
{"Log_count": 192, "Log_time": "07-06-2021 10:55:24", "Iteration": 18641, "EpisodFramesNumber": 13310, "TMCount": 1773, "RTMCount": 18604, "Epsilon": 0.07346838151151802, "Episodes": 6, "EndOfEpisod": true, "CurrenteEpisodRewardSum": 0, "EpisodRewardsSum": 2.0, "AverageEpisodReturn": 1.1428571428571428, "AverageDiscountedepisodReturn": 0.00502923242541014, "TDError2": 0.26164818014454005, "TotalFramesNumber": 93182}
{"Log_count": 193, "Log_time": "07-06-2021 11:14:54", "Iteration": 18699, "EpisodFramesNumber": 285, "TMCount": 2235, "RTMCount": 18604, "Epsilon": 0.07058555151997603, "Episodes": 7, "EndOfEpisod": false, "CurrenteEpisodRewardSum": 2, "EpisodRewardsSum": 4.0, "AverageEpisodReturn": 1.1428571428571428, "AverageDiscountedepisodReturn": 0.00502923242541014, "TDError2": 0.2616374283375058, "TotalFramesNumber": 93469}
{"Log_count": 194, "Log_time": "07-06-2021 11:54:43", "Iteration": 18799, "EpisodFramesNumber": 785, "TMCount": 2070, "RTMCount": 18724, "Epsilon": 0.06561515498283499, "Episodes": 7, "EndOfEpisod": false, "CurrenteEpisodRewardSum": 2, "EpisodRewardsSum": 4.0, "AverageEpisodReturn": 1.1428571428571428, "AverageDiscountedepisodReturn": 0.00502923242541014, "TDError2": 0.26096410852723306, "TotalFramesNumber": 93969}
{"Log_count": 195, "Log_time": "07-06-2021 12:35:09", "Iteration": 18899, "EpisodFramesNumber": 1285, "TMCount": 1924, "RTMCount": 18838, "Epsilon": 0.060644758445693836, "Episodes": 7, "EndOfEpisod": false, "CurrenteEpisodRewardSum": 3, "EpisodRewardsSum": 5.0, "AverageEpisodReturn": 1.1428571428571428, "AverageDiscountedepisodReturn": 0.00502923242541014, "TDError2": 0.2601789102297713, "TotalFramesNumber": 94469}
{"Log_count": 196, "Log_time": "07-06-2021 13:16:04", "Iteration": 18999, "EpisodFramesNumber": 1785, "TMCount": 2729, "RTMCount": 18960, "Epsilon": 0.05567436190855268, "Episodes": 7, "EndOfEpisod": false, "CurrenteEpisodRewardSum": 1, "EpisodRewardsSum": 3.0, "AverageEpisodReturn": 1.1428571428571428, "AverageDiscountedepisodReturn": 0.00502923242541014, "TDError2": 0.26051252297421, "TotalFramesNumber": 94969}
{"Log_count": 197, "Log_time": "07-06-2021 13:57:52", "Iteration": 19099, "EpisodFramesNumber": 2285, "TMCount": 2540, "RTMCount": 18960, "Epsilon": 0.05070396537141142, "Episodes": 7, "EndOfEpisod": false, "CurrenteEpisodRewardSum": 1, "EpisodRewardsSum": 3.0, "AverageEpisodReturn": 1.1428571428571428, "AverageDiscountedepisodReturn": 0.00502923242541014, "TDError2": 0.26076854713419767, "TotalFramesNumber": 95469}
{"Log_count": 198, "Log_time": "07-06-2021 14:39:16", "Iteration": 19199, "EpisodFramesNumber": 2785, "TMCount": 2361, "RTMCount": 19078, "Epsilon": 0.04573356883427038, "Episodes": 7, "EndOfEpisod": false, "CurrenteEpisodRewardSum": 0, "EpisodRewardsSum": 2.0, "AverageEpisodReturn": 1.1428571428571428, "AverageDiscountedepisodReturn": 0.00502923242541014, "TDError2": 0.2610108154250006, "TotalFramesNumber": 95969}
{"Log_count": 199, "Log_time": "07-06-2021 15:21:06", "Iteration": 19299, "EpisodFramesNumber": 3285, "TMCount": 2208, "RTMCount": 19202, "Epsilon": 0.040763172297129224, "Episodes": 7, "EndOfEpisod": false, "CurrenteEpisodRewardSum": 2, "EpisodRewardsSum": 4.0, "AverageEpisodReturn": 1.1428571428571428, "AverageDiscountedepisodReturn": 0.00502923242541014, "TDError2": 0.2603198564227945, "TotalFramesNumber": 96469}
{"Log_count": 200, "Log_time": "07-06-2021 16:02:53", "Iteration": 19399, "EpisodFramesNumber": 3785, "TMCount": 2050, "RTMCount": 19326, "Epsilon": 0.03579277575998807, "Episodes": 7, "EndOfEpisod": false, "CurrenteEpisodRewardSum": 3, "EpisodRewardsSum": 5.0, "AverageEpisodReturn": 1.1428571428571428, "AverageDiscountedepisodReturn": 0.00502923242541014, "TDError2": 0.2595588907790795, "TotalFramesNumber": 96969}
{"Log_count": 201, "Log_time": "07-06-2021 16:44:44", "Iteration": 19499, "EpisodFramesNumber": 4285, "TMCount": 1895, "RTMCount": 19442, "Epsilon": 0.030822379222846807, "Episodes": 7, "EndOfEpisod": false, "CurrenteEpisodRewardSum": 1, "EpisodRewardsSum": 3.0, "AverageEpisodReturn": 1.1428571428571428, "AverageDiscountedepisodReturn": 0.00502923242541014, "TDError2": 0.25898730316883806, "TotalFramesNumber": 97469}
{"Log_count": 202, "Log_time": "07-06-2021 17:27:00", "Iteration": 19599, "EpisodFramesNumber": 4785, "TMCount": 2701, "RTMCount": 19562, "Epsilon": 0.025851982685705766, "Episodes": 7, "EndOfEpisod": false, "CurrenteEpisodRewardSum": 2, "EpisodRewardsSum": 4.0, "AverageEpisodReturn": 1.1428571428571428, "AverageDiscountedepisodReturn": 0.00502923242541014, "TDError2": 0.25934519216282886, "TotalFramesNumber": 97969}
{"Log_count": 203, "Log_time": "07-06-2021 18:09:27", "Iteration": 19699, "EpisodFramesNumber": 5285, "TMCount": 2528, "RTMCount": 19562, "Epsilon": 0.020881586148564613, "Episodes": 7, "EndOfEpisod": false, "CurrenteEpisodRewardSum": 2, "EpisodRewardsSum": 4.0, "AverageEpisodReturn": 1.1428571428571428, "AverageDiscountedepisodReturn": 0.00502923242541014, "TDError2": 0.25972518735843814, "TotalFramesNumber": 98469}
{"Log_count": 204, "Log_time": "07-06-2021 18:51:57", "Iteration": 19799, "EpisodFramesNumber": 5785, "TMCount": 2356, "RTMCount": 19682, "Epsilon": 0.01591118961142346, "Episodes": 7, "EndOfEpisod": false, "CurrenteEpisodRewardSum": 0, "EpisodRewardsSum": 2.0, "AverageEpisodReturn": 1.1428571428571428, "AverageDiscountedepisodReturn": 0.00502923242541014, "TDError2": 0.2591272001671569, "TotalFramesNumber": 98969}
{"Log_count": 205, "Log_time": "07-06-2021 19:34:35", "Iteration": 19899, "EpisodFramesNumber": 6285, "TMCount": 2194, "RTMCount": 19806, "Epsilon": 0.010940793074282196, "Episodes": 7, "EndOfEpisod": false, "CurrenteEpisodRewardSum": 1, "EpisodRewardsSum": 3.0, "AverageEpisodReturn": 1.1428571428571428, "AverageDiscountedepisodReturn": 0.00502923242541014, "TDError2": 0.25935533022250024, "TotalFramesNumber": 99469}
{"Log_count": 206, "Log_time": "07-06-2021 20:17:22", "Iteration": 19999, "EpisodFramesNumber": 6785, "TMCount": 2046, "RTMCount": 19926, "Epsilon": 0.005970396537141154, "Episodes": 7, "EndOfEpisod": false, "CurrenteEpisodRewardSum": 2, "EpisodRewardsSum": 4.0, "AverageEpisodReturn": 1.1428571428571428, "AverageDiscountedepisodReturn": 0.00502923242541014, "TDError2": 0.25937026076399, "TotalFramesNumber": 99969}
{"Log_count": 207, "Log_time": "07-06-2021 21:01:29", "Iteration": 20099, "EpisodFramesNumber": 7285, "TMCount": 1896, "RTMCount": 20046, "Epsilon": 0.0010000000000000009, "Episodes": 7, "EndOfEpisod": false, "CurrenteEpisodRewardSum": 2, "EpisodRewardsSum": 4.0, "AverageEpisodReturn": 1.1428571428571428, "AverageDiscountedepisodReturn": 0.00502923242541014, "TDError2": 0.25968533018041196, "TotalFramesNumber": 100469}
{"Log_count": 208, "Log_time": "07-06-2021 21:45:23", "Iteration": 20199, "EpisodFramesNumber": 7785, "TMCount": 2707, "RTMCount": 20162, "Epsilon": 0.0010000000000000009, "Episodes": 7, "EndOfEpisod": false, "CurrenteEpisodRewardSum": 0, "EpisodRewardsSum": 2.0, "AverageEpisodReturn": 1.1428571428571428, "AverageDiscountedepisodReturn": 0.00502923242541014, "TDError2": 0.2600035597254744, "TotalFramesNumber": 100969}
{"Log_count": 209, "Log_time": "07-06-2021 22:28:57", "Iteration": 20299, "EpisodFramesNumber": 8285, "TMCount": 2520, "RTMCount": 20162, "Epsilon": 0.0010000000000000009, "Episodes": 7, "EndOfEpisod": false, "CurrenteEpisodRewardSum": 0, "EpisodRewardsSum": 2.0, "AverageEpisodReturn": 1.1428571428571428, "AverageDiscountedepisodReturn": 0.00502923242541014, "TDError2": 0.26026257169371053, "TotalFramesNumber": 101469}
{"Log_count": 210, "Log_time": "07-06-2021 23:13:01", "Iteration": 20399, "EpisodFramesNumber": 8785, "TMCount": 2365, "RTMCount": 20282, "Epsilon": 0.0010000000000000009, "Episodes": 7, "EndOfEpisod": false, "CurrenteEpisodRewardSum": 0, "EpisodRewardsSum": 2.0, "AverageEpisodReturn": 1.1428571428571428, "AverageDiscountedepisodReturn": 0.00502923242541014, "TDError2": 0.2602615411317709, "TotalFramesNumber": 101969}
{"Log_count": 211, "Log_time": "07-06-2021 23:56:26", "Iteration": 20499, "EpisodFramesNumber": 9285, "TMCount": 2209, "RTMCount": 20402, "Epsilon": 0.0010000000000000009, "Episodes": 7, "EndOfEpisod": false, "CurrenteEpisodRewardSum": 0, "EpisodRewardsSum": 2.0, "AverageEpisodReturn": 1.1428571428571428, "AverageDiscountedepisodReturn": 0.00502923242541014, "TDError2": 0.26030790312668745, "TotalFramesNumber": 102469}
{"Log_count": 212, "Log_time": "08-06-2021 00:40:15", "Iteration": 20599, "EpisodFramesNumber": 9785, "TMCount": 2055, "RTMCount": 20526, "Epsilon": 0.0010000000000000009, "Episodes": 7, "EndOfEpisod": false, "CurrenteEpisodRewardSum": 1, "EpisodRewardsSum": 3.0, "AverageEpisodReturn": 1.1428571428571428, "AverageDiscountedepisodReturn": 0.00502923242541014, "TDError2": 0.26035933141629125, "TotalFramesNumber": 102969}
{"Log_count": 213, "Log_time": "08-06-2021 01:24:04", "Iteration": 20699, "EpisodFramesNumber": 10285, "TMCount": 1909, "RTMCount": 20645, "Epsilon": 0.0010000000000000009, "Episodes": 7, "EndOfEpisod": false, "CurrenteEpisodRewardSum": 3, "EpisodRewardsSum": 5.0, "AverageEpisodReturn": 1.1428571428571428, "AverageDiscountedepisodReturn": 0.00502923242541014, "TDError2": 0.26056984638935327, "TotalFramesNumber": 103469}
{"Log_count": 214, "Log_time": "08-06-2021 02:08:23", "Iteration": 20799, "EpisodFramesNumber": 10785, "TMCount": 2729, "RTMCount": 20762, "Epsilon": 0.0010000000000000009, "Episodes": 7, "EndOfEpisod": false, "CurrenteEpisodRewardSum": 8, "EpisodRewardsSum": 10.0, "AverageEpisodReturn": 1.1428571428571428, "AverageDiscountedepisodReturn": 0.00502923242541014, "TDError2": 0.260755115690603, "TotalFramesNumber": 103969}
{"Log_count": 215, "Log_time": "08-06-2021 02:52:51", "Iteration": 20899, "EpisodFramesNumber": 11285, "TMCount": 2542, "RTMCount": 20762, "Epsilon": 0.0010000000000000009, "Episodes": 7, "EndOfEpisod": false, "CurrenteEpisodRewardSum": 5, "EpisodRewardsSum": 7.0, "AverageEpisodReturn": 1.1428571428571428, "AverageDiscountedepisodReturn": 0.00502923242541014, "TDError2": 0.2610592400795256, "TotalFramesNumber": 104469}
{"Log_count": 216, "Log_time": "08-06-2021 03:37:49", "Iteration": 20999, "EpisodFramesNumber": 11785, "TMCount": 2371, "RTMCount": 20878, "Epsilon": 0.0010000000000000009, "Episodes": 7, "EndOfEpisod": false, "CurrenteEpisodRewardSum": 0, "EpisodRewardsSum": 2.0, "AverageEpisodReturn": 1.1428571428571428, "AverageDiscountedepisodReturn": 0.00502923242541014, "TDError2": 0.2613112095301283, "TotalFramesNumber": 104969}
{"Log_count": 217, "Log_time": "08-06-2021 04:24:42", "Iteration": 21099, "EpisodFramesNumber": 12285, "TMCount": 2221, "RTMCount": 21002, "Epsilon": 0.0010000000000000009, "Episodes": 7, "EndOfEpisod": false, "CurrenteEpisodRewardSum": 0, "EpisodRewardsSum": 2.0, "AverageEpisodReturn": 1.1428571428571428, "AverageDiscountedepisodReturn": 0.00502923242541014, "TDError2": 0.26149279921465846, "TotalFramesNumber": 105469}
{"Log_count": 218, "Log_time": "08-06-2021 05:10:33", "Iteration": 21199, "EpisodFramesNumber": 12785, "TMCount": 2059, "RTMCount": 21122, "Epsilon": 0.0010000000000000009, "Episodes": 7, "EndOfEpisod": false, "CurrenteEpisodRewardSum": 0, "EpisodRewardsSum": 2.0, "AverageEpisodReturn": 1.1428571428571428, "AverageDiscountedepisodReturn": 0.00502923242541014, "TDError2": 0.2607798091375565, "TotalFramesNumber": 105969}
{"Log_count": 219, "Log_time": "08-06-2021 05:56:31", "Iteration": 21299, "EpisodFramesNumber": 13285, "TMCount": 1912, "RTMCount": 21242, "Epsilon": 0.0010000000000000009, "Episodes": 7, "EndOfEpisod": false, "CurrenteEpisodRewardSum": 0, "EpisodRewardsSum": 2.0, "AverageEpisodReturn": 1.1428571428571428, "AverageDiscountedepisodReturn": 0.00502923242541014, "TDError2": 0.2608924350195064, "TotalFramesNumber": 106469}
{"Log_count": 220, "Log_time": "08-06-2021 06:04:59", "Iteration": 21304, "EpisodFramesNumber": 13310, "TMCount": 1947, "RTMCount": 21362, "Epsilon": 0.0010000000000000009, "Episodes": 7, "EndOfEpisod": true, "CurrenteEpisodRewardSum": 0, "EpisodRewardsSum": 2.0, "AverageEpisodReturn": 1.25, "AverageDiscountedepisodReturn": 0.005029232425410911, "TDError2": 0.26086518276146503, "TotalFramesNumber": 106494}
